{"text": "Sokolowski, H Moriah and Fias, Wim and Bosah Ononye, Chuka and Ansari, Daniel\nNeuropsychologia, 2017\n\n# Title\n\nAre numbers grounded in a general magnitude processing system? A functional neuroimaging meta-analysis.\n\n# Keywords\n\nFunctional magnetic resonance imaging\nNeural specialization\nNon-numerical magnitude\nNonsymbolic\nNumerical magnitude\nSymbolic\n\n# Abstract\nIt is currently debated whether numbers are processed using a number-specific system or a general magnitude processing system, also used for non-numerical magnitudes such as physical size, duration, or luminance. Activation likelihood estimation (ALE) was used to conduct the first quantitative meta-analysis of 93 empirical neuroimaging papers examining neural activation during numerical and non-numerical magnitude processing. Foci were compiled to generate probabilistic maps of activation for non-numerical magnitudes (e.g. physical size), symbolic numerical magnitudes (e.g. Arabic digits), and nonsymbolic numerical magnitudes (e.g. dot arrays). Conjunction analyses revealed overlapping activation for symbolic, nonsymbolic and non-numerical magnitudes in frontal and parietal lobes. Contrast analyses revealed specific activation in the left superior parietal lobule for symbolic numerical magnitudes. In contrast, small regions in the bilateral precuneus were specifically activated for nonsymbolic numerical magnitudes. No regions in the parietal lobes were activated for non-numerical magnitudes that were not also activated for numerical magnitudes. Therefore, numbers are processed using both a generalized magnitude system and format specific number regions. ", "metadata": {"id": 28119003, "text_md5": "6e5abd7853d3943a90a10e77c10d2232", "field_positions": {"authors": [0, 77], "journal": [78, 94], "publication_year": [96, 100], "title": [111, 214], "keywords": [228, 352], "abstract": [365, 1639], "body": [1648, 1648]}, "batch": 2, "pmid": 28119003, "doi": "10.1016/j.neuropsychologia.2017.01.019", "pmid_url": "https://pubmed.ncbi.nlm.nih.gov/28119003/", "efetch_url": "https://eutils.ncbi.nlm.nih.gov/entrez/eutils/efetch.fcgi?db=pubmed&id=28119003"}, "display_title": "pmid: <a href=\"https://pubmed.ncbi.nlm.nih.gov/28119003/\">28119003</a>", "list_title": "PMID28119003  Are numbers grounded in a general magnitude processing system? A functional neuroimaging meta-analysis."}
{"text": "Sokolowski, H Moriah and Fias, Wim and Bosah Ononye, Chuka and Ansari, Daniel\nNeuropsychologia, 2018\n\n# Title\n\nAre numbers grounded in a general magnitude processing system? A functional neuroimaging meta-analysis.\n\n# Keywords\n\nFunctional magnetic resonance imaging \nNeural specialization \nNon-numerical magnitude \nNonsymbolic \nNumerical magnitude \nSymbolic \n\n\n# Abstract\n\nIt is currently debated whether numbers are processed using a number-specific system or a general magnitude processing system, also used for non-numerical magnitudes such as physical size, duration, or luminance. Activation likelihood estimation (ALE) was used to conduct the first quantitative meta-analysis of 93 empirical neuroimaging papers examining neural activation during numerical and non-numerical magnitude processing. Foci were compiled to generate probabilistic maps of activation for non-numerical magnitudes (e.g. physical size), symbolic numerical magnitudes (e.g. Arabic digits), and nonsymbolic numerical magnitudes (e.g. dot arrays). Conjunction analyses revealed overlapping activation for symbolic, nonsymbolic and non-numerical magnitudes in frontal and parietal lobes. Contrast analyses revealed specific activation in the left superior parietal lobule for symbolic numerical magnitudes. In contrast, small regions in the bilateral precuneus were specifically activated for nonsymbolic numerical magnitudes. No regions in the parietal lobes were activated for non-numerical magnitudes that were not also activated for numerical magnitudes. Therefore, numbers are processed using both a generalized magnitude system and format specific number regions. \n", "metadata": {"pmid": "28119003", "journal": "Neuropsychologia", "publication_year": "2018", "title": "Are numbers grounded in a general magnitude processing system? A functional neuroimaging meta-analysis.", "keywords": "Functional magnetic resonance imaging \nNeural specialization \nNon-numerical magnitude \nNonsymbolic \nNumerical magnitude \nSymbolic \n", "abstract": "It is currently debated whether numbers are processed using a number-specific system or a general magnitude processing system, also used for non-numerical magnitudes such as physical size, duration, or luminance. Activation likelihood estimation (ALE) was used to conduct the first quantitative meta-analysis of 93 empirical neuroimaging papers examining neural activation during numerical and non-numerical magnitude processing. Foci were compiled to generate probabilistic maps of activation for non-numerical magnitudes (e.g. physical size), symbolic numerical magnitudes (e.g. Arabic digits), and nonsymbolic numerical magnitudes (e.g. dot arrays). Conjunction analyses revealed overlapping activation for symbolic, nonsymbolic and non-numerical magnitudes in frontal and parietal lobes. Contrast analyses revealed specific activation in the left superior parietal lobule for symbolic numerical magnitudes. In contrast, small regions in the bilateral precuneus were specifically activated for nonsymbolic numerical magnitudes. No regions in the parietal lobes were activated for non-numerical magnitudes that were not also activated for numerical magnitudes. Therefore, numbers are processed using both a generalized magnitude system and format specific number regions. ", "authors": "Sokolowski, H Moriah and Fias, Wim and Bosah Ononye, Chuka and Ansari, Daniel"}, "display_title": "pmid: <a href=\"https://pubmed.ncbi.nlm.nih.gov/28119003\">28119003</a>", "list_title": "PMID28119003 Are numbers grounded in a general magnitude processing system? A functional neuroimaging meta-analysis."}
