{"text": "Fouragnan, Elsa and Retzler, Chris and Philiastides, Marios G\nHum Brain Mapp, 2018\n\n# Title\n\nSeparate neural representations of prediction error valence and surprise: Evidence from an fMRI meta-analysis.\n\n# Keywords\n\ndecision making\nlearning\nmeta-analysis\nprediction error\nreward\n\n# Abstract\nLearning occurs when an outcome differs from expectations, generating a reward prediction error signal (RPE). The RPE signal has been hypothesized to simultaneously embody the valence of an outcome (better or worse than expected) and its surprise (how far from expectations). Nonetheless, growing evidence suggests that separate representations of the two RPE components exist in the human brain. Meta-analyses provide an opportunity to test this hypothesis and directly probe the extent to which the valence and surprise of the error signal are encoded in separate or overlapping networks. We carried out several meta-analyses on a large set of fMRI studies investigating the neural basis of RPE, locked at decision outcome. We identified two valence learning systems by pooling studies searching for differential neural activity in response to categorical positive-versus-negative outcomes. The first valence network (negative\u2009>\u2009positive) involved areas regulating alertness and switching behaviours such as the midcingulate cortex, the thalamus and the dorsolateral prefrontal cortex whereas the second valence network (positive\u2009>\u2009negative) encompassed regions of the human reward circuitry such as the ventral striatum and the ventromedial prefrontal cortex. We also found evidence of a largely distinct surprise-encoding network including the anterior cingulate cortex, anterior insula and dorsal striatum. Together with recent animal and electrophysiological evidence this meta-analysis points to a sequential and distributed encoding of different components of the RPE signal, with potentially distinct functional roles. ", "metadata": {"id": 29575249, "text_md5": "6ac0f5e9480f7768f730f78331e9db39", "field_positions": {"authors": [0, 61], "journal": [62, 76], "publication_year": [78, 82], "title": [93, 203], "keywords": [217, 279], "abstract": [292, 1920], "body": [1929, 1929]}, "batch": 1, "pmid": 29575249, "doi": "10.1002/hbm.24047", "pmid_url": "https://pubmed.ncbi.nlm.nih.gov/29575249/", "efetch_url": "https://eutils.ncbi.nlm.nih.gov/entrez/eutils/efetch.fcgi?db=pubmed&id=29575249"}, "display_title": "pmid: <a href=\"https://pubmed.ncbi.nlm.nih.gov/29575249/\">29575249</a>", "list_title": "PMID29575249  Separate neural representations of prediction error valence and surprise: Evidence from an fMRI meta-analysis."}
{"text": "Fouragnan, Elsa and Retzler, Chris and Philiastides, Marios G\nHuman brain mapping, 2019\n\n# Title\n\nSeparate neural representations of prediction error valence and surprise: Evidence from an fMRI meta-analysis.\n\n# Keywords\n\ndecision making \nlearning \nmeta-analysis \nprediction error \nreward \n\n\n# Abstract\n\nLearning occurs when an outcome differs from expectations, generating a reward prediction error signal (RPE). The RPE signal has been hypothesized to simultaneously embody the valence of an outcome (better or worse than expected) and its surprise (how far from expectations). Nonetheless, growing evidence suggests that separate representations of the two RPE components exist in the human brain. Meta-analyses provide an opportunity to test this hypothesis and directly probe the extent to which the valence and surprise of the error signal are encoded in separate or overlapping networks. We carried out several meta-analyses on a large set of fMRI studies investigating the neural basis of RPE, locked at decision outcome. We identified two valence learning systems by pooling studies searching for differential neural activity in response to categorical positive-versus-negative outcomes. The first valence network (negative\u2009>\u2009positive) involved areas regulating alertness and switching behaviours such as the midcingulate cortex, the thalamus and the dorsolateral prefrontal cortex whereas the second valence network (positive\u2009>\u2009negative) encompassed regions of the human reward circuitry such as the ventral striatum and the ventromedial prefrontal cortex. We also found evidence of a largely distinct surprise-encoding network including the anterior cingulate cortex, anterior insula and dorsal striatum. Together with recent animal and electrophysiological evidence this meta-analysis points to a sequential and distributed encoding of different components of the RPE signal, with potentially distinct functional roles. \n", "metadata": {"pmid": "29575249", "journal": "Human brain mapping", "publication_year": "2019", "title": "Separate neural representations of prediction error valence and surprise: Evidence from an fMRI meta-analysis.", "keywords": "decision making \nlearning \nmeta-analysis \nprediction error \nreward \n", "abstract": "Learning occurs when an outcome differs from expectations, generating a reward prediction error signal (RPE). The RPE signal has been hypothesized to simultaneously embody the valence of an outcome (better or worse than expected) and its surprise (how far from expectations). Nonetheless, growing evidence suggests that separate representations of the two RPE components exist in the human brain. Meta-analyses provide an opportunity to test this hypothesis and directly probe the extent to which the valence and surprise of the error signal are encoded in separate or overlapping networks. We carried out several meta-analyses on a large set of fMRI studies investigating the neural basis of RPE, locked at decision outcome. We identified two valence learning systems by pooling studies searching for differential neural activity in response to categorical positive-versus-negative outcomes. The first valence network (negative\u2009>\u2009positive) involved areas regulating alertness and switching behaviours such as the midcingulate cortex, the thalamus and the dorsolateral prefrontal cortex whereas the second valence network (positive\u2009>\u2009negative) encompassed regions of the human reward circuitry such as the ventral striatum and the ventromedial prefrontal cortex. We also found evidence of a largely distinct surprise-encoding network including the anterior cingulate cortex, anterior insula and dorsal striatum. Together with recent animal and electrophysiological evidence this meta-analysis points to a sequential and distributed encoding of different components of the RPE signal, with potentially distinct functional roles. ", "authors": "Fouragnan, Elsa and Retzler, Chris and Philiastides, Marios G"}, "display_title": "pmid: <a href=\"https://pubmed.ncbi.nlm.nih.gov/29575249\">29575249</a>", "list_title": "PMID29575249 Separate neural representations of prediction error valence and surprise: Evidence from an fMRI meta-analysis."}
