{"text": "Han, Hyemin and Park, Joonsuk\nCogn Neurosci, 2019\n\n# Title\n\nBayesian meta-analysis of fMRI image data.\n\n# Keywords\n\n-value\nBayes factors\nBayesian inference\nBayesian random-effect meta-analysis\nfMRI\nmeta-analysis\n\n# Abstract\nWe composed an R-based script for Image-based Bayesian random-effect meta-analysis of previous fMRI studies. It meta-analyzes second-level test results of the studies and calculates Bayes Factors indicating whether the effect in each voxel is significantly different from zero. We compared results from Bayesian and classical meta-analyses by examining the overlap between the result from each method and that created by NeuroSynth as the target. As an example, we analyzed previous fMRI studies focusing on working memory extracted from NeuroSynth. The result from our Bayesian method showed a greater overlap than the classical method. In addition, Bayes Factors proved a better way to examine whether the evidence supported hypotheses than p-values. Given these, Bayesian meta-analysis provides neuroscientists with an alternative meta-analysis method for fMRI studies given the improved overlap with the NeuroSynth result and the practical and epistemological value of Bayes Factors that can directly test the presence of an effect. ", "metadata": {"id": 30663513, "text_md5": "2981f5c6c91d7f130a9261f925554ff6", "field_positions": {"authors": [0, 29], "journal": [30, 43], "publication_year": [45, 49], "title": [60, 102], "keywords": [116, 211], "abstract": [224, 1261], "body": [1270, 1270]}, "batch": 4, "pmid": 30663513, "doi": "10.1080/17588928.2019.1570103", "pmid_url": "https://pubmed.ncbi.nlm.nih.gov/30663513/", "efetch_url": "https://eutils.ncbi.nlm.nih.gov/entrez/eutils/efetch.fcgi?db=pubmed&id=30663513"}, "display_title": "pmid: <a href=\"https://pubmed.ncbi.nlm.nih.gov/30663513/\">30663513</a>", "list_title": "PMID30663513  Bayesian meta-analysis of fMRI image data."}
{"text": "Han, Hyemin and Park, Joonsuk\nCognitive neuroscience, 2019\n\n# Title\n\nBayesian meta-analysis of fMRI image data.\n\n# Keywords\n\n-value \nBayes factors \nBayesian inference \nBayesian random-effect meta-analysis \nfMRI \nmeta-analysis \n\n\n# Abstract\n\nWe composed an R-based script for Image-based Bayesian random-effect meta-analysis of previous fMRI studies. It meta-analyzes second-level test results of the studies and calculates Bayes Factors indicating whether the effect in each voxel is significantly different from zero. We compared results from Bayesian and classical meta-analyses by examining the overlap between the result from each method and that created by NeuroSynth as the target. As an example, we analyzed previous fMRI studies focusing on working memory extracted from NeuroSynth. The result from our Bayesian method showed a greater overlap than the classical method. In addition, Bayes Factors proved a better way to examine whether the evidence supported hypotheses than p-values. Given these, Bayesian meta-analysis provides neuroscientists with an alternative meta-analysis method for fMRI studies given the improved overlap with the NeuroSynth result and the practical and epistemological value of Bayes Factors that can directly test the presence of an effect. \n", "metadata": {"pmid": "30663513", "journal": "Cognitive neuroscience", "publication_year": "2019", "title": "Bayesian meta-analysis of fMRI image data.", "keywords": "-value \nBayes factors \nBayesian inference \nBayesian random-effect meta-analysis \nfMRI \nmeta-analysis \n", "abstract": "We composed an R-based script for Image-based Bayesian random-effect meta-analysis of previous fMRI studies. It meta-analyzes second-level test results of the studies and calculates Bayes Factors indicating whether the effect in each voxel is significantly different from zero. We compared results from Bayesian and classical meta-analyses by examining the overlap between the result from each method and that created by NeuroSynth as the target. As an example, we analyzed previous fMRI studies focusing on working memory extracted from NeuroSynth. The result from our Bayesian method showed a greater overlap than the classical method. In addition, Bayes Factors proved a better way to examine whether the evidence supported hypotheses than p-values. Given these, Bayesian meta-analysis provides neuroscientists with an alternative meta-analysis method for fMRI studies given the improved overlap with the NeuroSynth result and the practical and epistemological value of Bayes Factors that can directly test the presence of an effect. ", "authors": "Han, Hyemin and Park, Joonsuk"}, "display_title": "pmid: <a href=\"https://pubmed.ncbi.nlm.nih.gov/30663513\">30663513</a>", "list_title": "PMID30663513 Bayesian meta-analysis of fMRI image data."}
