{"text": "Daigle, Katrina M and Pietrzykowski, Malvina O and Waters, Abigail B and Swenson, Lance P and Gansler, David A\nJ Neuropsychiatry Clin Neurosci, 2022\n\n# Title\n\nCentral Executive Network and Executive Function in Patients With Alzheimer's Disease and Healthy Individuals: Meta-Analysis of Structural and Functional MRI.\n\n# Keywords\n\nAlzheimer\u2019s Disease\nCentral Executive Network\nExecutive Function\nMRI\nfMRI\nrsfcMRI\n\n# Abstract\nThe neural architecture of executive function is of interest given its utility as a transdiagnostic predictor of adaptive functioning. However, a gap exists in the meta-analytic literature assessing this relationship in neuropsychiatric populations, concordance between structural and functional architecture, and the relationship with neuropsychological assessment of executive function. Given the importance of the central executive network (CEN) in Alzheimer's disease, this population may be useful in understanding this relationship in Alzheimer's disease pathology. A meta-analysis of studies ( Analyses revealed a positive brain-behavior relationship ( Structural and functional imaging in the CEN are predictive of executive function performance among patients with Alzheimer's disease and HCs. Regardless of how the CEN is affected, behavior is correlated to the degree to which the CEN is affected. Findings are significant in the context of methodological decisions in multimodal neuroimaging research. ", "metadata": {"id": 35272491, "text_md5": "09c48be733cba510233cf6e92d4265ff", "field_positions": {"authors": [0, 110], "journal": [111, 142], "publication_year": [144, 148], "title": [159, 317], "keywords": [331, 412], "abstract": [425, 1439], "body": [1448, 1448]}, "batch": 2, "pmid": 35272491, "doi": "10.1176/appi.neuropsych.20110279", "pmid_url": "https://pubmed.ncbi.nlm.nih.gov/35272491/", "efetch_url": "https://eutils.ncbi.nlm.nih.gov/entrez/eutils/efetch.fcgi?db=pubmed&id=35272491"}, "display_title": "pmid: <a href=\"https://pubmed.ncbi.nlm.nih.gov/35272491/\">35272491</a>", "list_title": "PMID35272491  Central Executive Network and Executive Function in Patients With Alzheimer's Disease and Healthy Individuals: Meta-Analysis of Structural and Functional MRI."}
{"text": "Daigle, Katrina M and Pietrzykowski, Malvina O and Waters, Abigail B and Swenson, Lance P and Gansler, David A\nThe Journal of neuropsychiatry and clinical neurosciences, 2022\n\n# Title\n\nCentral Executive Network and Executive Function in Patients With Alzheimer's Disease and Healthy Individuals: Meta-Analysis of Structural and Functional MRI.\n\n# Keywords\n\nAlzheimer\u2019s Disease \nCentral Executive Network \nExecutive Function \nMRI \nfMRI \nrsfcMRI \n\n\n# Abstract\n\nThe neural architecture of executive function is of interest given its utility as a transdiagnostic predictor of adaptive functioning. However, a gap exists in the meta-analytic literature assessing this relationship in neuropsychiatric populations, concordance between structural and functional architecture, and the relationship with neuropsychological assessment of executive function. Given the importance of the central executive network (CEN) in Alzheimer's disease, this population may be useful in understanding this relationship in Alzheimer's disease pathology. A meta-analysis of studies ( Analyses revealed a positive brain-behavior relationship ( Structural and functional imaging in the CEN are predictive of executive function performance among patients with Alzheimer's disease and HCs. Regardless of how the CEN is affected, behavior is correlated to the degree to which the CEN is affected. Findings are significant in the context of methodological decisions in multimodal neuroimaging research. \n", "metadata": {"pmid": "35272491", "journal": "The Journal of neuropsychiatry and clinical neurosciences", "publication_year": "2022", "title": "Central Executive Network and Executive Function in Patients With Alzheimer's Disease and Healthy Individuals: Meta-Analysis of Structural and Functional MRI.", "keywords": "Alzheimer\u2019s Disease \nCentral Executive Network \nExecutive Function \nMRI \nfMRI \nrsfcMRI \n", "abstract": "The neural architecture of executive function is of interest given its utility as a transdiagnostic predictor of adaptive functioning. However, a gap exists in the meta-analytic literature assessing this relationship in neuropsychiatric populations, concordance between structural and functional architecture, and the relationship with neuropsychological assessment of executive function. Given the importance of the central executive network (CEN) in Alzheimer's disease, this population may be useful in understanding this relationship in Alzheimer's disease pathology. A meta-analysis of studies ( Analyses revealed a positive brain-behavior relationship ( Structural and functional imaging in the CEN are predictive of executive function performance among patients with Alzheimer's disease and HCs. Regardless of how the CEN is affected, behavior is correlated to the degree to which the CEN is affected. Findings are significant in the context of methodological decisions in multimodal neuroimaging research. ", "authors": "Daigle, Katrina M and Pietrzykowski, Malvina O and Waters, Abigail B and Swenson, Lance P and Gansler, David A"}, "display_title": "pmid: <a href=\"https://pubmed.ncbi.nlm.nih.gov/35272491\">35272491</a>", "list_title": "PMID35272491 Central Executive Network and Executive Function in Patients With Alzheimer's Disease and Healthy Individuals: Meta-Analysis of Structural and Functional MRI."}
