{"text": "Yu, Junhong and Tao, Qian and Zhang, Ruibin and Chan, Chetwyn C H and Lee, Tatia M C\nNeurosci Biobehav Rev, 2019\n\n# Title\n\nCan fMRI discriminate between deception and false memory? A meta-analytic comparison between deception and false memory studies.\n\n# Keywords\n\nDeception\nfMRI\nfalse memory\nmeta-analysis\n\n# Abstract\nPrevious research has highlighted the potential of fMRI in discriminating between truth and falsehood. However, falsehoods may not necessarily represent a deliberate intention to deceive; they can be a result of false memory too. It is important to show that fMRI can discriminate between deception and false memory, before it can be applied in legal contexts for deception detection. To this end, we performed a meta-analytic comparison of brain activation between deception and false memory. Activation likelihood estimation meta-analyses were conducted separately on 49 deception (61 contrasts; N ", "metadata": {"id": 31251965, "text_md5": "d5ef6fb30638efc40c2121a995cc6e24", "field_positions": {"authors": [0, 84], "journal": [85, 106], "publication_year": [108, 112], "title": [123, 251], "keywords": [265, 306], "abstract": [319, 919], "body": [928, 928]}, "batch": 3, "pmid": 31251965, "doi": "10.1016/j.neubiorev.2019.06.027", "pmid_url": "https://pubmed.ncbi.nlm.nih.gov/31251965/", "efetch_url": "https://eutils.ncbi.nlm.nih.gov/entrez/eutils/efetch.fcgi?db=pubmed&id=31251965"}, "display_title": "pmid: <a href=\"https://pubmed.ncbi.nlm.nih.gov/31251965/\">31251965</a>", "list_title": "PMID31251965  Can fMRI discriminate between deception and false memory? A meta-analytic comparison between deception and false memory studies."}
{"text": "Yu, Junhong and Tao, Qian and Zhang, Ruibin and Chan, Chetwyn C H and Lee, Tatia M C\nNeuroscience and biobehavioral reviews, 2020\n\n# Title\n\nCan fMRI discriminate between deception and false memory? A meta-analytic comparison between deception and false memory studies.\n\n# Keywords\n\nDeception \nfMRI \nfalse memory \nmeta-analysis \n\n\n# Abstract\n\nPrevious research has highlighted the potential of fMRI in discriminating between truth and falsehood. However, falsehoods may not necessarily represent a deliberate intention to deceive; they can be a result of false memory too. It is important to show that fMRI can discriminate between deception and false memory, before it can be applied in legal contexts for deception detection. To this end, we performed a meta-analytic comparison of brain activation between deception and false memory. Activation likelihood estimation meta-analyses were conducted separately on 49 deception (61 contrasts; N \n", "metadata": {"pmid": "31251965", "journal": "Neuroscience and biobehavioral reviews", "publication_year": "2020", "title": "Can fMRI discriminate between deception and false memory? A meta-analytic comparison between deception and false memory studies.", "keywords": "Deception \nfMRI \nfalse memory \nmeta-analysis \n", "abstract": "Previous research has highlighted the potential of fMRI in discriminating between truth and falsehood. However, falsehoods may not necessarily represent a deliberate intention to deceive; they can be a result of false memory too. It is important to show that fMRI can discriminate between deception and false memory, before it can be applied in legal contexts for deception detection. To this end, we performed a meta-analytic comparison of brain activation between deception and false memory. Activation likelihood estimation meta-analyses were conducted separately on 49 deception (61 contrasts; N ", "authors": "Yu, Junhong and Tao, Qian and Zhang, Ruibin and Chan, Chetwyn C H and Lee, Tatia M C"}, "display_title": "pmid: <a href=\"https://pubmed.ncbi.nlm.nih.gov/31251965\">31251965</a>", "list_title": "PMID31251965 Can fMRI discriminate between deception and false memory? A meta-analytic comparison between deception and false memory studies."}
