{"text": "Schrammen, Elisabeth and Roesmann, Kati and Rosenbaum, David and Redlich, Ronny and Harenbrock, Jana and Dannlowski, Udo and Leehr, Elisabeth J\nNeurosci Biobehav Rev, 2022\n\n# Title\n\nFunctional neural changes associated with psychotherapy in anxiety disorders - A meta-analysis of longitudinal fMRI studies.\n\n# Keywords\n\nAnxiety disorders\nMeta-analysis\nPsychotherapy\nTask-based fMRI\n\n# Abstract\nSuccessful psychotherapy for anxiety disorders is thought to be linked to functional neural changes in prefrontal control areas and fear-related limbic regions. Thus, discovering such therapy-associated neural changes might point to relevant mechanisms of action. Using AES-SDM, we conducted a coordinate-based meta-analysis of 22 whole-brain datasets (n\u00a0=\u00a0419 anxiety patients) from 18 studies identified by our systematic literature search following PRISMA criteria (preregistration available at OSF: https://osf.io/dgc4p). In these studies, fMRI data was collected in response to negative stimuli during cognitive-emotional tasks before and after psychotherapy. Post-psychotherapy, activation decreased in the right insula, the anterior cingulate cortex, and the dorsolateral prefrontal cortex; no region had increased activation. A subgroup analysis for CBT revealed additional decrease in the supplementary motor area. Reduced activation in limbic and frontal regions might indicate therapy-associated normalization regarding the perception of internal and external threat, subsequent allocation of cognitive resources, and changes in cognitive control. Due to the integration of diverse treatments and experimental tasks, these changes presumably reflect global effects of successful psychotherapy. ", "metadata": {"id": 36179918, "text_md5": "e9510d86219c6cb2bf969f88907e9543", "field_positions": {"authors": [0, 143], "journal": [144, 165], "publication_year": [167, 171], "title": [182, 306], "keywords": [320, 381], "abstract": [394, 1699], "body": [1708, 1708]}, "batch": 3, "pmid": 36179918, "doi": "10.1016/j.neubiorev.2022.104895", "pmid_url": "https://pubmed.ncbi.nlm.nih.gov/36179918/", "efetch_url": "https://eutils.ncbi.nlm.nih.gov/entrez/eutils/efetch.fcgi?db=pubmed&id=36179918"}, "display_title": "pmid: <a href=\"https://pubmed.ncbi.nlm.nih.gov/36179918/\">36179918</a>", "list_title": "PMID36179918  Functional neural changes associated with psychotherapy in anxiety disorders - A meta-analysis of longitudinal fMRI studies."}
{"text": "Schrammen, Elisabeth and Roesmann, Kati and Rosenbaum, David and Redlich, Ronny and Harenbrock, Jana and Dannlowski, Udo and Leehr, Elisabeth J\nNeuroscience and biobehavioral reviews, 2022\n\n# Title\n\nFunctional neural changes associated with psychotherapy in anxiety disorders - A meta-analysis of longitudinal fMRI studies.\n\n# Keywords\n\nAnxiety disorders \nMeta-analysis \nPsychotherapy \nTask-based fMRI \n\n\n# Abstract\n\nSuccessful psychotherapy for anxiety disorders is thought to be linked to functional neural changes in prefrontal control areas and fear-related limbic regions. Thus, discovering such therapy-associated neural changes might point to relevant mechanisms of action. Using AES-SDM, we conducted a coordinate-based meta-analysis of 22 whole-brain datasets (n\u00a0=\u00a0419 anxiety patients) from 18 studies identified by our systematic literature search following PRISMA criteria (preregistration available at OSF: https://osf.io/dgc4p). In these studies, fMRI data was collected in response to negative stimuli during cognitive-emotional tasks before and after psychotherapy. Post-psychotherapy, activation decreased in the right insula, the anterior cingulate cortex, and the dorsolateral prefrontal cortex; no region had increased activation. A subgroup analysis for CBT revealed additional decrease in the supplementary motor area. Reduced activation in limbic and frontal regions might indicate therapy-associated normalization regarding the perception of internal and external threat, subsequent allocation of cognitive resources, and changes in cognitive control. Due to the integration of diverse treatments and experimental tasks, these changes presumably reflect global effects of successful psychotherapy. \n", "metadata": {"pmid": "36179918", "journal": "Neuroscience and biobehavioral reviews", "publication_year": "2022", "title": "Functional neural changes associated with psychotherapy in anxiety disorders - A meta-analysis of longitudinal fMRI studies.", "keywords": "Anxiety disorders \nMeta-analysis \nPsychotherapy \nTask-based fMRI \n", "abstract": "Successful psychotherapy for anxiety disorders is thought to be linked to functional neural changes in prefrontal control areas and fear-related limbic regions. Thus, discovering such therapy-associated neural changes might point to relevant mechanisms of action. Using AES-SDM, we conducted a coordinate-based meta-analysis of 22 whole-brain datasets (n\u00a0=\u00a0419 anxiety patients) from 18 studies identified by our systematic literature search following PRISMA criteria (preregistration available at OSF: https://osf.io/dgc4p). In these studies, fMRI data was collected in response to negative stimuli during cognitive-emotional tasks before and after psychotherapy. Post-psychotherapy, activation decreased in the right insula, the anterior cingulate cortex, and the dorsolateral prefrontal cortex; no region had increased activation. A subgroup analysis for CBT revealed additional decrease in the supplementary motor area. Reduced activation in limbic and frontal regions might indicate therapy-associated normalization regarding the perception of internal and external threat, subsequent allocation of cognitive resources, and changes in cognitive control. Due to the integration of diverse treatments and experimental tasks, these changes presumably reflect global effects of successful psychotherapy. ", "authors": "Schrammen, Elisabeth and Roesmann, Kati and Rosenbaum, David and Redlich, Ronny and Harenbrock, Jana and Dannlowski, Udo and Leehr, Elisabeth J"}, "display_title": "pmid: <a href=\"https://pubmed.ncbi.nlm.nih.gov/36179918\">36179918</a>", "list_title": "PMID36179918 Functional neural changes associated with psychotherapy in anxiety disorders - A meta-analysis of longitudinal fMRI studies."}
