{"text": "Yeo, Darren J and Wilkey, Eric D and Price, Gavin R\nNeurosci Biobehav Rev, 2017\n\n# Title\n\nThe search for the number form area: A functional neuroimaging meta-analysis.\n\n# Keywords\n\nActivation likelihood estimation\nFrontal cortex\nInferior temporal gyrus\nMeta-analysis\nNumber form\nParietal cortex\nSymbolic number\n\n# Abstract\nRecent studies report a putative \"number form area\" (NFA) in the inferior temporal gyrus (ITG) suggested to be specialized for Arabic numeral processing. However, a number of earlier studies report no such NFA. The reasons for such discrepancies across studies are unclear. To examine evidence for a convergent NFA across studies, we conducted two activation likelihood estimation meta-analyses on 31 and a subset of 20 neuroimaging studies that have contrasted digits with other meaningful symbols. Results suggest the potential existence of an NFA in the right ITG, in addition to a 'symbolic number processing network' comprising bilateral parietal regions, and right-lateralized superior and inferior frontal regions. Critically, convergent localization for the NFA was only evident when contrasts were appropriately controlled for task demands, and does not appear to depend on employing methods designed to overcome fMRI signal dropout in the ITG. Importantly, only five studies had foci within the identified ITG NFA cluster boundary, indicating that more empirical evidence is necessary to determine the true functional specialization and regional specificity of the putative NFA. ", "metadata": {"id": 28467892, "text_md5": "860560ed7113e537ad1a137678754520", "field_positions": {"authors": [0, 51], "journal": [52, 73], "publication_year": [75, 79], "title": [90, 167], "keywords": [181, 310], "abstract": [323, 1512], "body": [1521, 1521]}, "batch": 3, "pmid": 28467892, "doi": "10.1016/j.neubiorev.2017.04.027", "pmid_url": "https://pubmed.ncbi.nlm.nih.gov/28467892/", "efetch_url": "https://eutils.ncbi.nlm.nih.gov/entrez/eutils/efetch.fcgi?db=pubmed&id=28467892"}, "display_title": "pmid: <a href=\"https://pubmed.ncbi.nlm.nih.gov/28467892/\">28467892</a>", "list_title": "PMID28467892  The search for the number form area: A functional neuroimaging meta-analysis."}
{"text": "Yeo, Darren J and Wilkey, Eric D and Price, Gavin R\nNeuroscience and biobehavioral reviews, 2017\n\n# Title\n\nThe search for the number form area: A functional neuroimaging meta-analysis.\n\n# Keywords\n\nActivation likelihood estimation \nFrontal cortex \nInferior temporal gyrus \nMeta-analysis \nNumber form \nParietal cortex \nSymbolic number \n\n\n# Abstract\n\nRecent studies report a putative \"number form area\" (NFA) in the inferior temporal gyrus (ITG) suggested to be specialized for Arabic numeral processing. However, a number of earlier studies report no such NFA. The reasons for such discrepancies across studies are unclear. To examine evidence for a convergent NFA across studies, we conducted two activation likelihood estimation meta-analyses on 31 and a subset of 20 neuroimaging studies that have contrasted digits with other meaningful symbols. Results suggest the potential existence of an NFA in the right ITG, in addition to a 'symbolic number processing network' comprising bilateral parietal regions, and right-lateralized superior and inferior frontal regions. Critically, convergent localization for the NFA was only evident when contrasts were appropriately controlled for task demands, and does not appear to depend on employing methods designed to overcome fMRI signal dropout in the ITG. Importantly, only five studies had foci within the identified ITG NFA cluster boundary, indicating that more empirical evidence is necessary to determine the true functional specialization and regional specificity of the putative NFA. \n", "metadata": {"pmid": "28467892", "journal": "Neuroscience and biobehavioral reviews", "publication_year": "2017", "title": "The search for the number form area: A functional neuroimaging meta-analysis.", "keywords": "Activation likelihood estimation \nFrontal cortex \nInferior temporal gyrus \nMeta-analysis \nNumber form \nParietal cortex \nSymbolic number \n", "abstract": "Recent studies report a putative \"number form area\" (NFA) in the inferior temporal gyrus (ITG) suggested to be specialized for Arabic numeral processing. However, a number of earlier studies report no such NFA. The reasons for such discrepancies across studies are unclear. To examine evidence for a convergent NFA across studies, we conducted two activation likelihood estimation meta-analyses on 31 and a subset of 20 neuroimaging studies that have contrasted digits with other meaningful symbols. Results suggest the potential existence of an NFA in the right ITG, in addition to a 'symbolic number processing network' comprising bilateral parietal regions, and right-lateralized superior and inferior frontal regions. Critically, convergent localization for the NFA was only evident when contrasts were appropriately controlled for task demands, and does not appear to depend on employing methods designed to overcome fMRI signal dropout in the ITG. Importantly, only five studies had foci within the identified ITG NFA cluster boundary, indicating that more empirical evidence is necessary to determine the true functional specialization and regional specificity of the putative NFA. ", "authors": "Yeo, Darren J and Wilkey, Eric D and Price, Gavin R"}, "display_title": "pmid: <a href=\"https://pubmed.ncbi.nlm.nih.gov/28467892\">28467892</a>", "list_title": "PMID28467892 The search for the number form area: A functional neuroimaging meta-analysis."}
