{"text": "Scheliga, Sebastian and Kellermann, Thilo and Lampert, Angelika and Rolke, Roman and Spehr, Marc and Habel, Ute\nRev Neurosci, 2023\n\n# Title\n\nNeural correlates of multisensory integration in the human brain: an ALE meta-analysis.\n\n# Keywords\n\nALE meta-analysis\nMACM analysis\nfMRI\nmultisensory integration\nmultisensory integration network\n\n# Abstract\nPrevious fMRI research identified superior temporal sulcus as central integration area for audiovisual stimuli. However, less is known about a general multisensory integration network across senses. Therefore, we conducted activation likelihood estimation meta-analysis with multiple sensory modalities to identify a common brain network. We included 49 studies covering all Aristotelian senses i.e.,\u00a0auditory, visual, tactile, gustatory, and olfactory stimuli. Analysis revealed significant activation in bilateral superior temporal gyrus, middle temporal gyrus, thalamus, right insula, and left\u00a0inferior frontal gyrus. We assume these regions to be part\u00a0of a general multisensory integration network comprising different functional roles. Here, thalamus operate as first subcortical relay projecting sensory information to higher cortical integration centers in superior temporal gyrus/sulcus while conflict-processing brain regions as insula and inferior frontal gyrus facilitate integration of incongruent information. We additionally performed meta-analytic connectivity modelling and found each brain region showed co-activations within the\u00a0identified multisensory integration network. Therefore, by including multiple sensory modalities in our meta-analysis the results may provide evidence for a common brain network that supports different functional roles for multisensory integration. ", "metadata": {"id": 36084305, "text_md5": "a0c8c913f7afc0dddbf98b4267e69c41", "field_positions": {"authors": [0, 111], "journal": [112, 124], "publication_year": [126, 130], "title": [141, 228], "keywords": [242, 336], "abstract": [349, 1745], "body": [1754, 1754]}, "batch": 2, "pmid": 36084305, "doi": "10.1515/revneuro-2022-0065", "pmid_url": "https://pubmed.ncbi.nlm.nih.gov/36084305/", "efetch_url": "https://eutils.ncbi.nlm.nih.gov/entrez/eutils/efetch.fcgi?db=pubmed&id=36084305"}, "display_title": "pmid: <a href=\"https://pubmed.ncbi.nlm.nih.gov/36084305/\">36084305</a>", "list_title": "PMID36084305  Neural correlates of multisensory integration in the human brain: an ALE meta-analysis."}
{"text": "Scheliga, Sebastian and Kellermann, Thilo and Lampert, Angelika and Rolke, Roman and Spehr, Marc and Habel, Ute\nReviews in the neurosciences, 2023\n\n# Title\n\nNeural correlates of multisensory integration in the human brain: an ALE meta-analysis.\n\n# Keywords\n\nALE meta-analysis \nMACM analysis \nfMRI \nmultisensory integration \nmultisensory integration network \n\n\n# Abstract\n\nPrevious fMRI research identified superior temporal sulcus as central integration area for audiovisual stimuli. However, less is known about a general multisensory integration network across senses. Therefore, we conducted activation likelihood estimation meta-analysis with multiple sensory modalities to identify a common brain network. We included 49 studies covering all Aristotelian senses i.e.,\u00a0auditory, visual, tactile, gustatory, and olfactory stimuli. Analysis revealed significant activation in bilateral superior temporal gyrus, middle temporal gyrus, thalamus, right insula, and left\u00a0inferior frontal gyrus. We assume these regions to be part\u00a0of a general multisensory integration network comprising different functional roles. Here, thalamus operate as first subcortical relay projecting sensory information to higher cortical integration centers in superior temporal gyrus/sulcus while conflict-processing brain regions as insula and inferior frontal gyrus facilitate integration of incongruent information. We additionally performed meta-analytic connectivity modelling and found each brain region showed co-activations within the\u00a0identified multisensory integration network. Therefore, by including multiple sensory modalities in our meta-analysis the results may provide evidence for a common brain network that supports different functional roles for multisensory integration. \n", "metadata": {"pmid": "36084305", "journal": "Reviews in the neurosciences", "publication_year": "2023", "title": "Neural correlates of multisensory integration in the human brain: an ALE meta-analysis.", "keywords": "ALE meta-analysis \nMACM analysis \nfMRI \nmultisensory integration \nmultisensory integration network \n", "abstract": "Previous fMRI research identified superior temporal sulcus as central integration area for audiovisual stimuli. However, less is known about a general multisensory integration network across senses. Therefore, we conducted activation likelihood estimation meta-analysis with multiple sensory modalities to identify a common brain network. We included 49 studies covering all Aristotelian senses i.e.,\u00a0auditory, visual, tactile, gustatory, and olfactory stimuli. Analysis revealed significant activation in bilateral superior temporal gyrus, middle temporal gyrus, thalamus, right insula, and left\u00a0inferior frontal gyrus. We assume these regions to be part\u00a0of a general multisensory integration network comprising different functional roles. Here, thalamus operate as first subcortical relay projecting sensory information to higher cortical integration centers in superior temporal gyrus/sulcus while conflict-processing brain regions as insula and inferior frontal gyrus facilitate integration of incongruent information. We additionally performed meta-analytic connectivity modelling and found each brain region showed co-activations within the\u00a0identified multisensory integration network. Therefore, by including multiple sensory modalities in our meta-analysis the results may provide evidence for a common brain network that supports different functional roles for multisensory integration. ", "authors": "Scheliga, Sebastian and Kellermann, Thilo and Lampert, Angelika and Rolke, Roman and Spehr, Marc and Habel, Ute"}, "display_title": "pmid: <a href=\"https://pubmed.ncbi.nlm.nih.gov/36084305\">36084305</a>", "list_title": "PMID36084305 Neural correlates of multisensory integration in the human brain: an ALE meta-analysis."}
