{"text": "Dugr\u00e9, Jules R and Dumais, Alexandre and Bitar, Nathalie and Potvin, St\u00e9phane\nPeerJ, 2018\n\n# Title\n\nLoss anticipation and outcome during the \n\n# Keywords\n\nLoss avoidance\nMeta-analysis\nMonetary Incentive Delay Task\nPunishment\nfMRI\n\n# Abstract\nReward seeking and avoidance of punishment are key motivational processes. Brain-imaging studies often use the  All functional neuro-imaging studies using the MIDT in healthy controls were retrieved using PubMed, Google Scholar & EMBASE databases. Functional neuro-imaging data was analyzed using the Seed-based d Mapping Software. Thirty-five studies met the inclusion criteria, comprising 699 healthy adults. In both anticipation and loss outcome phases, participants showed large and robust activations in the bilateral striatum, (anterior) insula, and anterior cingulate gyrus relatively to Loss > Neutral contrast. Although relatively similar activation patterns were observed during the two event types, they differed in the pattern of prefrontal activations: ventro-lateral prefrontal activations were observed during loss anticipation, while medial prefrontal activations were observed during loss receipt. Considering that previous meta-analyses highlighted activations in the medial prefrontal cortex/anterior cingulate cortex, the anterior insula and the ventral striatum, the current meta-analysis highlighted the potential specificity of the ventro-lateral prefrontal regions, the median cingulate cortex and the amygdala in the loss events. Future studies can rely on these latter results to examine the neural correlates of loss processing in psychiatric populations characterized by harm avoidance or insensitivity to punishment. ", "metadata": {"id": 29761060, "text_md5": "c4e9c7e3df87f9a97912c4227d92fab5", "field_positions": {"authors": [0, 77], "journal": [78, 83], "publication_year": [85, 89], "title": [100, 141], "keywords": [155, 229], "abstract": [242, 1688], "body": [1697, 1697]}, "batch": 3, "pmid": 29761060, "doi": "10.7717/peerj.4749", "pmid_url": "https://pubmed.ncbi.nlm.nih.gov/29761060/", "efetch_url": "https://eutils.ncbi.nlm.nih.gov/entrez/eutils/efetch.fcgi?db=pubmed&id=29761060"}, "display_title": "pmid: <a href=\"https://pubmed.ncbi.nlm.nih.gov/29761060/\">29761060</a>", "list_title": "PMID29761060  Loss anticipation and outcome during the "}
{"text": "Dugr\u00e9, Jules R and Dumais, Alexandre and Bitar, Nathalie and Potvin, St\u00e9phane\nPeerJ, 2022\n\n# Title\n\nLoss anticipation and outcome during the \n\n# Keywords\n\nLoss avoidance \nMeta-analysis \nMonetary Incentive Delay Task \nPunishment \nfMRI \n\n\n# Abstract\n\nReward seeking and avoidance of punishment are key motivational processes. Brain-imaging studies often use the  All functional neuro-imaging studies using the MIDT in healthy controls were retrieved using PubMed, Google Scholar & EMBASE databases. Functional neuro-imaging data was analyzed using the Seed-based d Mapping Software. Thirty-five studies met the inclusion criteria, comprising 699 healthy adults. In both anticipation and loss outcome phases, participants showed large and robust activations in the bilateral striatum, (anterior) insula, and anterior cingulate gyrus relatively to Loss > Neutral contrast. Although relatively similar activation patterns were observed during the two event types, they differed in the pattern of prefrontal activations: ventro-lateral prefrontal activations were observed during loss anticipation, while medial prefrontal activations were observed during loss receipt. Considering that previous meta-analyses highlighted activations in the medial prefrontal cortex/anterior cingulate cortex, the anterior insula and the ventral striatum, the current meta-analysis highlighted the potential specificity of the ventro-lateral prefrontal regions, the median cingulate cortex and the amygdala in the loss events. Future studies can rely on these latter results to examine the neural correlates of loss processing in psychiatric populations characterized by harm avoidance or insensitivity to punishment. \n", "metadata": {"pmid": "29761060", "journal": "PeerJ", "publication_year": "2022", "title": "Loss anticipation and outcome during the ", "keywords": "Loss avoidance \nMeta-analysis \nMonetary Incentive Delay Task \nPunishment \nfMRI \n", "abstract": "Reward seeking and avoidance of punishment are key motivational processes. Brain-imaging studies often use the  All functional neuro-imaging studies using the MIDT in healthy controls were retrieved using PubMed, Google Scholar & EMBASE databases. Functional neuro-imaging data was analyzed using the Seed-based d Mapping Software. Thirty-five studies met the inclusion criteria, comprising 699 healthy adults. In both anticipation and loss outcome phases, participants showed large and robust activations in the bilateral striatum, (anterior) insula, and anterior cingulate gyrus relatively to Loss > Neutral contrast. Although relatively similar activation patterns were observed during the two event types, they differed in the pattern of prefrontal activations: ventro-lateral prefrontal activations were observed during loss anticipation, while medial prefrontal activations were observed during loss receipt. Considering that previous meta-analyses highlighted activations in the medial prefrontal cortex/anterior cingulate cortex, the anterior insula and the ventral striatum, the current meta-analysis highlighted the potential specificity of the ventro-lateral prefrontal regions, the median cingulate cortex and the amygdala in the loss events. Future studies can rely on these latter results to examine the neural correlates of loss processing in psychiatric populations characterized by harm avoidance or insensitivity to punishment. ", "authors": "Dugr\u00e9, Jules R and Dumais, Alexandre and Bitar, Nathalie and Potvin, St\u00e9phane"}, "display_title": "pmid: <a href=\"https://pubmed.ncbi.nlm.nih.gov/29761060\">29761060</a>", "list_title": "PMID29761060 Loss anticipation and outcome during the "}
