{"text": "Sacheli, Lucia Maria and Tomasetig, Giulia and Musco, Margherita Adelaide and Pizzi, Stefano and Bottini, Gabriella and Pizzamiglio, Luigi and Paulesu, Eraldo\nNeurosci Biobehav Rev, 2022\n\n# Title\n\nThe unexplored link between aesthetic perception and creativity: A theory-driven meta-analysis of fMRI studies in the visual domain.\n\n# Keywords\n\nAesthetic experience\nCreativity\nFMRI\nInhibition\nMeta-analysis\nMotor cognition\nVisual\n\n# Abstract\nCreative production (related to art-making) and aesthetic appreciation (related to art-viewing) are inherently linked in visual arts, but their relationship has never been explored explicitly in cognitive neuroscience, nor the nature of such connection. The available literature suggests two cognitive processes as possible foundations of these two experiences: motor simulation or inhibitory control. In a meta-analysis of fMRI studies, we addressed this issue: we investigated whether there are shared neurofunctional underpinnings behind aesthetic and creative experiences in the visual domain; further, we examined whether any shared brain activation may reflect either motor simulation or inhibitory processes. A conjunction analysis revealed a common involvement of the pre-SMA in both classes of studies, a brain region, if anything, more concerned with top-down inhibitory motor and volitional cognitive control rather than bottom-up motor simulation. In the art-viewing domain, this finding was primarily driven by figurative rather than abstract art. The methodological limitations in the available literature are discussed together with possible new ways to expand the existing findings. ", "metadata": {"id": 35798126, "text_md5": "50d1930a7be011b1ef24b10ab50ef761", "field_positions": {"authors": [0, 158], "journal": [159, 180], "publication_year": [182, 186], "title": [197, 329], "keywords": [343, 427], "abstract": [440, 1639], "body": [1648, 1648]}, "batch": 2, "pmid": 35798126, "doi": "10.1016/j.neubiorev.2022.104768", "pmid_url": "https://pubmed.ncbi.nlm.nih.gov/35798126/", "efetch_url": "https://eutils.ncbi.nlm.nih.gov/entrez/eutils/efetch.fcgi?db=pubmed&id=35798126"}, "display_title": "pmid: <a href=\"https://pubmed.ncbi.nlm.nih.gov/35798126/\">35798126</a>", "list_title": "PMID35798126  The unexplored link between aesthetic perception and creativity: A theory-driven meta-analysis of fMRI studies in the visual domain."}
{"text": "Sacheli, Lucia Maria and Tomasetig, Giulia and Musco, Margherita Adelaide and Pizzi, Stefano and Bottini, Gabriella and Pizzamiglio, Luigi and Paulesu, Eraldo\nNeuroscience and biobehavioral reviews, 2022\n\n# Title\n\nThe unexplored link between aesthetic perception and creativity: A theory-driven meta-analysis of fMRI studies in the visual domain.\n\n# Keywords\n\nAesthetic experience \nCreativity \nFMRI \nInhibition \nMeta-analysis \nMotor cognition \nVisual \n\n\n# Abstract\n\nCreative production (related to art-making) and aesthetic appreciation (related to art-viewing) are inherently linked in visual arts, but their relationship has never been explored explicitly in cognitive neuroscience, nor the nature of such connection. The available literature suggests two cognitive processes as possible foundations of these two experiences: motor simulation or inhibitory control. In a meta-analysis of fMRI studies, we addressed this issue: we investigated whether there are shared neurofunctional underpinnings behind aesthetic and creative experiences in the visual domain; further, we examined whether any shared brain activation may reflect either motor simulation or inhibitory processes. A conjunction analysis revealed a common involvement of the pre-SMA in both classes of studies, a brain region, if anything, more concerned with top-down inhibitory motor and volitional cognitive control rather than bottom-up motor simulation. In the art-viewing domain, this finding was primarily driven by figurative rather than abstract art. The methodological limitations in the available literature are discussed together with possible new ways to expand the existing findings. \n", "metadata": {"pmid": "35798126", "journal": "Neuroscience and biobehavioral reviews", "publication_year": "2022", "title": "The unexplored link between aesthetic perception and creativity: A theory-driven meta-analysis of fMRI studies in the visual domain.", "keywords": "Aesthetic experience \nCreativity \nFMRI \nInhibition \nMeta-analysis \nMotor cognition \nVisual \n", "abstract": "Creative production (related to art-making) and aesthetic appreciation (related to art-viewing) are inherently linked in visual arts, but their relationship has never been explored explicitly in cognitive neuroscience, nor the nature of such connection. The available literature suggests two cognitive processes as possible foundations of these two experiences: motor simulation or inhibitory control. In a meta-analysis of fMRI studies, we addressed this issue: we investigated whether there are shared neurofunctional underpinnings behind aesthetic and creative experiences in the visual domain; further, we examined whether any shared brain activation may reflect either motor simulation or inhibitory processes. A conjunction analysis revealed a common involvement of the pre-SMA in both classes of studies, a brain region, if anything, more concerned with top-down inhibitory motor and volitional cognitive control rather than bottom-up motor simulation. In the art-viewing domain, this finding was primarily driven by figurative rather than abstract art. The methodological limitations in the available literature are discussed together with possible new ways to expand the existing findings. ", "authors": "Sacheli, Lucia Maria and Tomasetig, Giulia and Musco, Margherita Adelaide and Pizzi, Stefano and Bottini, Gabriella and Pizzamiglio, Luigi and Paulesu, Eraldo"}, "display_title": "pmid: <a href=\"https://pubmed.ncbi.nlm.nih.gov/35798126\">35798126</a>", "list_title": "PMID35798126 The unexplored link between aesthetic perception and creativity: A theory-driven meta-analysis of fMRI studies in the visual domain."}
