{"text": "Hill, Ashley C and Laird, Angela R and Robinson, Jennifer L\nBiol Psychol, 2014\n\n# Title\n\nGender differences in working memory networks: a BrainMap meta-analysis.\n\n# Keywords\n\nBrainMap\nGender differences\nSex differences\nWorking memory\nfMRI\n\n# Abstract\nGender differences in psychological processes have been of great interest in a variety of fields. While the majority of research in this area has focused on specific differences in relation to test performance, this study sought to determine the underlying neurofunctional differences observed during working memory, a pivotal cognitive process shown to be predictive of academic achievement and intelligence. Using the BrainMap database, we performed a meta-analysis and applied activation likelihood estimation to our search set. Our results demonstrate consistent working memory networks across genders, but also provide evidence for gender-specific networks whereby females consistently activate more limbic (e.g., amygdala and hippocampus) and prefrontal structures (e.g., right inferior frontal gyrus), and males activate a distributed network inclusive of more parietal regions. These data provide a framework for future investigations using functional or effective connectivity methods to elucidate the underpinnings of gender differences in neural network recruitment during working memory tasks. ", "metadata": {"id": 25042764, "text_md5": "939852754c84a07797a158e8c576a338", "field_positions": {"authors": [0, 59], "journal": [60, 72], "publication_year": [74, 78], "title": [89, 161], "keywords": [175, 238], "abstract": [251, 1357], "body": [1366, 1366]}, "batch": 3, "pmid": 25042764, "doi": "10.1016/j.biopsycho.2014.06.008", "pmid_url": "https://pubmed.ncbi.nlm.nih.gov/25042764/", "efetch_url": "https://eutils.ncbi.nlm.nih.gov/entrez/eutils/efetch.fcgi?db=pubmed&id=25042764"}, "display_title": "pmid: <a href=\"https://pubmed.ncbi.nlm.nih.gov/25042764/\">25042764</a>", "list_title": "PMID25042764  Gender differences in working memory networks: a BrainMap meta-analysis."}
{"text": "Hill, Ashley C and Laird, Angela R and Robinson, Jennifer L\nBiological psychology, 2015\n\n# Title\n\nGender differences in working memory networks: a BrainMap meta-analysis.\n\n# Keywords\n\nBrainMap \nGender differences \nSex differences \nWorking memory \nfMRI \n\n\n# Abstract\n\nGender differences in psychological processes have been of great interest in a variety of fields. While the majority of research in this area has focused on specific differences in relation to test performance, this study sought to determine the underlying neurofunctional differences observed during working memory, a pivotal cognitive process shown to be predictive of academic achievement and intelligence. Using the BrainMap database, we performed a meta-analysis and applied activation likelihood estimation to our search set. Our results demonstrate consistent working memory networks across genders, but also provide evidence for gender-specific networks whereby females consistently activate more limbic (e.g., amygdala and hippocampus) and prefrontal structures (e.g., right inferior frontal gyrus), and males activate a distributed network inclusive of more parietal regions. These data provide a framework for future investigations using functional or effective connectivity methods to elucidate the underpinnings of gender differences in neural network recruitment during working memory tasks. \n", "metadata": {"pmid": "25042764", "journal": "Biological psychology", "publication_year": "2015", "title": "Gender differences in working memory networks: a BrainMap meta-analysis.", "keywords": "BrainMap \nGender differences \nSex differences \nWorking memory \nfMRI \n", "abstract": "Gender differences in psychological processes have been of great interest in a variety of fields. While the majority of research in this area has focused on specific differences in relation to test performance, this study sought to determine the underlying neurofunctional differences observed during working memory, a pivotal cognitive process shown to be predictive of academic achievement and intelligence. Using the BrainMap database, we performed a meta-analysis and applied activation likelihood estimation to our search set. Our results demonstrate consistent working memory networks across genders, but also provide evidence for gender-specific networks whereby females consistently activate more limbic (e.g., amygdala and hippocampus) and prefrontal structures (e.g., right inferior frontal gyrus), and males activate a distributed network inclusive of more parietal regions. These data provide a framework for future investigations using functional or effective connectivity methods to elucidate the underpinnings of gender differences in neural network recruitment during working memory tasks. ", "authors": "Hill, Ashley C and Laird, Angela R and Robinson, Jennifer L"}, "display_title": "pmid: <a href=\"https://pubmed.ncbi.nlm.nih.gov/25042764\">25042764</a>", "list_title": "PMID25042764 Gender differences in working memory networks: a BrainMap meta-analysis."}
