{"text": "Caras, Andrew and Mugge, Luke and Miller, William Kyle and Mansour, Tarek R and Schroeder, Jason and Medhkour, Azedine\nWorld Neurosurg, 2020\n\n# Title\n\nUsefulness and Impact of Intraoperative Imaging for Glioma Resection on Patient Outcome and Extent of Resection: A Systematic Review and Meta-Analysis.\n\n# Keywords\n\nExtent of resection\nGlioma resection\nIntraoperative imaging\nQuality of life\n\n# Abstract\nDiffusion tensor imaging (DTI), functional magnetic resonance imaging (fMRI), and intraoperative magnetic resonance imaging (iMRI) permit greater visualization and more accurate presurgical planning. Meta-analysis of these techniques for maximizing resection, postoperative functionality, and survival may further validate purported strengths of these techniques compared with standard neuronavigation. A systematic search of the PubMed database was conducted in line with the PRISMA guidelines for meta-analysis with the following keywords: \"Diffusion tensor imaging\" OR \"intraoperative MRI\" OR \"functional MRI\" AND \"glioma surgery resection outcome.\" Articles found to meet inclusion criteria were segregated and analyzed and resulting data were compared with standard neuronavigation (control cohort). A total of 435 articles were identified, with 29 distinct studies meeting inclusion criteria, including DTI (n\u00a0= 3), fMRI (n\u00a0= 5), and iMRI (n\u00a0= 21). Nine studies directly compared results with standard navigation. Mean gross total resection (GTR) rates were not different among cases using DTI, fMRI, iMRI, or traditional neuronavigation (P\u00a0= 0.136). On controlling for covariates, more patients received GTR in the advanced imaging cohort, although statistically insignificant (46.5% [95% confidence interval, 38.0%-55.0%] vs. 30.4% [95% confidence interval, 11.6%-49.1%]; P\u00a0= 0.127; partial \u03b7 Current data are overall insufficient to support the notion that advanced imaging techniques are superior, either as a combined cohort or individually, in achieving GTR, improved symptom resolution, or survival compared with traditional neuronavigation. ", "metadata": {"id": 31639502, "text_md5": "559665fe43be62d73578f37babcd88f9", "field_positions": {"authors": [0, 118], "journal": [119, 134], "publication_year": [136, 140], "title": [151, 302], "keywords": [316, 391], "abstract": [404, 2059], "body": [2068, 2068]}, "batch": 1, "pmid": 31639502, "doi": "10.1016/j.wneu.2019.10.072", "pmid_url": "https://pubmed.ncbi.nlm.nih.gov/31639502/", "efetch_url": "https://eutils.ncbi.nlm.nih.gov/entrez/eutils/efetch.fcgi?db=pubmed&id=31639502"}, "display_title": "pmid: <a href=\"https://pubmed.ncbi.nlm.nih.gov/31639502/\">31639502</a>", "list_title": "PMID31639502  Usefulness and Impact of Intraoperative Imaging for Glioma Resection on Patient Outcome and Extent of Resection: A Systematic Review and Meta-Analysis."}
{"text": "Caras, Andrew and Mugge, Luke and Miller, William Kyle and Mansour, Tarek R and Schroeder, Jason and Medhkour, Azedine\nWorld neurosurgery, 2020\n\n# Title\n\nUsefulness and Impact of Intraoperative Imaging for Glioma Resection on Patient Outcome and Extent of Resection: A Systematic Review and Meta-Analysis.\n\n# Keywords\n\nExtent of resection \nGlioma resection \nIntraoperative imaging \nQuality of life \n\n\n# Abstract\n\nDiffusion tensor imaging (DTI), functional magnetic resonance imaging (fMRI), and intraoperative magnetic resonance imaging (iMRI) permit greater visualization and more accurate presurgical planning. Meta-analysis of these techniques for maximizing resection, postoperative functionality, and survival may further validate purported strengths of these techniques compared with standard neuronavigation. A systematic search of the PubMed database was conducted in line with the PRISMA guidelines for meta-analysis with the following keywords: \"Diffusion tensor imaging\" OR \"intraoperative MRI\" OR \"functional MRI\" AND \"glioma surgery resection outcome.\" Articles found to meet inclusion criteria were segregated and analyzed and resulting data were compared with standard neuronavigation (control cohort). A total of 435 articles were identified, with 29 distinct studies meeting inclusion criteria, including DTI (n\u00a0= 3), fMRI (n\u00a0= 5), and iMRI (n\u00a0= 21). Nine studies directly compared results with standard navigation. Mean gross total resection (GTR) rates were not different among cases using DTI, fMRI, iMRI, or traditional neuronavigation (P\u00a0= 0.136). On controlling for covariates, more patients received GTR in the advanced imaging cohort, although statistically insignificant (46.5% [95% confidence interval, 38.0%-55.0%] vs. 30.4% [95% confidence interval, 11.6%-49.1%]; P\u00a0= 0.127; partial \u03b7 Current data are overall insufficient to support the notion that advanced imaging techniques are superior, either as a combined cohort or individually, in achieving GTR, improved symptom resolution, or survival compared with traditional neuronavigation. \n", "metadata": {"pmid": "31639502", "journal": "World neurosurgery", "publication_year": "2020", "title": "Usefulness and Impact of Intraoperative Imaging for Glioma Resection on Patient Outcome and Extent of Resection: A Systematic Review and Meta-Analysis.", "keywords": "Extent of resection \nGlioma resection \nIntraoperative imaging \nQuality of life \n", "abstract": "Diffusion tensor imaging (DTI), functional magnetic resonance imaging (fMRI), and intraoperative magnetic resonance imaging (iMRI) permit greater visualization and more accurate presurgical planning. Meta-analysis of these techniques for maximizing resection, postoperative functionality, and survival may further validate purported strengths of these techniques compared with standard neuronavigation. A systematic search of the PubMed database was conducted in line with the PRISMA guidelines for meta-analysis with the following keywords: \"Diffusion tensor imaging\" OR \"intraoperative MRI\" OR \"functional MRI\" AND \"glioma surgery resection outcome.\" Articles found to meet inclusion criteria were segregated and analyzed and resulting data were compared with standard neuronavigation (control cohort). A total of 435 articles were identified, with 29 distinct studies meeting inclusion criteria, including DTI (n\u00a0= 3), fMRI (n\u00a0= 5), and iMRI (n\u00a0= 21). Nine studies directly compared results with standard navigation. Mean gross total resection (GTR) rates were not different among cases using DTI, fMRI, iMRI, or traditional neuronavigation (P\u00a0= 0.136). On controlling for covariates, more patients received GTR in the advanced imaging cohort, although statistically insignificant (46.5% [95% confidence interval, 38.0%-55.0%] vs. 30.4% [95% confidence interval, 11.6%-49.1%]; P\u00a0= 0.127; partial \u03b7 Current data are overall insufficient to support the notion that advanced imaging techniques are superior, either as a combined cohort or individually, in achieving GTR, improved symptom resolution, or survival compared with traditional neuronavigation. ", "authors": "Caras, Andrew and Mugge, Luke and Miller, William Kyle and Mansour, Tarek R and Schroeder, Jason and Medhkour, Azedine"}, "display_title": "pmid: <a href=\"https://pubmed.ncbi.nlm.nih.gov/31639502\">31639502</a>", "list_title": "PMID31639502 Usefulness and Impact of Intraoperative Imaging for Glioma Resection on Patient Outcome and Extent of Resection: A Systematic Review and Meta-Analysis."}
