{"text": "Gu\u00e0rdia-Olmos, Joan and Per\u00f3-Cebollero, Maribel and Gudayol-Ferr\u00e9, Esteve\nFrontiers in behavioral neuroscience, 2020\n\n# Title\n\nMeta-Analysis of the Structural Equation Models' Parameters for the Estimation of Brain Connectivity with \n\n# Keywords\n\ncognitive neuroscience \neffective connectivity \nfMRI \nfunctional connectivity \nstructural equation models \n\n\n# Abstract\n\nStructural Equation Models (SEM) is among of the most extensively applied statistical techniques in the study of human behavior in the fields of Neuroscience and Cognitive Neuroscience. This paper reviews the application of SEM to estimate functional and effective connectivity models in work published since 2001. The articles analyzed were compiled from Journal Citation Reports, PsycInfo, Pubmed, and Scopus, after searching with the following keywords: fMRI, SEMs, and Connectivity.  \n", "metadata": {"pmid": "29497368", "journal": "Frontiers in behavioral neuroscience", "publication_year": "2020", "title": "Meta-Analysis of the Structural Equation Models' Parameters for the Estimation of Brain Connectivity with ", "keywords": "cognitive neuroscience \neffective connectivity \nfMRI \nfunctional connectivity \nstructural equation models \n", "abstract": "Structural Equation Models (SEM) is among of the most extensively applied statistical techniques in the study of human behavior in the fields of Neuroscience and Cognitive Neuroscience. This paper reviews the application of SEM to estimate functional and effective connectivity models in work published since 2001. The articles analyzed were compiled from Journal Citation Reports, PsycInfo, Pubmed, and Scopus, after searching with the following keywords: fMRI, SEMs, and Connectivity.  ", "authors": "Gu\u00e0rdia-Olmos, Joan and Per\u00f3-Cebollero, Maribel and Gudayol-Ferr\u00e9, Esteve"}, "display_title": "pmid: <a href=\"https://pubmed.ncbi.nlm.nih.gov/29497368\">29497368</a>", "list_title": "PMID29497368 Meta-Analysis of the Structural Equation Models' Parameters for the Estimation of Brain Connectivity with "}
