{"text": "Zhang, Sirui and Lin, Junyu and Cheng, Yangfan and Hou, Yanbin and Shang, Huifang\nFront Neurol, 2023\n\n# Title\n\nAberrant resting-state brain activity in Huntington's disease: A voxel-based meta-analysis.\n\n# Keywords\n\nHuntington's disease\nfunctional magnetic resonance imaging\nmeta-analysis\npsychoradiology\nresting-state\n\n# Abstract\nFunctional neuroimaging could provide abundant information of underling pathophysiological mechanisms of the clinical triad including motor, cognitive and psychiatric impairment in Huntington's Disease (HD). We performed a voxel-based meta-analysis using anisotropic effect size-signed differential mapping (AES-SDM) method. 6 studies (78 symptomatic HD, 102 premanifest HD and 131 healthy controls) were included in total. Altered resting-state brain activity was primarily detected in the bilateral medial part of superior frontal gyrus, bilateral anterior cingulate/paracingulate gyrus, left insula, left striatum, right cortico-spinal projections area, right inferior temporal gyrus area, right thalamus, right cerebellum and right gyrus rectus area. Premanifest and symptomatic HD patients showed different alterative pattern in the subgroup analyses. The robust and consistent abnormalities in the specific brain regions identified in the current study could help to understand the pathophysiology of HD and explore reliable neuroimaging biomarkers for monitoring disease progression, or even predicting the onset of premanifest HD patients. ", "metadata": {"id": 37064205, "text_md5": "6dce1826ef4ba726540d9e9a6261c9af", "field_positions": {"authors": [0, 81], "journal": [82, 94], "publication_year": [96, 100], "title": [111, 202], "keywords": [216, 318], "abstract": [331, 1479], "body": [1488, 1488]}, "batch": 3, "pmid": 37064205, "doi": "10.3389/fneur.2023.1124158", "pmid_url": "https://pubmed.ncbi.nlm.nih.gov/37064205/", "efetch_url": "https://eutils.ncbi.nlm.nih.gov/entrez/eutils/efetch.fcgi?db=pubmed&id=37064205"}, "display_title": "pmid: <a href=\"https://pubmed.ncbi.nlm.nih.gov/37064205/\">37064205</a>", "list_title": "PMID37064205  Aberrant resting-state brain activity in Huntington's disease: A voxel-based meta-analysis."}
{"text": "Zhang, Sirui and Lin, Junyu and Cheng, Yangfan and Hou, Yanbin and Shang, Huifang\nFrontiers in neurology, 2023\n\n# Title\n\nAberrant resting-state brain activity in Huntington's disease: A voxel-based meta-analysis.\n\n# Keywords\n\nHuntington's disease \nfunctional magnetic resonance imaging \nmeta-analysis \npsychoradiology \nresting-state \n\n\n# Abstract\n\nFunctional neuroimaging could provide abundant information of underling pathophysiological mechanisms of the clinical triad including motor, cognitive and psychiatric impairment in Huntington's Disease (HD). We performed a voxel-based meta-analysis using anisotropic effect size-signed differential mapping (AES-SDM) method. 6 studies (78 symptomatic HD, 102 premanifest HD and 131 healthy controls) were included in total. Altered resting-state brain activity was primarily detected in the bilateral medial part of superior frontal gyrus, bilateral anterior cingulate/paracingulate gyrus, left insula, left striatum, right cortico-spinal projections area, right inferior temporal gyrus area, right thalamus, right cerebellum and right gyrus rectus area. Premanifest and symptomatic HD patients showed different alterative pattern in the subgroup analyses. The robust and consistent abnormalities in the specific brain regions identified in the current study could help to understand the pathophysiology of HD and explore reliable neuroimaging biomarkers for monitoring disease progression, or even predicting the onset of premanifest HD patients. \n", "metadata": {"pmid": "37064205", "journal": "Frontiers in neurology", "publication_year": "2023", "title": "Aberrant resting-state brain activity in Huntington's disease: A voxel-based meta-analysis.", "keywords": "Huntington's disease \nfunctional magnetic resonance imaging \nmeta-analysis \npsychoradiology \nresting-state \n", "abstract": "Functional neuroimaging could provide abundant information of underling pathophysiological mechanisms of the clinical triad including motor, cognitive and psychiatric impairment in Huntington's Disease (HD). We performed a voxel-based meta-analysis using anisotropic effect size-signed differential mapping (AES-SDM) method. 6 studies (78 symptomatic HD, 102 premanifest HD and 131 healthy controls) were included in total. Altered resting-state brain activity was primarily detected in the bilateral medial part of superior frontal gyrus, bilateral anterior cingulate/paracingulate gyrus, left insula, left striatum, right cortico-spinal projections area, right inferior temporal gyrus area, right thalamus, right cerebellum and right gyrus rectus area. Premanifest and symptomatic HD patients showed different alterative pattern in the subgroup analyses. The robust and consistent abnormalities in the specific brain regions identified in the current study could help to understand the pathophysiology of HD and explore reliable neuroimaging biomarkers for monitoring disease progression, or even predicting the onset of premanifest HD patients. ", "authors": "Zhang, Sirui and Lin, Junyu and Cheng, Yangfan and Hou, Yanbin and Shang, Huifang"}, "display_title": "pmid: <a href=\"https://pubmed.ncbi.nlm.nih.gov/37064205\">37064205</a>", "list_title": "PMID37064205 Aberrant resting-state brain activity in Huntington's disease: A voxel-based meta-analysis."}
