{"text": "Vucurovic, Ksenija and Caillies, St\u00e9phanie and Kaladjian, Arthur\nFront Psychiatry, 2021\n\n# Title\n\nNeural Correlates of Mentalizing in Individuals With Clinical High Risk for Schizophrenia: ALE Meta-Analysis.\n\n# Keywords\n\nfMRI\npsychosis proneness\nschizophrenia\nsocial cognition\ntheory of mind\n\n# Abstract\nPsychotic disorder refers to a spectrum of disorders that have multiple etiologies, due to the complex interaction of biological and genetic vulnerability with familial and cultural factors. A clinical high risk (CHR) for schizophrenia is defined as the presence of brief, attenuated, or intermittent psychotic symptoms in non-schizophrenic individuals. The transition to schizophrenia appears significantly more frequent in this at-risk population than in the general population. Moreover, the ability to attribute mental states to others, known as mentalizing or theory of mind, and its neural correlates found in individuals with CHR are similar to those described in patients with schizophrenia. We have therefore explored neurofunctional correlates of mentalizing in individuals with CHR vs. healthy controls, in order to identify the differences in brain activation. A neural coordinate-based activation likelihood estimation meta-analysis of existing neuroimaging data revealed that three regions displayed decreased activation in individuals with CHR, compared with healthy controls: the right temporoparietal junction, the right middle temporal gyrus, and the left precuneus. These results, combined with those in the literature, further support the hypothesis that abnormal activation of posterior brain regions involved in mentalizing correlates with psychotic symptoms in help-seeking individuals. ", "metadata": {"id": 33959048, "text_md5": "c304fb791c7a5642df377ba5abee2730", "field_positions": {"authors": [0, 64], "journal": [65, 81], "publication_year": [83, 87], "title": [98, 207], "keywords": [221, 291], "abstract": [304, 1714], "body": [1723, 1723]}, "batch": 3, "pmid": 33959048, "doi": "10.3389/fpsyt.2021.634015", "pmid_url": "https://pubmed.ncbi.nlm.nih.gov/33959048/", "efetch_url": "https://eutils.ncbi.nlm.nih.gov/entrez/eutils/efetch.fcgi?db=pubmed&id=33959048"}, "display_title": "pmid: <a href=\"https://pubmed.ncbi.nlm.nih.gov/33959048/\">33959048</a>", "list_title": "PMID33959048  Neural Correlates of Mentalizing in Individuals With Clinical High Risk for Schizophrenia: ALE Meta-Analysis."}
{"text": "Vucurovic, Ksenija and Caillies, St\u00e9phanie and Kaladjian, Arthur\nFrontiers in psychiatry, 2021\n\n# Title\n\nNeural Correlates of Mentalizing in Individuals With Clinical High Risk for Schizophrenia: ALE Meta-Analysis.\n\n# Keywords\n\nfMRI \npsychosis proneness \nschizophrenia \nsocial cognition \ntheory of mind \n\n\n# Abstract\n\nPsychotic disorder refers to a spectrum of disorders that have multiple etiologies, due to the complex interaction of biological and genetic vulnerability with familial and cultural factors. A clinical high risk (CHR) for schizophrenia is defined as the presence of brief, attenuated, or intermittent psychotic symptoms in non-schizophrenic individuals. The transition to schizophrenia appears significantly more frequent in this at-risk population than in the general population. Moreover, the ability to attribute mental states to others, known as mentalizing or theory of mind, and its neural correlates found in individuals with CHR are similar to those described in patients with schizophrenia. We have therefore explored neurofunctional correlates of mentalizing in individuals with CHR vs. healthy controls, in order to identify the differences in brain activation. A neural coordinate-based activation likelihood estimation meta-analysis of existing neuroimaging data revealed that three regions displayed decreased activation in individuals with CHR, compared with healthy controls: the right temporoparietal junction, the right middle temporal gyrus, and the left precuneus. These results, combined with those in the literature, further support the hypothesis that abnormal activation of posterior brain regions involved in mentalizing correlates with psychotic symptoms in help-seeking individuals. \n", "metadata": {"pmid": "33959048", "journal": "Frontiers in psychiatry", "publication_year": "2021", "title": "Neural Correlates of Mentalizing in Individuals With Clinical High Risk for Schizophrenia: ALE Meta-Analysis.", "keywords": "fMRI \npsychosis proneness \nschizophrenia \nsocial cognition \ntheory of mind \n", "abstract": "Psychotic disorder refers to a spectrum of disorders that have multiple etiologies, due to the complex interaction of biological and genetic vulnerability with familial and cultural factors. A clinical high risk (CHR) for schizophrenia is defined as the presence of brief, attenuated, or intermittent psychotic symptoms in non-schizophrenic individuals. The transition to schizophrenia appears significantly more frequent in this at-risk population than in the general population. Moreover, the ability to attribute mental states to others, known as mentalizing or theory of mind, and its neural correlates found in individuals with CHR are similar to those described in patients with schizophrenia. We have therefore explored neurofunctional correlates of mentalizing in individuals with CHR vs. healthy controls, in order to identify the differences in brain activation. A neural coordinate-based activation likelihood estimation meta-analysis of existing neuroimaging data revealed that three regions displayed decreased activation in individuals with CHR, compared with healthy controls: the right temporoparietal junction, the right middle temporal gyrus, and the left precuneus. These results, combined with those in the literature, further support the hypothesis that abnormal activation of posterior brain regions involved in mentalizing correlates with psychotic symptoms in help-seeking individuals. ", "authors": "Vucurovic, Ksenija and Caillies, St\u00e9phanie and Kaladjian, Arthur"}, "display_title": "pmid: <a href=\"https://pubmed.ncbi.nlm.nih.gov/33959048\">33959048</a>", "list_title": "PMID33959048 Neural Correlates of Mentalizing in Individuals With Clinical High Risk for Schizophrenia: ALE Meta-Analysis."}
