{"text": "Kim, Jeffrey J and Cunnington, Ross and Kirby, James N\nNeurosci Biobehav Rev, 2020\n\n# Title\n\nThe neurophysiological basis of compassion: An fMRI meta-analysis of compassion and its related neural processes.\n\n# Keywords\n\nBasal-ganglia\nCompassion\nPAG\nReview\nSalience\nfMRI\n\n# Abstract\nTheoretical and neurophysiological investigations into compassion are burgeoning, yet the putative neural mechanisms which underpin such processes are less well understood. Therefore, we have conducted an Activation-Likelihood Estimate meta-analysis in order to ascertain the shared neural processes consistently identified as relevant to compassion. Our analysis of sixteen fMRI studies revealed activation across seven broad regions, with the largest peaks localized to the Periaqueductal Grey, Anterior Insula, Anterior Cingulate, and Inferior Frontal Gyrus. Overall, we identified a tendency for studies to operationalize compassion in one of three ways, as driven either 'top-down', 'bottom-up', or modified by target context. We failed to identify regions purportedly common to compassion such as the DLPFC, OFC, and Amygdala, possibly due to a small number of studies which used Loving-Kindness meditation. We argue future research in compassion science continue a multi-modal approach to examine links between neural activity and actual prosocial behavior, and recommend the application of fMRI paradigms on compassion with clinically diagnosed populations to parallel current trends in psychotherapy such as Compassion Focused Therapy. ", "metadata": {"id": 31697955, "text_md5": "5f5f80835534262c2872c2d789e0618f", "field_positions": {"authors": [0, 54], "journal": [55, 76], "publication_year": [78, 82], "title": [93, 206], "keywords": [220, 269], "abstract": [282, 1527], "body": [1536, 1536]}, "batch": 1, "pmid": 31697955, "doi": "10.1016/j.neubiorev.2019.10.023", "pmid_url": "https://pubmed.ncbi.nlm.nih.gov/31697955/", "efetch_url": "https://eutils.ncbi.nlm.nih.gov/entrez/eutils/efetch.fcgi?db=pubmed&id=31697955"}, "display_title": "pmid: <a href=\"https://pubmed.ncbi.nlm.nih.gov/31697955/\">31697955</a>", "list_title": "PMID31697955  The neurophysiological basis of compassion: An fMRI meta-analysis of compassion and its related neural processes."}
{"text": "Kim, Jeffrey J and Cunnington, Ross and Kirby, James N\nNeuroscience and biobehavioral reviews, 2020\n\n# Title\n\nThe neurophysiological basis of compassion: An fMRI meta-analysis of compassion and its related neural processes.\n\n# Keywords\n\nBasal-ganglia \nCompassion \nPAG \nReview \nSalience \nfMRI \n\n\n# Abstract\n\nTheoretical and neurophysiological investigations into compassion are burgeoning, yet the putative neural mechanisms which underpin such processes are less well understood. Therefore, we have conducted an Activation-Likelihood Estimate meta-analysis in order to ascertain the shared neural processes consistently identified as relevant to compassion. Our analysis of sixteen fMRI studies revealed activation across seven broad regions, with the largest peaks localized to the Periaqueductal Grey, Anterior Insula, Anterior Cingulate, and Inferior Frontal Gyrus. Overall, we identified a tendency for studies to operationalize compassion in one of three ways, as driven either 'top-down', 'bottom-up', or modified by target context. We failed to identify regions purportedly common to compassion such as the DLPFC, OFC, and Amygdala, possibly due to a small number of studies which used Loving-Kindness meditation. We argue future research in compassion science continue a multi-modal approach to examine links between neural activity and actual prosocial behavior, and recommend the application of fMRI paradigms on compassion with clinically diagnosed populations to parallel current trends in psychotherapy such as Compassion Focused Therapy. \n", "metadata": {"pmid": "31697955", "journal": "Neuroscience and biobehavioral reviews", "publication_year": "2020", "title": "The neurophysiological basis of compassion: An fMRI meta-analysis of compassion and its related neural processes.", "keywords": "Basal-ganglia \nCompassion \nPAG \nReview \nSalience \nfMRI \n", "abstract": "Theoretical and neurophysiological investigations into compassion are burgeoning, yet the putative neural mechanisms which underpin such processes are less well understood. Therefore, we have conducted an Activation-Likelihood Estimate meta-analysis in order to ascertain the shared neural processes consistently identified as relevant to compassion. Our analysis of sixteen fMRI studies revealed activation across seven broad regions, with the largest peaks localized to the Periaqueductal Grey, Anterior Insula, Anterior Cingulate, and Inferior Frontal Gyrus. Overall, we identified a tendency for studies to operationalize compassion in one of three ways, as driven either 'top-down', 'bottom-up', or modified by target context. We failed to identify regions purportedly common to compassion such as the DLPFC, OFC, and Amygdala, possibly due to a small number of studies which used Loving-Kindness meditation. We argue future research in compassion science continue a multi-modal approach to examine links between neural activity and actual prosocial behavior, and recommend the application of fMRI paradigms on compassion with clinically diagnosed populations to parallel current trends in psychotherapy such as Compassion Focused Therapy. ", "authors": "Kim, Jeffrey J and Cunnington, Ross and Kirby, James N"}, "display_title": "pmid: <a href=\"https://pubmed.ncbi.nlm.nih.gov/31697955\">31697955</a>", "list_title": "PMID31697955 The neurophysiological basis of compassion: An fMRI meta-analysis of compassion and its related neural processes."}
