{"text": "Zhang, Zheng and Peng, Peng and Zhang, Delong\nJ Autism Dev Disord, 2020\n\n# Title\n\nExecutive Function in High-Functioning Autism Spectrum Disorder: A Meta-analysis of fMRI Studies.\n\n# Keywords\n\nAutism spectrum disorder\nDevelopment\nExecutive function\nFronto-parietal areas\nMeta-analysis\nUnity and diversity\n\n# Abstract\nAbnormalities in executive function (EF) are clinical markers for autism spectrum disorder (ASD). However, the neural mechanisms underlying abnormal EF in ASD remain unclear. This meta-analysis investigated the construct, abnormalities, and age-related changes of EF in ASD. Thirty-three fMRI studies of inhibition, updating, and switching in individuals with high-functioning ASD were included (n\u2009=\u20091114; age range 7-57\u00a0years). The results revealed that the EF construct in ASD could be unitary (i.e., common EF) in children/adolescents, but unitary and diverse (i.e., common EF and inhibition) in adults. Abnormalities in this EF construct were found across development in individuals with ASD in comparison with typically developing individuals. Implications and recommendations are discussed for EF theory and for practice in ASD. ", "metadata": {"id": 32200468, "text_md5": "510111e88be9bd08b69c8be221b0db3f", "field_positions": {"authors": [0, 45], "journal": [46, 65], "publication_year": [67, 71], "title": [82, 179], "keywords": [193, 304], "abstract": [317, 1152], "body": [1161, 1161]}, "batch": 1, "pmid": 32200468, "doi": "10.1007/s10803-020-04461-z", "pmid_url": "https://pubmed.ncbi.nlm.nih.gov/32200468/", "efetch_url": "https://eutils.ncbi.nlm.nih.gov/entrez/eutils/efetch.fcgi?db=pubmed&id=32200468"}, "display_title": "pmid: <a href=\"https://pubmed.ncbi.nlm.nih.gov/32200468/\">32200468</a>", "list_title": "PMID32200468  Executive Function in High-Functioning Autism Spectrum Disorder: A Meta-analysis of fMRI Studies."}
{"text": "Zhang, Zheng and Peng, Peng and Zhang, Delong\nJournal of autism and developmental disorders, 2021\n\n# Title\n\nExecutive Function in High-Functioning Autism Spectrum Disorder: A Meta-analysis of fMRI Studies.\n\n# Keywords\n\nAutism spectrum disorder \nDevelopment \nExecutive function \nFronto-parietal areas \nMeta-analysis \nUnity and diversity \n\n\n# Abstract\n\nAbnormalities in executive function (EF) are clinical markers for autism spectrum disorder (ASD). However, the neural mechanisms underlying abnormal EF in ASD remain unclear. This meta-analysis investigated the construct, abnormalities, and age-related changes of EF in ASD. Thirty-three fMRI studies of inhibition, updating, and switching in individuals with high-functioning ASD were included (n\u2009=\u20091114; age range 7-57\u00a0years). The results revealed that the EF construct in ASD could be unitary (i.e., common EF) in children/adolescents, but unitary and diverse (i.e., common EF and inhibition) in adults. Abnormalities in this EF construct were found across development in individuals with ASD in comparison with typically developing individuals. Implications and recommendations are discussed for EF theory and for practice in ASD. \n", "metadata": {"pmid": "32200468", "journal": "Journal of autism and developmental disorders", "publication_year": "2021", "title": "Executive Function in High-Functioning Autism Spectrum Disorder: A Meta-analysis of fMRI Studies.", "keywords": "Autism spectrum disorder \nDevelopment \nExecutive function \nFronto-parietal areas \nMeta-analysis \nUnity and diversity \n", "abstract": "Abnormalities in executive function (EF) are clinical markers for autism spectrum disorder (ASD). However, the neural mechanisms underlying abnormal EF in ASD remain unclear. This meta-analysis investigated the construct, abnormalities, and age-related changes of EF in ASD. Thirty-three fMRI studies of inhibition, updating, and switching in individuals with high-functioning ASD were included (n\u2009=\u20091114; age range 7-57\u00a0years). The results revealed that the EF construct in ASD could be unitary (i.e., common EF) in children/adolescents, but unitary and diverse (i.e., common EF and inhibition) in adults. Abnormalities in this EF construct were found across development in individuals with ASD in comparison with typically developing individuals. Implications and recommendations are discussed for EF theory and for practice in ASD. ", "authors": "Zhang, Zheng and Peng, Peng and Zhang, Delong"}, "display_title": "pmid: <a href=\"https://pubmed.ncbi.nlm.nih.gov/32200468\">32200468</a>", "list_title": "PMID32200468 Executive Function in High-Functioning Autism Spectrum Disorder: A Meta-analysis of fMRI Studies."}
