{"text": "Morandini, Hugo A E and Silk, Timothy J and Griffiths, Kristi and Rao, Pradeep and Hood, Sean D and Zepf, Florian D\nCortex, 2020\n\n# Title\n\nMeta-analysis of the neural correlates of vigilant attention in children and adolescents.\n\n# Keywords\n\nALE meta-analysis\nChildren and adolescents\nFunctional magnetic resonance imaging\nSustained attention\nVigilant attention\nfMRI\n\n# Abstract\nVigilant Attention (VA), defined as the ability to maintain attention to cognitively unchallenging activities over a prolonged period of time, is critical to support higher cognitive functions and many behaviours in our everyday life. Evidence has shown that VA rapidly improves throughout childhood and adolescence until young adulthood and tends to decline in older adulthood. Although neuroimaging studies have extensively investigated this cognitive function in adults, the neural correlates of VA in neurotypical children and adolescents remain unclear. The current meta-analysis reviewed and examined functional neuroimaging studies in paediatric populations that used behavioural tasks involving VA. The selected studies (N\u00a0=\u00a025) were analyzed using the activation likelihood estimation method. Findings showed convergence of activation in mainly right-lateralized brain areas, including dorsomedial frontal cortex and parieto-temporal areas, and are consistent with previous literature on the neural correlates of VA. Results are discussed in terms of their functional and developmental implications for VA in children and adolescents. ", "metadata": {"id": 33035933, "text_md5": "2e0f050ead39727a8124279fd14db448", "field_positions": {"authors": [0, 115], "journal": [116, 122], "publication_year": [124, 128], "title": [139, 228], "keywords": [242, 366], "abstract": [379, 1523], "body": [1532, 1532]}, "batch": 3, "pmid": 33035933, "doi": "10.1016/j.cortex.2020.08.008", "pmid_url": "https://pubmed.ncbi.nlm.nih.gov/33035933/", "efetch_url": "https://eutils.ncbi.nlm.nih.gov/entrez/eutils/efetch.fcgi?db=pubmed&id=33035933"}, "display_title": "pmid: <a href=\"https://pubmed.ncbi.nlm.nih.gov/33035933/\">33035933</a>", "list_title": "PMID33035933  Meta-analysis of the neural correlates of vigilant attention in children and adolescents."}
{"text": "Morandini, Hugo A E and Silk, Timothy J and Griffiths, Kristi and Rao, Pradeep and Hood, Sean D and Zepf, Florian D\nCortex; a journal devoted to the study of the nervous system and behavior, 2021\n\n# Title\n\nMeta-analysis of the neural correlates of vigilant attention in children and adolescents.\n\n# Keywords\n\nALE meta-analysis \nChildren and adolescents \nFunctional magnetic resonance imaging \nSustained attention \nVigilant attention \nfMRI \n\n\n# Abstract\n\nVigilant Attention (VA), defined as the ability to maintain attention to cognitively unchallenging activities over a prolonged period of time, is critical to support higher cognitive functions and many behaviours in our everyday life. Evidence has shown that VA rapidly improves throughout childhood and adolescence until young adulthood and tends to decline in older adulthood. Although neuroimaging studies have extensively investigated this cognitive function in adults, the neural correlates of VA in neurotypical children and adolescents remain unclear. The current meta-analysis reviewed and examined functional neuroimaging studies in paediatric populations that used behavioural tasks involving VA. The selected studies (N\u00a0=\u00a025) were analyzed using the activation likelihood estimation method. Findings showed convergence of activation in mainly right-lateralized brain areas, including dorsomedial frontal cortex and parieto-temporal areas, and are consistent with previous literature on the neural correlates of VA. Results are discussed in terms of their functional and developmental implications for VA in children and adolescents. \n", "metadata": {"pmid": "33035933", "journal": "Cortex; a journal devoted to the study of the nervous system and behavior", "publication_year": "2021", "title": "Meta-analysis of the neural correlates of vigilant attention in children and adolescents.", "keywords": "ALE meta-analysis \nChildren and adolescents \nFunctional magnetic resonance imaging \nSustained attention \nVigilant attention \nfMRI \n", "abstract": "Vigilant Attention (VA), defined as the ability to maintain attention to cognitively unchallenging activities over a prolonged period of time, is critical to support higher cognitive functions and many behaviours in our everyday life. Evidence has shown that VA rapidly improves throughout childhood and adolescence until young adulthood and tends to decline in older adulthood. Although neuroimaging studies have extensively investigated this cognitive function in adults, the neural correlates of VA in neurotypical children and adolescents remain unclear. The current meta-analysis reviewed and examined functional neuroimaging studies in paediatric populations that used behavioural tasks involving VA. The selected studies (N\u00a0=\u00a025) were analyzed using the activation likelihood estimation method. Findings showed convergence of activation in mainly right-lateralized brain areas, including dorsomedial frontal cortex and parieto-temporal areas, and are consistent with previous literature on the neural correlates of VA. Results are discussed in terms of their functional and developmental implications for VA in children and adolescents. ", "authors": "Morandini, Hugo A E and Silk, Timothy J and Griffiths, Kristi and Rao, Pradeep and Hood, Sean D and Zepf, Florian D"}, "display_title": "pmid: <a href=\"https://pubmed.ncbi.nlm.nih.gov/33035933\">33035933</a>", "list_title": "PMID33035933 Meta-analysis of the neural correlates of vigilant attention in children and adolescents."}
