{"text": "Isherwood, S J S and Keuken, M C and Bazin, P L and Forstmann, B U\nNeurosci Biobehav Rev, 2021\n\n# Title\n\nCortical and subcortical contributions to interference resolution and inhibition - An fMRI ALE meta-analysis.\n\n# Keywords\n\nCognitive control\nInhibition\nInterference\nfMRI ALE meta-analysis\n\n# Abstract\nInteracting with our environment requires the selection of appropriate responses and the inhibition of others. Such effortful inhibition is achieved by a number of interference resolution and global inhibition processes. This meta-analysis including 57 studies and 73 contrasts revisits the overlap and differences in brain areas supporting interference resolution and global inhibition in cortical and subcortical brain areas. Activation likelihood estimation was used to discern the brain regions subserving each type of cognitive control. Individual contrast analysis revealed a common activation of the bilateral insula and supplementary motor areas. Subtraction analyses demonstrated the voxel-wise differences in recruitment in a number of areas including the precuneus in the interference tasks and the frontal pole and dorsal striatum in the inhibition tasks. Our results display a surprising lack of subcortical involvement within these types of cognitive control, a finding that is likely to reflect a systematic gap in the field of functional neuroimaging. ", "metadata": {"id": 34310977, "text_md5": "5f54599c592b7cf0140275a0fdb201cb", "field_positions": {"authors": [0, 66], "journal": [67, 88], "publication_year": [90, 94], "title": [105, 214], "keywords": [228, 292], "abstract": [305, 1373], "body": [1382, 1382]}, "batch": 1, "pmid": 34310977, "doi": "10.1016/j.neubiorev.2021.07.021", "pmid_url": "https://pubmed.ncbi.nlm.nih.gov/34310977/", "efetch_url": "https://eutils.ncbi.nlm.nih.gov/entrez/eutils/efetch.fcgi?db=pubmed&id=34310977"}, "display_title": "pmid: <a href=\"https://pubmed.ncbi.nlm.nih.gov/34310977/\">34310977</a>", "list_title": "PMID34310977  Cortical and subcortical contributions to interference resolution and inhibition - An fMRI ALE meta-analysis."}
{"text": "Isherwood, S J S and Keuken, M C and Bazin, P L and Forstmann, B U\nNeuroscience and biobehavioral reviews, 2021\n\n# Title\n\nCortical and subcortical contributions to interference resolution and inhibition - An fMRI ALE meta-analysis.\n\n# Keywords\n\nCognitive control \nInhibition \nInterference \nfMRI ALE meta-analysis \n\n\n# Abstract\n\nInteracting with our environment requires the selection of appropriate responses and the inhibition of others. Such effortful inhibition is achieved by a number of interference resolution and global inhibition processes. This meta-analysis including 57 studies and 73 contrasts revisits the overlap and differences in brain areas supporting interference resolution and global inhibition in cortical and subcortical brain areas. Activation likelihood estimation was used to discern the brain regions subserving each type of cognitive control. Individual contrast analysis revealed a common activation of the bilateral insula and supplementary motor areas. Subtraction analyses demonstrated the voxel-wise differences in recruitment in a number of areas including the precuneus in the interference tasks and the frontal pole and dorsal striatum in the inhibition tasks. Our results display a surprising lack of subcortical involvement within these types of cognitive control, a finding that is likely to reflect a systematic gap in the field of functional neuroimaging. \n", "metadata": {"pmid": "34310977", "journal": "Neuroscience and biobehavioral reviews", "publication_year": "2021", "title": "Cortical and subcortical contributions to interference resolution and inhibition - An fMRI ALE meta-analysis.", "keywords": "Cognitive control \nInhibition \nInterference \nfMRI ALE meta-analysis \n", "abstract": "Interacting with our environment requires the selection of appropriate responses and the inhibition of others. Such effortful inhibition is achieved by a number of interference resolution and global inhibition processes. This meta-analysis including 57 studies and 73 contrasts revisits the overlap and differences in brain areas supporting interference resolution and global inhibition in cortical and subcortical brain areas. Activation likelihood estimation was used to discern the brain regions subserving each type of cognitive control. Individual contrast analysis revealed a common activation of the bilateral insula and supplementary motor areas. Subtraction analyses demonstrated the voxel-wise differences in recruitment in a number of areas including the precuneus in the interference tasks and the frontal pole and dorsal striatum in the inhibition tasks. Our results display a surprising lack of subcortical involvement within these types of cognitive control, a finding that is likely to reflect a systematic gap in the field of functional neuroimaging. ", "authors": "Isherwood, S J S and Keuken, M C and Bazin, P L and Forstmann, B U"}, "display_title": "pmid: <a href=\"https://pubmed.ncbi.nlm.nih.gov/34310977\">34310977</a>", "list_title": "PMID34310977 Cortical and subcortical contributions to interference resolution and inhibition - An fMRI ALE meta-analysis."}
