{"text": "Chuan-Peng, Hu and Huang, Yi and Eickhoff, Simon B and Peng, Kaiping and Sui, Jie\nCogn Affect Behav Neurosci, 2020\n\n# Title\n\nSeeking the \"Beauty Center\" in the Brain: A Meta-Analysis of fMRI Studies of Beautiful Human Faces and Visual Art.\n\n# Keywords\n\nActivation likelihood estimation\nBeauty\nFaces\nFunctional magnetic resonance imaging\nVisual art\n\n# Abstract\nDuring the past two decades, cognitive neuroscientists have sought to elucidate the common neural basis of the experience of beauty. Still, empirical evidence for such common neural basis of different forms of beauty is not conclusive. To address this question, we performed an activation likelihood estimation (ALE) meta-analysis on the existing neuroimaging studies of beauty appreciation of faces and visual art by nonexpert adults (49 studies, 982 participants, meta-data are available at https://osf.io/s9xds/ ). We observed that perceiving these two forms of beauty activated distinct brain regions: While the beauty of faces convergently activated the left ventral striatum, the beauty of visual art convergently activated the anterior medial prefrontal cortex (aMPFC). However, a conjunction analysis failed to reveal any common brain regions for the beauty of visual art and faces. The implications of these results are discussed. ", "metadata": {"id": 33089442, "text_md5": "d1d2977ed07afa880a4622c24ead23a5", "field_positions": {"authors": [0, 81], "journal": [82, 108], "publication_year": [110, 114], "title": [125, 239], "keywords": [253, 347], "abstract": [360, 1300], "body": [1309, 1309]}, "batch": 4, "pmid": 33089442, "doi": "10.3758/s13415-020-00827-z", "pmid_url": "https://pubmed.ncbi.nlm.nih.gov/33089442/", "efetch_url": "https://eutils.ncbi.nlm.nih.gov/entrez/eutils/efetch.fcgi?db=pubmed&id=33089442"}, "display_title": "pmid: <a href=\"https://pubmed.ncbi.nlm.nih.gov/33089442/\">33089442</a>", "list_title": "PMID33089442  Seeking the \"Beauty Center\" in the Brain: A Meta-Analysis of fMRI Studies of Beautiful Human Faces and Visual Art."}
{"text": "Chuan-Peng, Hu and Huang, Yi and Eickhoff, Simon B and Peng, Kaiping and Sui, Jie\nCognitive, affective & behavioral neuroscience, 2021\n\n# Title\n\nSeeking the \"Beauty Center\" in the Brain: A Meta-Analysis of fMRI Studies of Beautiful Human Faces and Visual Art.\n\n# Keywords\n\nActivation likelihood estimation \nBeauty \nFaces \nFunctional magnetic resonance imaging \nVisual art \n\n\n# Abstract\n\nDuring the past two decades, cognitive neuroscientists have sought to elucidate the common neural basis of the experience of beauty. Still, empirical evidence for such common neural basis of different forms of beauty is not conclusive. To address this question, we performed an activation likelihood estimation (ALE) meta-analysis on the existing neuroimaging studies of beauty appreciation of faces and visual art by nonexpert adults (49 studies, 982 participants, meta-data are available at https://osf.io/s9xds/ ). We observed that perceiving these two forms of beauty activated distinct brain regions: While the beauty of faces convergently activated the left ventral striatum, the beauty of visual art convergently activated the anterior medial prefrontal cortex (aMPFC). However, a conjunction analysis failed to reveal any common brain regions for the beauty of visual art and faces. The implications of these results are discussed. \n", "metadata": {"pmid": "33089442", "journal": "Cognitive, affective & behavioral neuroscience", "publication_year": "2021", "title": "Seeking the \"Beauty Center\" in the Brain: A Meta-Analysis of fMRI Studies of Beautiful Human Faces and Visual Art.", "keywords": "Activation likelihood estimation \nBeauty \nFaces \nFunctional magnetic resonance imaging \nVisual art \n", "abstract": "During the past two decades, cognitive neuroscientists have sought to elucidate the common neural basis of the experience of beauty. Still, empirical evidence for such common neural basis of different forms of beauty is not conclusive. To address this question, we performed an activation likelihood estimation (ALE) meta-analysis on the existing neuroimaging studies of beauty appreciation of faces and visual art by nonexpert adults (49 studies, 982 participants, meta-data are available at https://osf.io/s9xds/ ). We observed that perceiving these two forms of beauty activated distinct brain regions: While the beauty of faces convergently activated the left ventral striatum, the beauty of visual art convergently activated the anterior medial prefrontal cortex (aMPFC). However, a conjunction analysis failed to reveal any common brain regions for the beauty of visual art and faces. The implications of these results are discussed. ", "authors": "Chuan-Peng, Hu and Huang, Yi and Eickhoff, Simon B and Peng, Kaiping and Sui, Jie"}, "display_title": "pmid: <a href=\"https://pubmed.ncbi.nlm.nih.gov/33089442\">33089442</a>", "list_title": "PMID33089442 Seeking the \"Beauty Center\" in the Brain: A Meta-Analysis of fMRI Studies of Beautiful Human Faces and Visual Art."}
