{"text": "Crow, Andrew J D and Thomas, Alisha and Rao, Yash and Beloor-Suresh, Ashithkumar and Weinstein, David and Hinds, Walter A and Tracy, Joseph I\nEpilepsia, 2023\n\n# Title\n\nTask-based functional magnetic resonance imaging prediction of postsurgical cognitive outcomes in temporal lobe epilepsy: A systematic review, meta-analysis, and new data.\n\n# Keywords\n\nfunctional neuroimaging\nneuropsychology\nprognosis\nresearch synthesis\nsurgical planning\n\n# Abstract\nTask-based functional magnetic resonance imaging (tfMRI) has developed as a common alternative in epilepsy surgery to the intracarotid amobarbital procedure, also known as the Wada procedure. Prior studies have implicated tfMRI as a comparable predictor of postsurgical cognitive outcomes. However, the predictive validity of tfMRI has not been established. This preregistered systematic review and meta-analysis (CRD42020183563) synthesizes the literature predicting postsurgical cognitive outcomes in temporal lobe epilepsy (TLE) using tfMRI. The PubMed and PsycINFO literature databases were queried for English-language articles published between January 1, 2009 and December 31, 2020 associating tfMRI laterality indices or symmetry of task activation with outcomes in TLE. Their references were reviewed for additional relevant literature, and unpublished data from our center were incorporated. Nineteen studies were included in the meta-analysis. tfMRI studies predicted postsurgical cognitive outcomes in left TLE (  ", "metadata": {"id": 36522799, "text_md5": "eaba840e963d8b9b7ce242c822b956fb", "field_positions": {"authors": [0, 141], "journal": [142, 151], "publication_year": [153, 157], "title": [168, 339], "keywords": [353, 439], "abstract": [452, 1478], "body": [1487, 1487]}, "batch": 4, "pmid": 36522799, "doi": "10.1111/epi.17475", "pmid_url": "https://pubmed.ncbi.nlm.nih.gov/36522799/", "efetch_url": "https://eutils.ncbi.nlm.nih.gov/entrez/eutils/efetch.fcgi?db=pubmed&id=36522799"}, "display_title": "pmid: <a href=\"https://pubmed.ncbi.nlm.nih.gov/36522799/\">36522799</a>", "list_title": "PMID36522799  Task-based functional magnetic resonance imaging prediction of postsurgical cognitive outcomes in temporal lobe epilepsy: A systematic review, meta-analysis, and new data."}
{"text": "Crow, Andrew J D and Thomas, Alisha and Rao, Yash and Beloor-Suresh, Ashithkumar and Weinstein, David and Hinds, Walter A and Tracy, Joseph I\nEpilepsia, 2023\n\n# Title\n\nTask-based functional magnetic resonance imaging prediction of postsurgical cognitive outcomes in temporal lobe epilepsy: A systematic review, meta-analysis, and new data.\n\n# Keywords\n\nfunctional neuroimaging \nneuropsychology \nprognosis \nresearch synthesis \nsurgical planning \n\n\n# Abstract\n\nTask-based functional magnetic resonance imaging (tfMRI) has developed as a common alternative in epilepsy surgery to the intracarotid amobarbital procedure, also known as the Wada procedure. Prior studies have implicated tfMRI as a comparable predictor of postsurgical cognitive outcomes. However, the predictive validity of tfMRI has not been established. This preregistered systematic review and meta-analysis (CRD42020183563) synthesizes the literature predicting postsurgical cognitive outcomes in temporal lobe epilepsy (TLE) using tfMRI. The PubMed and PsycINFO literature databases were queried for English-language articles published between January 1, 2009 and December 31, 2020 associating tfMRI laterality indices or symmetry of task activation with outcomes in TLE. Their references were reviewed for additional relevant literature, and unpublished data from our center were incorporated. Nineteen studies were included in the meta-analysis. tfMRI studies predicted postsurgical cognitive outcomes in left TLE (  \n", "metadata": {"pmid": "36522799", "journal": "Epilepsia", "publication_year": "2023", "title": "Task-based functional magnetic resonance imaging prediction of postsurgical cognitive outcomes in temporal lobe epilepsy: A systematic review, meta-analysis, and new data.", "keywords": "functional neuroimaging \nneuropsychology \nprognosis \nresearch synthesis \nsurgical planning \n", "abstract": "Task-based functional magnetic resonance imaging (tfMRI) has developed as a common alternative in epilepsy surgery to the intracarotid amobarbital procedure, also known as the Wada procedure. Prior studies have implicated tfMRI as a comparable predictor of postsurgical cognitive outcomes. However, the predictive validity of tfMRI has not been established. This preregistered systematic review and meta-analysis (CRD42020183563) synthesizes the literature predicting postsurgical cognitive outcomes in temporal lobe epilepsy (TLE) using tfMRI. The PubMed and PsycINFO literature databases were queried for English-language articles published between January 1, 2009 and December 31, 2020 associating tfMRI laterality indices or symmetry of task activation with outcomes in TLE. Their references were reviewed for additional relevant literature, and unpublished data from our center were incorporated. Nineteen studies were included in the meta-analysis. tfMRI studies predicted postsurgical cognitive outcomes in left TLE (  ", "authors": "Crow, Andrew J D and Thomas, Alisha and Rao, Yash and Beloor-Suresh, Ashithkumar and Weinstein, David and Hinds, Walter A and Tracy, Joseph I"}, "display_title": "pmid: <a href=\"https://pubmed.ncbi.nlm.nih.gov/36522799\">36522799</a>", "list_title": "PMID36522799 Task-based functional magnetic resonance imaging prediction of postsurgical cognitive outcomes in temporal lobe epilepsy: A systematic review, meta-analysis, and new data."}
