{"text": "Kirby, Lauren A J and Robinson, Jennifer L\nBrain Cogn, 2017\n\n# Title\n\nAffective mapping: An activation likelihood estimation (ALE) meta-analysis.\n\n# Keywords\n\nActivation likelihood estimation\nAffect programs\nBrainmap\nEmotion\nNeuroimaging\nfMRI\n\n# Abstract\nFunctional neuroimaging has the spatial resolution to explain the neural basis of emotions. Activation likelihood estimation (ALE), as opposed to traditional qualitative meta-analysis, quantifies convergence of activation across studies within affective categories. Others have used ALE to investigate a broad range of emotions, but without the convenience of the BrainMap database. We used the BrainMap database and analysis resources to run separate meta-analyses on coordinates reported for anger, anxiety, disgust, fear, happiness, humor, and sadness. Resultant ALE maps were compared to determine areas of convergence between emotions, as well as to identify affect-specific networks. Five out of the seven emotions demonstrated consistent activation within the amygdala, whereas all emotions consistently activated the right inferior frontal gyrus, which has been implicated as an integration hub for affective and cognitive processes. These data provide the framework for models of affect-specific networks, as well as emotional processing hubs, which can be used for future studies of functional or effective connectivity. ", "metadata": {"id": 26074298, "text_md5": "2194ce01257c058c3baeba500d34f91d", "field_positions": {"authors": [0, 42], "journal": [43, 53], "publication_year": [55, 59], "title": [70, 145], "keywords": [159, 242], "abstract": [255, 1386], "body": [1395, 1395]}, "batch": 3, "pmid": 26074298, "doi": "10.1016/j.bandc.2015.04.006", "pmid_url": "https://pubmed.ncbi.nlm.nih.gov/26074298/", "efetch_url": "https://eutils.ncbi.nlm.nih.gov/entrez/eutils/efetch.fcgi?db=pubmed&id=26074298"}, "display_title": "pmid: <a href=\"https://pubmed.ncbi.nlm.nih.gov/26074298/\">26074298</a>", "list_title": "PMID26074298  Affective mapping: An activation likelihood estimation (ALE) meta-analysis."}
{"text": "Kirby, Lauren A J and Robinson, Jennifer L\nBrain and cognition, 2018\n\n# Title\n\nAffective mapping: An activation likelihood estimation (ALE) meta-analysis.\n\n# Keywords\n\nActivation likelihood estimation \nAffect programs \nBrainmap \nEmotion \nNeuroimaging \nfMRI \n\n\n# Abstract\n\nFunctional neuroimaging has the spatial resolution to explain the neural basis of emotions. Activation likelihood estimation (ALE), as opposed to traditional qualitative meta-analysis, quantifies convergence of activation across studies within affective categories. Others have used ALE to investigate a broad range of emotions, but without the convenience of the BrainMap database. We used the BrainMap database and analysis resources to run separate meta-analyses on coordinates reported for anger, anxiety, disgust, fear, happiness, humor, and sadness. Resultant ALE maps were compared to determine areas of convergence between emotions, as well as to identify affect-specific networks. Five out of the seven emotions demonstrated consistent activation within the amygdala, whereas all emotions consistently activated the right inferior frontal gyrus, which has been implicated as an integration hub for affective and cognitive processes. These data provide the framework for models of affect-specific networks, as well as emotional processing hubs, which can be used for future studies of functional or effective connectivity. \n", "metadata": {"pmid": "26074298", "journal": "Brain and cognition", "publication_year": "2018", "title": "Affective mapping: An activation likelihood estimation (ALE) meta-analysis.", "keywords": "Activation likelihood estimation \nAffect programs \nBrainmap \nEmotion \nNeuroimaging \nfMRI \n", "abstract": "Functional neuroimaging has the spatial resolution to explain the neural basis of emotions. Activation likelihood estimation (ALE), as opposed to traditional qualitative meta-analysis, quantifies convergence of activation across studies within affective categories. Others have used ALE to investigate a broad range of emotions, but without the convenience of the BrainMap database. We used the BrainMap database and analysis resources to run separate meta-analyses on coordinates reported for anger, anxiety, disgust, fear, happiness, humor, and sadness. Resultant ALE maps were compared to determine areas of convergence between emotions, as well as to identify affect-specific networks. Five out of the seven emotions demonstrated consistent activation within the amygdala, whereas all emotions consistently activated the right inferior frontal gyrus, which has been implicated as an integration hub for affective and cognitive processes. These data provide the framework for models of affect-specific networks, as well as emotional processing hubs, which can be used for future studies of functional or effective connectivity. ", "authors": "Kirby, Lauren A J and Robinson, Jennifer L"}, "display_title": "pmid: <a href=\"https://pubmed.ncbi.nlm.nih.gov/26074298\">26074298</a>", "list_title": "PMID26074298 Affective mapping: An activation likelihood estimation (ALE) meta-analysis."}
