{"text": "Teghil, Alice and Boccia, Maddalena and D'Antonio, Fabrizia and Di Vita, Antonella and de Lena, Carlo and Guariglia, Cecilia\nNeurosci Biobehav Rev, 2019\n\n# Title\n\nNeural substrates of internally-based and externally-cued timing: An activation likelihood estimation (ALE) meta-analysis of fMRI studies.\n\n# Keywords\n\nALE\nDuration\nMeta-analysis\nRhythm\nTime perception\nTiming\nfMRI\n\n# Abstract\nA dynamic interplay exists between Internally-Based (IBT) and Externally-Cued (ECT) time processing. While IBT processes support the self-generation of context-independent temporal representations, ECT mechanisms allow constructing temporal representations primarily derived from the structure of the sensory environment. We performed an activation likelihood estimation (ALE) meta-analysis on 177 fMRI experiments, from 79 articles, to identify brain areas involved in timing; two individual ALEs tested the hypothesis of a neural segregation between IBT and ECT. The general ALE highlighted a network involving supplementary motor area (SMA), intraparietal sulcus, inferior frontal gyrus (IFG), insula (INS) and basal ganglia. We found evidence of a partial dissociation between IBT and ECT. IBT relies on a subset of areas also involved in ECT, however ECT tasks activate SMA, right IFG, left precentral gyrus and INS in a significantly stronger way. Present results suggest that ECT involves the detection of environmental temporal regularities and their integration with the output of the IBT processing, to generate a representation of time which reflects the temporal metric of the environment. ", "metadata": {"id": 30316722, "text_md5": "d09cfb5838b689a02c605a8af223af96", "field_positions": {"authors": [0, 124], "journal": [125, 146], "publication_year": [148, 152], "title": [163, 301], "keywords": [315, 376], "abstract": [389, 1591], "body": [1600, 1600]}, "batch": 1, "pmid": 30316722, "doi": "10.1016/j.neubiorev.2018.10.003", "pmid_url": "https://pubmed.ncbi.nlm.nih.gov/30316722/", "efetch_url": "https://eutils.ncbi.nlm.nih.gov/entrez/eutils/efetch.fcgi?db=pubmed&id=30316722"}, "display_title": "pmid: <a href=\"https://pubmed.ncbi.nlm.nih.gov/30316722/\">30316722</a>", "list_title": "PMID30316722  Neural substrates of internally-based and externally-cued timing: An activation likelihood estimation (ALE) meta-analysis of fMRI studies."}
{"text": "Teghil, Alice and Boccia, Maddalena and D'Antonio, Fabrizia and Di Vita, Antonella and de Lena, Carlo and Guariglia, Cecilia\nNeuroscience and biobehavioral reviews, 2019\n\n# Title\n\nNeural substrates of internally-based and externally-cued timing: An activation likelihood estimation (ALE) meta-analysis of fMRI studies.\n\n# Keywords\n\nALE \nDuration \nMeta-analysis \nRhythm \nTime perception \nTiming \nfMRI \n\n\n# Abstract\n\nA dynamic interplay exists between Internally-Based (IBT) and Externally-Cued (ECT) time processing. While IBT processes support the self-generation of context-independent temporal representations, ECT mechanisms allow constructing temporal representations primarily derived from the structure of the sensory environment. We performed an activation likelihood estimation (ALE) meta-analysis on 177 fMRI experiments, from 79 articles, to identify brain areas involved in timing; two individual ALEs tested the hypothesis of a neural segregation between IBT and ECT. The general ALE highlighted a network involving supplementary motor area (SMA), intraparietal sulcus, inferior frontal gyrus (IFG), insula (INS) and basal ganglia. We found evidence of a partial dissociation between IBT and ECT. IBT relies on a subset of areas also involved in ECT, however ECT tasks activate SMA, right IFG, left precentral gyrus and INS in a significantly stronger way. Present results suggest that ECT involves the detection of environmental temporal regularities and their integration with the output of the IBT processing, to generate a representation of time which reflects the temporal metric of the environment. \n", "metadata": {"pmid": "30316722", "journal": "Neuroscience and biobehavioral reviews", "publication_year": "2019", "title": "Neural substrates of internally-based and externally-cued timing: An activation likelihood estimation (ALE) meta-analysis of fMRI studies.", "keywords": "ALE \nDuration \nMeta-analysis \nRhythm \nTime perception \nTiming \nfMRI \n", "abstract": "A dynamic interplay exists between Internally-Based (IBT) and Externally-Cued (ECT) time processing. While IBT processes support the self-generation of context-independent temporal representations, ECT mechanisms allow constructing temporal representations primarily derived from the structure of the sensory environment. We performed an activation likelihood estimation (ALE) meta-analysis on 177 fMRI experiments, from 79 articles, to identify brain areas involved in timing; two individual ALEs tested the hypothesis of a neural segregation between IBT and ECT. The general ALE highlighted a network involving supplementary motor area (SMA), intraparietal sulcus, inferior frontal gyrus (IFG), insula (INS) and basal ganglia. We found evidence of a partial dissociation between IBT and ECT. IBT relies on a subset of areas also involved in ECT, however ECT tasks activate SMA, right IFG, left precentral gyrus and INS in a significantly stronger way. Present results suggest that ECT involves the detection of environmental temporal regularities and their integration with the output of the IBT processing, to generate a representation of time which reflects the temporal metric of the environment. ", "authors": "Teghil, Alice and Boccia, Maddalena and D'Antonio, Fabrizia and Di Vita, Antonella and de Lena, Carlo and Guariglia, Cecilia"}, "display_title": "pmid: <a href=\"https://pubmed.ncbi.nlm.nih.gov/30316722\">30316722</a>", "list_title": "PMID30316722 Neural substrates of internally-based and externally-cued timing: An activation likelihood estimation (ALE) meta-analysis of fMRI studies."}
