{"text": "Yaple, Zachary and Arsalidou, Marie\nExp Brain Res, 2017\n\n# Title\n\nNegative priming: a meta-analysis of fMRI studies.\n\n# Keywords\n\nAnterior cingulate gyrus\nMeta-analysis\nMiddle prefrontal cortex\nNegative priming\nSuperior temporal gyrus\nfMRI\n\n# Abstract\nA phenomenon termed negative priming is defined as an increase in reaction time and/or decrease in performance during instances in which current target stimuli are employed as distractor stimuli in the previous trial. A recent qualitative review on negative priming reported neural regions of interest underlined by activity within the right middle frontal gyrus and left middle temporal gyrus; however, these areas of interest have not been tested and supported by using coordinate-based, quantitative meta-analysis. We compiled functional magnetic resonance imaging studies that examined neural correlates of priming tasks using perceptual, conceptual and lexical primes. Effect-size signed differential mapping was used to perform a neuroimaging meta-analysis on the negative priming effect. Results from fourteen studies (245 participants; 85 foci) show concordance across studies in the right middle frontal gyrus and the left superior temporal gyrus, as suggested by the previous review; however, results also yielded concordance within the anterior cingulate cortex. Our data support the extant hypothesis and offer new insights into the neural mechanisms of the negative priming effect. ", "metadata": {"id": 28821983, "text_md5": "1f08f33726e2f1e0372dd107d2c9ec80", "field_positions": {"authors": [0, 35], "journal": [36, 49], "publication_year": [51, 55], "title": [66, 116], "keywords": [130, 239], "abstract": [252, 1447], "body": [1456, 1456]}, "batch": 1, "pmid": 28821983, "doi": "10.1007/s00221-017-5065-6", "pmid_url": "https://pubmed.ncbi.nlm.nih.gov/28821983/", "efetch_url": "https://eutils.ncbi.nlm.nih.gov/entrez/eutils/efetch.fcgi?db=pubmed&id=28821983"}, "display_title": "pmid: <a href=\"https://pubmed.ncbi.nlm.nih.gov/28821983/\">28821983</a>", "list_title": "PMID28821983  Negative priming: a meta-analysis of fMRI studies."}
{"text": "Yaple, Zachary and Arsalidou, Marie\nExperimental brain research, 2018\n\n# Title\n\nNegative priming: a meta-analysis of fMRI studies.\n\n# Keywords\n\nAnterior cingulate gyrus \nMeta-analysis \nMiddle prefrontal cortex \nNegative priming \nSuperior temporal gyrus \nfMRI \n\n\n# Abstract\n\nA phenomenon termed negative priming is defined as an increase in reaction time and/or decrease in performance during instances in which current target stimuli are employed as distractor stimuli in the previous trial. A recent qualitative review on negative priming reported neural regions of interest underlined by activity within the right middle frontal gyrus and left middle temporal gyrus; however, these areas of interest have not been tested and supported by using coordinate-based, quantitative meta-analysis. We compiled functional magnetic resonance imaging studies that examined neural correlates of priming tasks using perceptual, conceptual and lexical primes. Effect-size signed differential mapping was used to perform a neuroimaging meta-analysis on the negative priming effect. Results from fourteen studies (245 participants; 85 foci) show concordance across studies in the right middle frontal gyrus and the left superior temporal gyrus, as suggested by the previous review; however, results also yielded concordance within the anterior cingulate cortex. Our data support the extant hypothesis and offer new insights into the neural mechanisms of the negative priming effect. \n", "metadata": {"pmid": "28821983", "journal": "Experimental brain research", "publication_year": "2018", "title": "Negative priming: a meta-analysis of fMRI studies.", "keywords": "Anterior cingulate gyrus \nMeta-analysis \nMiddle prefrontal cortex \nNegative priming \nSuperior temporal gyrus \nfMRI \n", "abstract": "A phenomenon termed negative priming is defined as an increase in reaction time and/or decrease in performance during instances in which current target stimuli are employed as distractor stimuli in the previous trial. A recent qualitative review on negative priming reported neural regions of interest underlined by activity within the right middle frontal gyrus and left middle temporal gyrus; however, these areas of interest have not been tested and supported by using coordinate-based, quantitative meta-analysis. We compiled functional magnetic resonance imaging studies that examined neural correlates of priming tasks using perceptual, conceptual and lexical primes. Effect-size signed differential mapping was used to perform a neuroimaging meta-analysis on the negative priming effect. Results from fourteen studies (245 participants; 85 foci) show concordance across studies in the right middle frontal gyrus and the left superior temporal gyrus, as suggested by the previous review; however, results also yielded concordance within the anterior cingulate cortex. Our data support the extant hypothesis and offer new insights into the neural mechanisms of the negative priming effect. ", "authors": "Yaple, Zachary and Arsalidou, Marie"}, "display_title": "pmid: <a href=\"https://pubmed.ncbi.nlm.nih.gov/28821983\">28821983</a>", "list_title": "PMID28821983 Negative priming: a meta-analysis of fMRI studies."}
