{"text": "Morriss, Jayne and Gell, Martin and van Reekum, Carien M\nNeurosci Biobehav Rev, 2019\n\n# Title\n\nThe uncertain brain: A co-ordinate based meta-analysis of the neural signatures supporting uncertainty during different contexts.\n\n# Keywords\n\nAmygdala\nAnterior insula\nAnticipation\nAssociative learning\nDecision-making\nUncertainty\nfMRI\n\n# Abstract\nUncertainty is often inevitable in everyday life and can be both stressful and exciting. Given its relevance to psychopathology and wellbeing, recent research has begun to address the brain basis of uncertainty. In the current review we examined whether there are discrete and shared neural signatures for different uncertain contexts. From the literature we identified three broad categories of uncertainty currently empirically studied using functional MRI (fMRI): basic threat and reward uncertainty, decision-making under uncertainty, and associative learning under uncertainty. We examined the neural basis of each category by using a coordinate based meta-analysis, where brain activation foci from previously published fMRI experiments were drawn together (1998-2017; 87 studies). The analyses revealed shared and discrete patterns of neural activation for uncertainty, such as the insula and amygdala, depending on the category. Such findings will have relevance for researchers attempting to conceptualise uncertainty, as well as clinical researchers examining the neural basis of uncertainty in relation to psychopathology. ", "metadata": {"id": 30550858, "text_md5": "2de6f9bc8ebf61669303f81614f620ee", "field_positions": {"authors": [0, 56], "journal": [57, 78], "publication_year": [80, 84], "title": [95, 224], "keywords": [238, 329], "abstract": [342, 1476], "body": [1485, 1485]}, "batch": 3, "pmid": 30550858, "doi": "10.1016/j.neubiorev.2018.12.013", "pmid_url": "https://pubmed.ncbi.nlm.nih.gov/30550858/", "efetch_url": "https://eutils.ncbi.nlm.nih.gov/entrez/eutils/efetch.fcgi?db=pubmed&id=30550858"}, "display_title": "pmid: <a href=\"https://pubmed.ncbi.nlm.nih.gov/30550858/\">30550858</a>", "list_title": "PMID30550858  The uncertain brain: A co-ordinate based meta-analysis of the neural signatures supporting uncertainty during different contexts."}
{"text": "Morriss, Jayne and Gell, Martin and van Reekum, Carien M\nNeuroscience and biobehavioral reviews, 2019\n\n# Title\n\nThe uncertain brain: A co-ordinate based meta-analysis of the neural signatures supporting uncertainty during different contexts.\n\n# Keywords\n\nAmygdala \nAnterior insula \nAnticipation \nAssociative learning \nDecision-making \nUncertainty \nfMRI \n\n\n# Abstract\n\nUncertainty is often inevitable in everyday life and can be both stressful and exciting. Given its relevance to psychopathology and wellbeing, recent research has begun to address the brain basis of uncertainty. In the current review we examined whether there are discrete and shared neural signatures for different uncertain contexts. From the literature we identified three broad categories of uncertainty currently empirically studied using functional MRI (fMRI): basic threat and reward uncertainty, decision-making under uncertainty, and associative learning under uncertainty. We examined the neural basis of each category by using a coordinate based meta-analysis, where brain activation foci from previously published fMRI experiments were drawn together (1998-2017; 87 studies). The analyses revealed shared and discrete patterns of neural activation for uncertainty, such as the insula and amygdala, depending on the category. Such findings will have relevance for researchers attempting to conceptualise uncertainty, as well as clinical researchers examining the neural basis of uncertainty in relation to psychopathology. \n", "metadata": {"pmid": "30550858", "journal": "Neuroscience and biobehavioral reviews", "publication_year": "2019", "title": "The uncertain brain: A co-ordinate based meta-analysis of the neural signatures supporting uncertainty during different contexts.", "keywords": "Amygdala \nAnterior insula \nAnticipation \nAssociative learning \nDecision-making \nUncertainty \nfMRI \n", "abstract": "Uncertainty is often inevitable in everyday life and can be both stressful and exciting. Given its relevance to psychopathology and wellbeing, recent research has begun to address the brain basis of uncertainty. In the current review we examined whether there are discrete and shared neural signatures for different uncertain contexts. From the literature we identified three broad categories of uncertainty currently empirically studied using functional MRI (fMRI): basic threat and reward uncertainty, decision-making under uncertainty, and associative learning under uncertainty. We examined the neural basis of each category by using a coordinate based meta-analysis, where brain activation foci from previously published fMRI experiments were drawn together (1998-2017; 87 studies). The analyses revealed shared and discrete patterns of neural activation for uncertainty, such as the insula and amygdala, depending on the category. Such findings will have relevance for researchers attempting to conceptualise uncertainty, as well as clinical researchers examining the neural basis of uncertainty in relation to psychopathology. ", "authors": "Morriss, Jayne and Gell, Martin and van Reekum, Carien M"}, "display_title": "pmid: <a href=\"https://pubmed.ncbi.nlm.nih.gov/30550858\">30550858</a>", "list_title": "PMID30550858 The uncertain brain: A co-ordinate based meta-analysis of the neural signatures supporting uncertainty during different contexts."}
