{"text": "Samartsidis, Pantelis and Montagna, Silvia and Laird, Angela R and Fox, Peter T and Johnson, Timothy D and Nichols, Thomas E\nRes Synth Methods, 2020\n\n# Title\n\nEstimating the prevalence of missing experiments in a neuroimaging meta-analysis.\n\n# Keywords\n\nmeta-analysis\nneuroimaging\npublication-bias\nzero-truncated modeling\n\n# Abstract\nCoordinate-based meta-analyses (CBMA) allow researchers to combine the results from multiple functional magnetic resonance imaging experiments with the goal of obtaining results that are more likely to generalize. However, the interpretation of CBMA findings can be impaired by the file drawer problem, a type of publication bias that refers to experiments that are carried out but are not published. Using foci per contrast count data from the BrainMap database, we propose a zero-truncated modeling approach that allows us to estimate the prevalence of nonsignificant experiments. We validate our method with simulations and real coordinate data generated from the Human Connectome Project. Application of our method to the data from BrainMap provides evidence for the existence of a file drawer effect, with the rate of missing experiments estimated as at least 6 per 100 reported. The R code that we used is available at https://osf.io/ayhfv/. ", "metadata": {"id": 32860642, "text_md5": "2223d45f1946c961f550ed4cec15407b", "field_positions": {"authors": [0, 124], "journal": [125, 142], "publication_year": [144, 148], "title": [159, 240], "keywords": [254, 321], "abstract": [334, 1282], "body": [1291, 1291]}, "batch": 4, "pmid": 32860642, "doi": "10.1002/jrsm.1448", "pmid_url": "https://pubmed.ncbi.nlm.nih.gov/32860642/", "efetch_url": "https://eutils.ncbi.nlm.nih.gov/entrez/eutils/efetch.fcgi?db=pubmed&id=32860642"}, "display_title": "pmid: <a href=\"https://pubmed.ncbi.nlm.nih.gov/32860642/\">32860642</a>", "list_title": "PMID32860642  Estimating the prevalence of missing experiments in a neuroimaging meta-analysis."}
{"text": "Samartsidis, Pantelis and Montagna, Silvia and Laird, Angela R and Fox, Peter T and Johnson, Timothy D and Nichols, Thomas E\nResearch synthesis methods, 2021\n\n# Title\n\nEstimating the prevalence of missing experiments in a neuroimaging meta-analysis.\n\n# Keywords\n\nmeta-analysis \nneuroimaging \npublication-bias \nzero-truncated modeling \n\n\n# Abstract\n\nCoordinate-based meta-analyses (CBMA) allow researchers to combine the results from multiple functional magnetic resonance imaging experiments with the goal of obtaining results that are more likely to generalize. However, the interpretation of CBMA findings can be impaired by the file drawer problem, a type of publication bias that refers to experiments that are carried out but are not published. Using foci per contrast count data from the BrainMap database, we propose a zero-truncated modeling approach that allows us to estimate the prevalence of nonsignificant experiments. We validate our method with simulations and real coordinate data generated from the Human Connectome Project. Application of our method to the data from BrainMap provides evidence for the existence of a file drawer effect, with the rate of missing experiments estimated as at least 6 per 100 reported. The R code that we used is available at https://osf.io/ayhfv/. \n", "metadata": {"pmid": "32860642", "journal": "Research synthesis methods", "publication_year": "2021", "title": "Estimating the prevalence of missing experiments in a neuroimaging meta-analysis.", "keywords": "meta-analysis \nneuroimaging \npublication-bias \nzero-truncated modeling \n", "abstract": "Coordinate-based meta-analyses (CBMA) allow researchers to combine the results from multiple functional magnetic resonance imaging experiments with the goal of obtaining results that are more likely to generalize. However, the interpretation of CBMA findings can be impaired by the file drawer problem, a type of publication bias that refers to experiments that are carried out but are not published. Using foci per contrast count data from the BrainMap database, we propose a zero-truncated modeling approach that allows us to estimate the prevalence of nonsignificant experiments. We validate our method with simulations and real coordinate data generated from the Human Connectome Project. Application of our method to the data from BrainMap provides evidence for the existence of a file drawer effect, with the rate of missing experiments estimated as at least 6 per 100 reported. The R code that we used is available at https://osf.io/ayhfv/. ", "authors": "Samartsidis, Pantelis and Montagna, Silvia and Laird, Angela R and Fox, Peter T and Johnson, Timothy D and Nichols, Thomas E"}, "display_title": "pmid: <a href=\"https://pubmed.ncbi.nlm.nih.gov/32860642\">32860642</a>", "list_title": "PMID32860642 Estimating the prevalence of missing experiments in a neuroimaging meta-analysis."}
