{"text": "Martinez-Saito, Mario and Gorina, Elena\nHum Brain Mapp, 2022\n\n# Title\n\nLearning under social versus nonsocial uncertainty: A meta-analytic approach.\n\n# Keywords\n\nfunctional magnetic resonance imaging\niterated games\nreinforcement learning\ntheory of mind\n\n# Abstract\nMuch of the uncertainty that clouds our understanding of the world springs from the covert values and intentions held by other people. Thus, it is plausible that specialized mechanisms that compute learning signals under uncertainty of exclusively social origin operate in the brain. To test this hypothesis, we scoured academic databases for neuroimaging studies involving learning under uncertainty, and performed a meta-analysis of brain activation maps that compared learning in the face of social versus nonsocial uncertainty. Although most of the brain activations associated with learning error signals were shared between social and nonsocial conditions, we found some evidence for functional segregation of error signals of exclusively social origin during learning in limited regions of ventrolateral prefrontal cortex and insula. This suggests that most behavioral adaptations to navigate social environments are reused from frontal and subcortical areas processing generic value representation and learning, but that a specialized circuitry might have evolved in prefrontal regions to deal with social context representation and strategic action. ", "metadata": {"id": 35620870, "text_md5": "fe56c77ff8927079be2e55263850e6cd", "field_positions": {"authors": [0, 39], "journal": [40, 54], "publication_year": [56, 60], "title": [71, 148], "keywords": [162, 252], "abstract": [265, 1424], "body": [1433, 1433]}, "batch": 4, "pmid": 35620870, "doi": "10.1002/hbm.25948", "pmid_url": "https://pubmed.ncbi.nlm.nih.gov/35620870/", "efetch_url": "https://eutils.ncbi.nlm.nih.gov/entrez/eutils/efetch.fcgi?db=pubmed&id=35620870"}, "display_title": "pmid: <a href=\"https://pubmed.ncbi.nlm.nih.gov/35620870/\">35620870</a>", "list_title": "PMID35620870  Learning under social versus nonsocial uncertainty: A meta-analytic approach."}
{"text": "Martinez-Saito, Mario and Gorina, Elena\nHuman brain mapping, 2022\n\n# Title\n\nLearning under social versus nonsocial uncertainty: A meta-analytic approach.\n\n# Keywords\n\nfunctional magnetic resonance imaging \niterated games \nreinforcement learning \ntheory of mind \n\n\n# Abstract\n\nMuch of the uncertainty that clouds our understanding of the world springs from the covert values and intentions held by other people. Thus, it is plausible that specialized mechanisms that compute learning signals under uncertainty of exclusively social origin operate in the brain. To test this hypothesis, we scoured academic databases for neuroimaging studies involving learning under uncertainty, and performed a meta-analysis of brain activation maps that compared learning in the face of social versus nonsocial uncertainty. Although most of the brain activations associated with learning error signals were shared between social and nonsocial conditions, we found some evidence for functional segregation of error signals of exclusively social origin during learning in limited regions of ventrolateral prefrontal cortex and insula. This suggests that most behavioral adaptations to navigate social environments are reused from frontal and subcortical areas processing generic value representation and learning, but that a specialized circuitry might have evolved in prefrontal regions to deal with social context representation and strategic action. \n", "metadata": {"pmid": "35620870", "journal": "Human brain mapping", "publication_year": "2022", "title": "Learning under social versus nonsocial uncertainty: A meta-analytic approach.", "keywords": "functional magnetic resonance imaging \niterated games \nreinforcement learning \ntheory of mind \n", "abstract": "Much of the uncertainty that clouds our understanding of the world springs from the covert values and intentions held by other people. Thus, it is plausible that specialized mechanisms that compute learning signals under uncertainty of exclusively social origin operate in the brain. To test this hypothesis, we scoured academic databases for neuroimaging studies involving learning under uncertainty, and performed a meta-analysis of brain activation maps that compared learning in the face of social versus nonsocial uncertainty. Although most of the brain activations associated with learning error signals were shared between social and nonsocial conditions, we found some evidence for functional segregation of error signals of exclusively social origin during learning in limited regions of ventrolateral prefrontal cortex and insula. This suggests that most behavioral adaptations to navigate social environments are reused from frontal and subcortical areas processing generic value representation and learning, but that a specialized circuitry might have evolved in prefrontal regions to deal with social context representation and strategic action. ", "authors": "Martinez-Saito, Mario and Gorina, Elena"}, "display_title": "pmid: <a href=\"https://pubmed.ncbi.nlm.nih.gov/35620870\">35620870</a>", "list_title": "PMID35620870 Learning under social versus nonsocial uncertainty: A meta-analytic approach."}
