{"text": "Goodwill, Alicia M and Low, Li Tong and Fox, Peter T and Fox, P Mickle and Poon, Kenneth K and Bhowmick, Sourav S and Chen, S H Annabel\nBrain Imaging Behav, 2023\n\n# Title\n\nMeta-analytic connectivity modelling of functional magnetic resonance imaging studies in autism spectrum disorders.\n\n# Keywords\n\nAdult\nAutism spectrum disorder\nBrainMap\nMeta-analysis\nMeta-analytic connectivity modelling\nfMRI\n\n# Abstract\nSocial and non-social deficits in autism spectrum disorders (ASD) persist into adulthood and may share common regions of aberrant neural activations. The current meta-analysis investigated activation differences between ASD and neurotypical controls irrespective of task type. Activation likelihood estimation meta-analyses were performed to examine consistent hypo-activated and/or hyper-activated regions for all tasks combined, and for social and non-social tasks separately; meta-analytic connectivity modelling and behavioral/paradigm analyses were performed to examine co-activated regions and associated behaviors. One hundred studies (mean age range\u2009=\u200918-41 years) were included. For all tasks combined, the ASD group showed significant (p\u2009<\u2009.05) hypo-activation in one cluster around the left amygdala (peak -\u200926, -2, -20, volume\u2009=\u20091336 mm ", "metadata": {"id": 36633738, "text_md5": "592713c31c9ea82208d00116672291cb", "field_positions": {"authors": [0, 135], "journal": [136, 155], "publication_year": [157, 161], "title": [172, 287], "keywords": [301, 396], "abstract": [409, 1258], "body": [1267, 1267]}, "batch": 1, "pmid": 36633738, "doi": "10.1007/s11682-022-00754-2", "pmid_url": "https://pubmed.ncbi.nlm.nih.gov/36633738/", "efetch_url": "https://eutils.ncbi.nlm.nih.gov/entrez/eutils/efetch.fcgi?db=pubmed&id=36633738"}, "display_title": "pmid: <a href=\"https://pubmed.ncbi.nlm.nih.gov/36633738/\">36633738</a>", "list_title": "PMID36633738  Meta-analytic connectivity modelling of functional magnetic resonance imaging studies in autism spectrum disorders."}
{"text": "Goodwill, Alicia M and Low, Li Tong and Fox, Peter T and Fox, P Mickle and Poon, Kenneth K and Bhowmick, Sourav S and Chen, S H Annabel\nBrain imaging and behavior, 2023\n\n# Title\n\nMeta-analytic connectivity modelling of functional magnetic resonance imaging studies in autism spectrum disorders.\n\n# Keywords\n\nAdult \nAutism spectrum disorder \nBrainMap \nMeta-analysis \nMeta-analytic connectivity modelling \nfMRI \n\n\n# Abstract\n\nSocial and non-social deficits in autism spectrum disorders (ASD) persist into adulthood and may share common regions of aberrant neural activations. The current meta-analysis investigated activation differences between ASD and neurotypical controls irrespective of task type. Activation likelihood estimation meta-analyses were performed to examine consistent hypo-activated and/or hyper-activated regions for all tasks combined, and for social and non-social tasks separately; meta-analytic connectivity modelling and behavioral/paradigm analyses were performed to examine co-activated regions and associated behaviors. One hundred studies (mean age range\u2009=\u200918-41 years) were included. For all tasks combined, the ASD group showed significant (p\u2009<\u2009.05) hypo-activation in one cluster around the left amygdala (peak -\u200926, -2, -20, volume\u2009=\u20091336 mm \n", "metadata": {"pmid": "36633738", "journal": "Brain imaging and behavior", "publication_year": "2023", "title": "Meta-analytic connectivity modelling of functional magnetic resonance imaging studies in autism spectrum disorders.", "keywords": "Adult \nAutism spectrum disorder \nBrainMap \nMeta-analysis \nMeta-analytic connectivity modelling \nfMRI \n", "abstract": "Social and non-social deficits in autism spectrum disorders (ASD) persist into adulthood and may share common regions of aberrant neural activations. The current meta-analysis investigated activation differences between ASD and neurotypical controls irrespective of task type. Activation likelihood estimation meta-analyses were performed to examine consistent hypo-activated and/or hyper-activated regions for all tasks combined, and for social and non-social tasks separately; meta-analytic connectivity modelling and behavioral/paradigm analyses were performed to examine co-activated regions and associated behaviors. One hundred studies (mean age range\u2009=\u200918-41 years) were included. For all tasks combined, the ASD group showed significant (p\u2009<\u2009.05) hypo-activation in one cluster around the left amygdala (peak -\u200926, -2, -20, volume\u2009=\u20091336 mm ", "authors": "Goodwill, Alicia M and Low, Li Tong and Fox, Peter T and Fox, P Mickle and Poon, Kenneth K and Bhowmick, Sourav S and Chen, S H Annabel"}, "display_title": "pmid: <a href=\"https://pubmed.ncbi.nlm.nih.gov/36633738\">36633738</a>", "list_title": "PMID36633738 Meta-analytic connectivity modelling of functional magnetic resonance imaging studies in autism spectrum disorders."}
