{"text": "Yu, Zheng and Wang, Rong-Rong and Wei, Wei and Liu, Li-Ying and Wen, Chuan-Biao and Yu, Shu-Guang and Guo, Xiao-Li and Yang, Jie\nFrontiers in neuroscience, 2023\n\n# Title\n\nA coordinate-based meta-analysis of acupuncture for chronic pain: Evidence from fMRI studies.\n\n# Keywords\n\nactivation likelihood estimation \nacupuncture \nchronic pain \nfMRI \nsystematic review \n\n\n# Abstract\n\nChronic pain (CP) patients tend to represent aberrant functional brain activity. Acupuncture is an effective clinical treatment for CP, and some fMRI studies were conducted to discover the alternation of brain regions after acupuncture therapy for CP. However, the heterogeneity of neuroimaging studies has prevented researchers from systematically generalizing the central mechanisms of acupuncture in the treatment of CP. We searched bibliographic databases, including PubMed, EMBASE, PsycINFO, Web of Science Core Collection, ScienceDirect, China Academic Journal Network Publishing Database, etc., and trials registration platforms (From inception to September 1 Totally 14 studies with 524 CP patients were included in the study. ALE analysis showed that CP patients presented with decreased ALFF/ReHo in the precuneus, posterior cingulate cortex, right inferior parietal lobule, right superior temporal gyrus, cingulate gyrus, superior frontal gyrus, left medial frontal gyrus including medial prefrontal gurus, left middle frontal gyrus. This ALE meta-analysis pointed out that acupuncture could modulate the default mode network, the frontoparietal network to treat CP. This provided a systematic summary of the neuroimage biomarker of acupuncture for the treatment of CP. PROSPERO, identifier: CRD42021239633. \n", "metadata": {"pmid": "36590302", "journal": "Frontiers in neuroscience", "publication_year": "2023", "title": "A coordinate-based meta-analysis of acupuncture for chronic pain: Evidence from fMRI studies.", "keywords": "activation likelihood estimation \nacupuncture \nchronic pain \nfMRI \nsystematic review \n", "abstract": "Chronic pain (CP) patients tend to represent aberrant functional brain activity. Acupuncture is an effective clinical treatment for CP, and some fMRI studies were conducted to discover the alternation of brain regions after acupuncture therapy for CP. However, the heterogeneity of neuroimaging studies has prevented researchers from systematically generalizing the central mechanisms of acupuncture in the treatment of CP. We searched bibliographic databases, including PubMed, EMBASE, PsycINFO, Web of Science Core Collection, ScienceDirect, China Academic Journal Network Publishing Database, etc., and trials registration platforms (From inception to September 1 Totally 14 studies with 524 CP patients were included in the study. ALE analysis showed that CP patients presented with decreased ALFF/ReHo in the precuneus, posterior cingulate cortex, right inferior parietal lobule, right superior temporal gyrus, cingulate gyrus, superior frontal gyrus, left medial frontal gyrus including medial prefrontal gurus, left middle frontal gyrus. This ALE meta-analysis pointed out that acupuncture could modulate the default mode network, the frontoparietal network to treat CP. This provided a systematic summary of the neuroimage biomarker of acupuncture for the treatment of CP. PROSPERO, identifier: CRD42021239633. ", "authors": "Yu, Zheng and Wang, Rong-Rong and Wei, Wei and Liu, Li-Ying and Wen, Chuan-Biao and Yu, Shu-Guang and Guo, Xiao-Li and Yang, Jie"}, "display_title": "pmid: <a href=\"https://pubmed.ncbi.nlm.nih.gov/36590302\">36590302</a>", "list_title": "PMID36590302 A coordinate-based meta-analysis of acupuncture for chronic pain: Evidence from fMRI studies."}
