{"text": "Smith, Benjamin J and Monterosso, John R and Wakslak, Cheryl J and Bechara, Antoine and Read, Stephen J\nNeurosci Biobehav Rev, 2018\n\n# Title\n\nA meta-analytical review of brain activity associated with intertemporal decisions: Evidence for an anterior-posterior tangibility axis.\n\n# Keywords\n\nAbstraction\nConstrual level theory\nDelay discounting\nMeta-analysis\nPrefrontal cortex\nPsychological distance\nTangibility\nTemporal discounting\n\n# Abstract\nIn temporal discounting experiments, subjects are repeatedly presented with option sets in which they must choose between receiving a small amount of money sooner (SmallerSooner) or a larger amount of money at a more distant point in time (LargerLater). Although over 50 temporal discounting experiments using fMRI are described in literature, there has not been a meta-analysis identifying regions activated when subjects choose SmallerSooner versus LargerLater alternatives. Evidence suggests a prefrontal cortex 'abstraction hierarchy', from abstract planning in more anterior regions to concrete processing in posterior regions. Because abstraction has been linked with making LargerLater choices, we hypothesized an association between LargerLater choices and more anterior prefrontal cortex activity, and an association between SmallerSooner choices and more posterior activity. Across thirteen fMRI temporal discounting studies including 436 subjects, we observed LargerLater activity anterior of SmallerSooner activity, both in the left inferior frontal gyrus pars triangularis, consistent with our pre-registered hypothesis. We call for further work linking temporal discounting and hierarchical processing of abstract and concrete information in the prefrontal cortex. ", "metadata": {"id": 29366699, "text_md5": "14795a242820958135187cb9e9436641", "field_positions": {"authors": [0, 103], "journal": [104, 125], "publication_year": [127, 131], "title": [142, 278], "keywords": [292, 432], "abstract": [445, 1724], "body": [1733, 1733]}, "batch": 3, "pmid": 29366699, "doi": "10.1016/j.neubiorev.2018.01.005", "pmid_url": "https://pubmed.ncbi.nlm.nih.gov/29366699/", "efetch_url": "https://eutils.ncbi.nlm.nih.gov/entrez/eutils/efetch.fcgi?db=pubmed&id=29366699"}, "display_title": "pmid: <a href=\"https://pubmed.ncbi.nlm.nih.gov/29366699/\">29366699</a>", "list_title": "PMID29366699  A meta-analytical review of brain activity associated with intertemporal decisions: Evidence for an anterior-posterior tangibility axis."}
{"text": "Smith, Benjamin J and Monterosso, John R and Wakslak, Cheryl J and Bechara, Antoine and Read, Stephen J\nNeuroscience and biobehavioral reviews, 2019\n\n# Title\n\nA meta-analytical review of brain activity associated with intertemporal decisions: Evidence for an anterior-posterior tangibility axis.\n\n# Keywords\n\nAbstraction \nConstrual level theory \nDelay discounting \nMeta-analysis \nPrefrontal cortex \nPsychological distance \nTangibility \nTemporal discounting \n\n\n# Abstract\n\nIn temporal discounting experiments, subjects are repeatedly presented with option sets in which they must choose between receiving a small amount of money sooner (SmallerSooner) or a larger amount of money at a more distant point in time (LargerLater). Although over 50 temporal discounting experiments using fMRI are described in literature, there has not been a meta-analysis identifying regions activated when subjects choose SmallerSooner versus LargerLater alternatives. Evidence suggests a prefrontal cortex 'abstraction hierarchy', from abstract planning in more anterior regions to concrete processing in posterior regions. Because abstraction has been linked with making LargerLater choices, we hypothesized an association between LargerLater choices and more anterior prefrontal cortex activity, and an association between SmallerSooner choices and more posterior activity. Across thirteen fMRI temporal discounting studies including 436 subjects, we observed LargerLater activity anterior of SmallerSooner activity, both in the left inferior frontal gyrus pars triangularis, consistent with our pre-registered hypothesis. We call for further work linking temporal discounting and hierarchical processing of abstract and concrete information in the prefrontal cortex. \n", "metadata": {"pmid": "29366699", "journal": "Neuroscience and biobehavioral reviews", "publication_year": "2019", "title": "A meta-analytical review of brain activity associated with intertemporal decisions: Evidence for an anterior-posterior tangibility axis.", "keywords": "Abstraction \nConstrual level theory \nDelay discounting \nMeta-analysis \nPrefrontal cortex \nPsychological distance \nTangibility \nTemporal discounting \n", "abstract": "In temporal discounting experiments, subjects are repeatedly presented with option sets in which they must choose between receiving a small amount of money sooner (SmallerSooner) or a larger amount of money at a more distant point in time (LargerLater). Although over 50 temporal discounting experiments using fMRI are described in literature, there has not been a meta-analysis identifying regions activated when subjects choose SmallerSooner versus LargerLater alternatives. Evidence suggests a prefrontal cortex 'abstraction hierarchy', from abstract planning in more anterior regions to concrete processing in posterior regions. Because abstraction has been linked with making LargerLater choices, we hypothesized an association between LargerLater choices and more anterior prefrontal cortex activity, and an association between SmallerSooner choices and more posterior activity. Across thirteen fMRI temporal discounting studies including 436 subjects, we observed LargerLater activity anterior of SmallerSooner activity, both in the left inferior frontal gyrus pars triangularis, consistent with our pre-registered hypothesis. We call for further work linking temporal discounting and hierarchical processing of abstract and concrete information in the prefrontal cortex. ", "authors": "Smith, Benjamin J and Monterosso, John R and Wakslak, Cheryl J and Bechara, Antoine and Read, Stephen J"}, "display_title": "pmid: <a href=\"https://pubmed.ncbi.nlm.nih.gov/29366699\">29366699</a>", "list_title": "PMID29366699 A meta-analytical review of brain activity associated with intertemporal decisions: Evidence for an anterior-posterior tangibility axis."}
