{"text": "Huang, Yuefeng and Hullfish, Jeffrey and De Ridder, Dirk and Vanneste, Sven\nBrain Struct Funct, 2019\n\n# Title\n\nMeta-analysis of functional subdivisions within human posteromedial cortex.\n\n# Keywords\n\nDefault mode network\nPosterior cingulate cortex\nPrecuneus\nRetrosplenial cortex\n\n# Abstract\nThe posteromedial cortex (PMC)-comprising posterior cingulate cortex (PCC), retrosplenial cortex (RSC), and the precuneus (PrC)-is perhaps best known for its involvement in the default mode network. There is no consensus regarding the specific functions of PMC, however, and its component regions each exhibit distinct, but partially overlapping functional profiles. To date, there has been minimal effort to disentangle the functions of these regions. In the present study, we use Neurosynth ( http://neurosynth.org ) to conduct an unbiased meta-analysis of the PMC based on fMRI coactivation and semantic information extracted from 11,406 studies. Our analyses revealed six PMC clusters with distinct functional profiles: superior and inferior dorsal PCC, anterior and posterior PrC, ventral PCC, and RSC. We discuss these findings in the context of the existing literature and suggest several fruitful avenues for continued research. ", "metadata": {"id": 30367247, "text_md5": "43b900491ec31a96ee8783648af4af63", "field_positions": {"authors": [0, 75], "journal": [76, 94], "publication_year": [96, 100], "title": [111, 186], "keywords": [200, 278], "abstract": [291, 1228], "body": [1237, 1237]}, "batch": 3, "pmid": 30367247, "doi": "10.1007/s00429-018-1781-3", "pmid_url": "https://pubmed.ncbi.nlm.nih.gov/30367247/", "efetch_url": "https://eutils.ncbi.nlm.nih.gov/entrez/eutils/efetch.fcgi?db=pubmed&id=30367247"}, "display_title": "pmid: <a href=\"https://pubmed.ncbi.nlm.nih.gov/30367247/\">30367247</a>", "list_title": "PMID30367247  Meta-analysis of functional subdivisions within human posteromedial cortex."}
{"text": "Huang, Yuefeng and Hullfish, Jeffrey and De Ridder, Dirk and Vanneste, Sven\nBrain structure & function, 2019\n\n# Title\n\nMeta-analysis of functional subdivisions within human posteromedial cortex.\n\n# Keywords\n\nDefault mode network \nPosterior cingulate cortex \nPrecuneus \nRetrosplenial cortex \n\n\n# Abstract\n\nThe posteromedial cortex (PMC)-comprising posterior cingulate cortex (PCC), retrosplenial cortex (RSC), and the precuneus (PrC)-is perhaps best known for its involvement in the default mode network. There is no consensus regarding the specific functions of PMC, however, and its component regions each exhibit distinct, but partially overlapping functional profiles. To date, there has been minimal effort to disentangle the functions of these regions. In the present study, we use Neurosynth ( http://neurosynth.org ) to conduct an unbiased meta-analysis of the PMC based on fMRI coactivation and semantic information extracted from 11,406 studies. Our analyses revealed six PMC clusters with distinct functional profiles: superior and inferior dorsal PCC, anterior and posterior PrC, ventral PCC, and RSC. We discuss these findings in the context of the existing literature and suggest several fruitful avenues for continued research. \n", "metadata": {"pmid": "30367247", "journal": "Brain structure & function", "publication_year": "2019", "title": "Meta-analysis of functional subdivisions within human posteromedial cortex.", "keywords": "Default mode network \nPosterior cingulate cortex \nPrecuneus \nRetrosplenial cortex \n", "abstract": "The posteromedial cortex (PMC)-comprising posterior cingulate cortex (PCC), retrosplenial cortex (RSC), and the precuneus (PrC)-is perhaps best known for its involvement in the default mode network. There is no consensus regarding the specific functions of PMC, however, and its component regions each exhibit distinct, but partially overlapping functional profiles. To date, there has been minimal effort to disentangle the functions of these regions. In the present study, we use Neurosynth ( http://neurosynth.org ) to conduct an unbiased meta-analysis of the PMC based on fMRI coactivation and semantic information extracted from 11,406 studies. Our analyses revealed six PMC clusters with distinct functional profiles: superior and inferior dorsal PCC, anterior and posterior PrC, ventral PCC, and RSC. We discuss these findings in the context of the existing literature and suggest several fruitful avenues for continued research. ", "authors": "Huang, Yuefeng and Hullfish, Jeffrey and De Ridder, Dirk and Vanneste, Sven"}, "display_title": "pmid: <a href=\"https://pubmed.ncbi.nlm.nih.gov/30367247\">30367247</a>", "list_title": "PMID30367247 Meta-analysis of functional subdivisions within human posteromedial cortex."}
