{"text": "Eres, Robert and Louis, Winnifred R and Molenberghs, Pascal\nSoc Neurosci, 2018\n\n# Title\n\nCommon and distinct neural networks involved in fMRI studies investigating morality: an ALE meta-analysis.\n\n# Keywords\n\nActivation likelihood estimation (ALE)\nmeta-analysis\nmoral emotions\nmoral judgment and decision making\nmorality\n\n# Abstract\nMorality is an important social construct necessary for understanding what is right and wrong. Neuroimaging studies investigating morality have used a wide variety of paradigms and implicated many different brain areas. Yet, it remains unclear whether differences amongst morality tasks are the cause for such heterogeneous findings. Therefore, in the present study, a series of activation likelihood estimation (ALE) meta-analyses were conducted on 123 datasets (inclusive of 1963 participants) to address this question. The ALE meta-analyses revealed a series of common brain areas associated with all moral tasks, including medial prefrontal cortex, lateral orbitofrontal cortex, amygdala, temporoparietal junction, and precuneus. However, individual and contrast analyses also revealed unique networks associated with each moral modality, suggesting that different moral tasks recruit specialised brain regions. ", "metadata": {"id": 28724332, "text_md5": "6b1c737c4e143a7e26d1c7466b8325a5", "field_positions": {"authors": [0, 59], "journal": [60, 72], "publication_year": [74, 78], "title": [89, 195], "keywords": [209, 320], "abstract": [333, 1249], "body": [1258, 1258]}, "batch": 2, "pmid": 28724332, "doi": "10.1080/17470919.2017.1357657", "pmid_url": "https://pubmed.ncbi.nlm.nih.gov/28724332/", "efetch_url": "https://eutils.ncbi.nlm.nih.gov/entrez/eutils/efetch.fcgi?db=pubmed&id=28724332"}, "display_title": "pmid: <a href=\"https://pubmed.ncbi.nlm.nih.gov/28724332/\">28724332</a>", "list_title": "PMID28724332  Common and distinct neural networks involved in fMRI studies investigating morality: an ALE meta-analysis."}
{"text": "Eres, Robert and Louis, Winnifred R and Molenberghs, Pascal\nSocial neuroscience, 2018\n\n# Title\n\nCommon and distinct neural networks involved in fMRI studies investigating morality: an ALE meta-analysis.\n\n# Keywords\n\nActivation likelihood estimation (ALE) \nmeta-analysis \nmoral emotions \nmoral judgment and decision making \nmorality \n\n\n# Abstract\n\nMorality is an important social construct necessary for understanding what is right and wrong. Neuroimaging studies investigating morality have used a wide variety of paradigms and implicated many different brain areas. Yet, it remains unclear whether differences amongst morality tasks are the cause for such heterogeneous findings. Therefore, in the present study, a series of activation likelihood estimation (ALE) meta-analyses were conducted on 123 datasets (inclusive of 1963 participants) to address this question. The ALE meta-analyses revealed a series of common brain areas associated with all moral tasks, including medial prefrontal cortex, lateral orbitofrontal cortex, amygdala, temporoparietal junction, and precuneus. However, individual and contrast analyses also revealed unique networks associated with each moral modality, suggesting that different moral tasks recruit specialised brain regions. \n", "metadata": {"pmid": "28724332", "journal": "Social neuroscience", "publication_year": "2018", "title": "Common and distinct neural networks involved in fMRI studies investigating morality: an ALE meta-analysis.", "keywords": "Activation likelihood estimation (ALE) \nmeta-analysis \nmoral emotions \nmoral judgment and decision making \nmorality \n", "abstract": "Morality is an important social construct necessary for understanding what is right and wrong. Neuroimaging studies investigating morality have used a wide variety of paradigms and implicated many different brain areas. Yet, it remains unclear whether differences amongst morality tasks are the cause for such heterogeneous findings. Therefore, in the present study, a series of activation likelihood estimation (ALE) meta-analyses were conducted on 123 datasets (inclusive of 1963 participants) to address this question. The ALE meta-analyses revealed a series of common brain areas associated with all moral tasks, including medial prefrontal cortex, lateral orbitofrontal cortex, amygdala, temporoparietal junction, and precuneus. However, individual and contrast analyses also revealed unique networks associated with each moral modality, suggesting that different moral tasks recruit specialised brain regions. ", "authors": "Eres, Robert and Louis, Winnifred R and Molenberghs, Pascal"}, "display_title": "pmid: <a href=\"https://pubmed.ncbi.nlm.nih.gov/28724332\">28724332</a>", "list_title": "PMID28724332 Common and distinct neural networks involved in fMRI studies investigating morality: an ALE meta-analysis."}
