{"text": "Zhang, Ruibin and Picchioni, Marco and Allen, Paul and Toulopoulou, Timothea\nSchizophr Bull, 2016\n\n# Title\n\nWorking Memory in Unaffected Relatives of Patients With Schizophrenia: A Meta-Analysis of Functional Magnetic Resonance Imaging Studies.\n\n# Keywords\n\ndorsolateral prefrontal cortex\nendophenotype\nfunctional magnetic resonance imaging (fMRI)\nintermediate phenotype\nmeta-analyses\n\n# Abstract\nWorking memory deficits, a core cognitive feature of schizophrenia may arise from dysfunction in the frontal and parietal cortices. Numerous studies have also found abnormal neural activation during working memory tasks in patients' unaffected relatives. The aim of this study was to systematically identify and anatomically localize the evidence for those activation differences across all eligible studies. Fifteen functional magnetic resonance imaging (fMRI) manuscripts, containing 16 samples of 289 unaffected relatives of patients with schizophrenia, and 358 healthy controls were identified that met our inclusion criteria: (1) used a working memory task; and (2) reported standard space coordinates. Activation likelihood estimation (ALE) identified convergence across studies. Compared to healthy controls, patients' unaffected relatives showed decreases in neural activation in the right middle frontal gyrus (BA9), as well as right inferior frontal gyrus (BA44). Increased activation was seen in relatives in the right frontopolar (BA10), left inferior parietal lobe (BA40), and thalamus bilaterally. These results suggest that the familial risk of schizophrenia is expressed in changes in neural activation in the unaffected relatives in the cortical-subcortical working memory network that includes, but is not restricted to the middle prefrontal cortex. ", "metadata": {"id": 26738528, "text_md5": "21bd51d33853006154952262e437833d", "field_positions": {"authors": [0, 76], "journal": [77, 91], "publication_year": [93, 97], "title": [108, 244], "keywords": [258, 384], "abstract": [397, 1765], "body": [1774, 1774]}, "batch": 1, "pmid": 26738528, "doi": "10.1093/schbul/sbv221", "pmid_url": "https://pubmed.ncbi.nlm.nih.gov/26738528/", "efetch_url": "https://eutils.ncbi.nlm.nih.gov/entrez/eutils/efetch.fcgi?db=pubmed&id=26738528"}, "display_title": "pmid: <a href=\"https://pubmed.ncbi.nlm.nih.gov/26738528/\">26738528</a>", "list_title": "PMID26738528  Working Memory in Unaffected Relatives of Patients With Schizophrenia: A Meta-Analysis of Functional Magnetic Resonance Imaging Studies."}
{"text": "Zhang, Ruibin and Picchioni, Marco and Allen, Paul and Toulopoulou, Timothea\nSchizophrenia bulletin, 2017\n\n# Title\n\nWorking Memory in Unaffected Relatives of Patients With Schizophrenia: A Meta-Analysis of Functional Magnetic Resonance Imaging Studies.\n\n# Keywords\n\ndorsolateral prefrontal cortex \nendophenotype \nfunctional magnetic resonance imaging (fMRI) \nintermediate phenotype \nmeta-analyses \n\n\n# Abstract\n\nWorking memory deficits, a core cognitive feature of schizophrenia may arise from dysfunction in the frontal and parietal cortices. Numerous studies have also found abnormal neural activation during working memory tasks in patients' unaffected relatives. The aim of this study was to systematically identify and anatomically localize the evidence for those activation differences across all eligible studies. Fifteen functional magnetic resonance imaging (fMRI) manuscripts, containing 16 samples of 289 unaffected relatives of patients with schizophrenia, and 358 healthy controls were identified that met our inclusion criteria: (1) used a working memory task; and (2) reported standard space coordinates. Activation likelihood estimation (ALE) identified convergence across studies. Compared to healthy controls, patients' unaffected relatives showed decreases in neural activation in the right middle frontal gyrus (BA9), as well as right inferior frontal gyrus (BA44). Increased activation was seen in relatives in the right frontopolar (BA10), left inferior parietal lobe (BA40), and thalamus bilaterally. These results suggest that the familial risk of schizophrenia is expressed in changes in neural activation in the unaffected relatives in the cortical-subcortical working memory network that includes, but is not restricted to the middle prefrontal cortex. \n", "metadata": {"pmid": "26738528", "journal": "Schizophrenia bulletin", "publication_year": "2017", "title": "Working Memory in Unaffected Relatives of Patients With Schizophrenia: A Meta-Analysis of Functional Magnetic Resonance Imaging Studies.", "keywords": "dorsolateral prefrontal cortex \nendophenotype \nfunctional magnetic resonance imaging (fMRI) \nintermediate phenotype \nmeta-analyses \n", "abstract": "Working memory deficits, a core cognitive feature of schizophrenia may arise from dysfunction in the frontal and parietal cortices. Numerous studies have also found abnormal neural activation during working memory tasks in patients' unaffected relatives. The aim of this study was to systematically identify and anatomically localize the evidence for those activation differences across all eligible studies. Fifteen functional magnetic resonance imaging (fMRI) manuscripts, containing 16 samples of 289 unaffected relatives of patients with schizophrenia, and 358 healthy controls were identified that met our inclusion criteria: (1) used a working memory task; and (2) reported standard space coordinates. Activation likelihood estimation (ALE) identified convergence across studies. Compared to healthy controls, patients' unaffected relatives showed decreases in neural activation in the right middle frontal gyrus (BA9), as well as right inferior frontal gyrus (BA44). Increased activation was seen in relatives in the right frontopolar (BA10), left inferior parietal lobe (BA40), and thalamus bilaterally. These results suggest that the familial risk of schizophrenia is expressed in changes in neural activation in the unaffected relatives in the cortical-subcortical working memory network that includes, but is not restricted to the middle prefrontal cortex. ", "authors": "Zhang, Ruibin and Picchioni, Marco and Allen, Paul and Toulopoulou, Timothea"}, "display_title": "pmid: <a href=\"https://pubmed.ncbi.nlm.nih.gov/26738528\">26738528</a>", "list_title": "PMID26738528 Working Memory in Unaffected Relatives of Patients With Schizophrenia: A Meta-Analysis of Functional Magnetic Resonance Imaging Studies."}
