{"text": "Leroy, Arnaud and Amad, Ali and D'Hondt, Fabien and Pins, Delphine and Jaafari, Nematollah and Thomas, Pierre and Jardri, Renaud\nSchizophr Res, 2020\n\n# Title\n\nReward anticipation in schizophrenia: A coordinate-based meta-analysis.\n\n# Keywords\n\nAntipsychotics\nMeta-analysis\nReward\nSalience\nSchizophrenia\nfMRI\n\n# Abstract\nReward processing impairments have been linked with positive and negative symptoms of schizophrenia. Here, we performed a coordinate-based meta-analysis that combined eleven BOLD-fMRI studies comparing reward anticipation signals between schizophrenia patients and healthy controls. We observed a reduced difference in activation in schizophrenia patients within a frontal-striatal network. Meta-regressions revealed that this functional signature was linked to the severity of psychotic symptoms and persisted even after controlling for the dose of antipsychotic medications. ", "metadata": {"id": 31948895, "text_md5": "7e42bfb2e637abc2784f3dc8eb713f79", "field_positions": {"authors": [0, 128], "journal": [129, 142], "publication_year": [144, 148], "title": [159, 230], "keywords": [244, 307], "abstract": [320, 897], "body": [906, 906]}, "batch": 2, "pmid": 31948895, "doi": "10.1016/j.schres.2019.12.041", "pmid_url": "https://pubmed.ncbi.nlm.nih.gov/31948895/", "efetch_url": "https://eutils.ncbi.nlm.nih.gov/entrez/eutils/efetch.fcgi?db=pubmed&id=31948895"}, "display_title": "pmid: <a href=\"https://pubmed.ncbi.nlm.nih.gov/31948895/\">31948895</a>", "list_title": "PMID31948895  Reward anticipation in schizophrenia: A coordinate-based meta-analysis."}
{"text": "Leroy, Arnaud and Amad, Ali and D'Hondt, Fabien and Pins, Delphine and Jaafari, Nematollah and Thomas, Pierre and Jardri, Renaud\nSchizophrenia research, 2021\n\n# Title\n\nReward anticipation in schizophrenia: A coordinate-based meta-analysis.\n\n# Keywords\n\nAntipsychotics \nMeta-analysis \nReward \nSalience \nSchizophrenia \nfMRI \n\n\n# Abstract\n\nReward processing impairments have been linked with positive and negative symptoms of schizophrenia. Here, we performed a coordinate-based meta-analysis that combined eleven BOLD-fMRI studies comparing reward anticipation signals between schizophrenia patients and healthy controls. We observed a reduced difference in activation in schizophrenia patients within a frontal-striatal network. Meta-regressions revealed that this functional signature was linked to the severity of psychotic symptoms and persisted even after controlling for the dose of antipsychotic medications. \n", "metadata": {"pmid": "31948895", "journal": "Schizophrenia research", "publication_year": "2021", "title": "Reward anticipation in schizophrenia: A coordinate-based meta-analysis.", "keywords": "Antipsychotics \nMeta-analysis \nReward \nSalience \nSchizophrenia \nfMRI \n", "abstract": "Reward processing impairments have been linked with positive and negative symptoms of schizophrenia. Here, we performed a coordinate-based meta-analysis that combined eleven BOLD-fMRI studies comparing reward anticipation signals between schizophrenia patients and healthy controls. We observed a reduced difference in activation in schizophrenia patients within a frontal-striatal network. Meta-regressions revealed that this functional signature was linked to the severity of psychotic symptoms and persisted even after controlling for the dose of antipsychotic medications. ", "authors": "Leroy, Arnaud and Amad, Ali and D'Hondt, Fabien and Pins, Delphine and Jaafari, Nematollah and Thomas, Pierre and Jardri, Renaud"}, "display_title": "pmid: <a href=\"https://pubmed.ncbi.nlm.nih.gov/31948895\">31948895</a>", "list_title": "PMID31948895 Reward anticipation in schizophrenia: A coordinate-based meta-analysis."}
