{"text": "Saberi, Amin and Mohammadi, Esmaeil and Zarei, Mojtaba and Eickhoff, Simon B and Tahmasian, Masoud\nBrain Imaging Behav, 2022\n\n# Title\n\nStructural and functional neuroimaging of late-life depression: a coordinate-based meta-analysis.\n\n# Keywords\n\nActivation likelihood estimation\nFunctional magnetic resonance imaging\nLate-life depression\nPositron emission tomography\nVoxel-based morphometry\n\n# Abstract\nSeveral neuroimaging studies have investigated localized aberrations in brain structure, function or connectivity in late-life depression, but the ensuing results are equivocal and often conflicting. Here, we provide a quantitative consolidation of neuroimaging in late-life depression using coordinate-based meta-analysis by searching multiple databases up to March 2020. Our search revealed 3252 unique records, among which we identified 32 eligible whole-brain neuroimaging publications comparing 674 patients with 568 controls. The peak coordinates of group comparisons between the patients and the controls were extracted and then analyzed using activation likelihood estimation method. Our sufficiently powered analysis on all the experiments, and more homogenous subsections of the data (patients\u2009>\u2009controls, controls\u2009>\u2009patients, and functional imaging experiments) revealed no significant convergent regional abnormality in late-life depression. This inconsistency might be due\u00a0to clinical and biological heterogeneity of LLD, as well as experimental (e.g., choice of tasks, image modalities) and analytic flexibility (e.g., preprocessing and analytic parameters), and distributed patterns of neural abnormalities. Our findings highlight the importance of clinical/biological heterogeneity of late-life depression, in addition to the need for more reproducible research by using pre-registered and standardized protocols on more homogenous populations to identify potential consistent brain abnormalities in late-life depression. ", "metadata": {"id": 34331655, "text_md5": "d2b40cc0fe9e8671b27cfb409ba37ebe", "field_positions": {"authors": [0, 98], "journal": [99, 118], "publication_year": [120, 124], "title": [135, 232], "keywords": [246, 390], "abstract": [403, 1941], "body": [1950, 1950]}, "batch": 4, "pmid": 34331655, "doi": "10.1007/s11682-021-00494-9", "pmid_url": "https://pubmed.ncbi.nlm.nih.gov/34331655/", "efetch_url": "https://eutils.ncbi.nlm.nih.gov/entrez/eutils/efetch.fcgi?db=pubmed&id=34331655"}, "display_title": "pmid: <a href=\"https://pubmed.ncbi.nlm.nih.gov/34331655/\">34331655</a>", "list_title": "PMID34331655  Structural and functional neuroimaging of late-life depression: a coordinate-based meta-analysis."}
{"text": "Saberi, Amin and Mohammadi, Esmaeil and Zarei, Mojtaba and Eickhoff, Simon B and Tahmasian, Masoud\nBrain imaging and behavior, 2022\n\n# Title\n\nStructural and functional neuroimaging of late-life depression: a coordinate-based meta-analysis.\n\n# Keywords\n\nActivation likelihood estimation \nFunctional magnetic resonance imaging \nLate-life depression \nPositron emission tomography \nVoxel-based morphometry \n\n\n# Abstract\n\nSeveral neuroimaging studies have investigated localized aberrations in brain structure, function or connectivity in late-life depression, but the ensuing results are equivocal and often conflicting. Here, we provide a quantitative consolidation of neuroimaging in late-life depression using coordinate-based meta-analysis by searching multiple databases up to March 2020. Our search revealed 3252 unique records, among which we identified 32 eligible whole-brain neuroimaging publications comparing 674 patients with 568 controls. The peak coordinates of group comparisons between the patients and the controls were extracted and then analyzed using activation likelihood estimation method. Our sufficiently powered analysis on all the experiments, and more homogenous subsections of the data (patients\u2009>\u2009controls, controls\u2009>\u2009patients, and functional imaging experiments) revealed no significant convergent regional abnormality in late-life depression. This inconsistency might be due\u00a0to clinical and biological heterogeneity of LLD, as well as experimental (e.g., choice of tasks, image modalities) and analytic flexibility (e.g., preprocessing and analytic parameters), and distributed patterns of neural abnormalities. Our findings highlight the importance of clinical/biological heterogeneity of late-life depression, in addition to the need for more reproducible research by using pre-registered and standardized protocols on more homogenous populations to identify potential consistent brain abnormalities in late-life depression. \n", "metadata": {"pmid": "34331655", "journal": "Brain imaging and behavior", "publication_year": "2022", "title": "Structural and functional neuroimaging of late-life depression: a coordinate-based meta-analysis.", "keywords": "Activation likelihood estimation \nFunctional magnetic resonance imaging \nLate-life depression \nPositron emission tomography \nVoxel-based morphometry \n", "abstract": "Several neuroimaging studies have investigated localized aberrations in brain structure, function or connectivity in late-life depression, but the ensuing results are equivocal and often conflicting. Here, we provide a quantitative consolidation of neuroimaging in late-life depression using coordinate-based meta-analysis by searching multiple databases up to March 2020. Our search revealed 3252 unique records, among which we identified 32 eligible whole-brain neuroimaging publications comparing 674 patients with 568 controls. The peak coordinates of group comparisons between the patients and the controls were extracted and then analyzed using activation likelihood estimation method. Our sufficiently powered analysis on all the experiments, and more homogenous subsections of the data (patients\u2009>\u2009controls, controls\u2009>\u2009patients, and functional imaging experiments) revealed no significant convergent regional abnormality in late-life depression. This inconsistency might be due\u00a0to clinical and biological heterogeneity of LLD, as well as experimental (e.g., choice of tasks, image modalities) and analytic flexibility (e.g., preprocessing and analytic parameters), and distributed patterns of neural abnormalities. Our findings highlight the importance of clinical/biological heterogeneity of late-life depression, in addition to the need for more reproducible research by using pre-registered and standardized protocols on more homogenous populations to identify potential consistent brain abnormalities in late-life depression. ", "authors": "Saberi, Amin and Mohammadi, Esmaeil and Zarei, Mojtaba and Eickhoff, Simon B and Tahmasian, Masoud"}, "display_title": "pmid: <a href=\"https://pubmed.ncbi.nlm.nih.gov/34331655\">34331655</a>", "list_title": "PMID34331655 Structural and functional neuroimaging of late-life depression: a coordinate-based meta-analysis."}
