{"text": "Cargnelutti, Elisa and Tomasino, Barbara and Fabbro, Franco\nFront Hum Neurosci, 2021\n\n# Title\n\nEffects of Linguistic Distance on Second Language Brain Activations in Bilinguals: An Exploratory Coordinate-Based Meta-Analysis.\n\n# Keywords\n\nGinger-ALE meta-analysis\nage of appropriation (AoA)\nbilingualism\nfMRI\nlanguage families\nlinguistic distance\n\n# Abstract\nIn this quantitative meta-analysis, we used the activation likelihood estimation (ALE) approach to address the effects of linguistic distance between first (L1) and second (L2) languages on language-related brain activations. In particular, we investigated how L2-related networks may change in response to linguistic distance from L1. Thus, we examined L2 brain activations in two groups of participants with English as L2 and either (i) a European language (European group,  ", "metadata": {"id": 35069147, "text_md5": "9d163302d58f0eac5e5afb9b5bd19ba0", "field_positions": {"authors": [0, 59], "journal": [60, 78], "publication_year": [80, 84], "title": [95, 224], "keywords": [238, 345], "abstract": [358, 835], "body": [844, 844]}, "batch": 3, "pmid": 35069147, "doi": "10.3389/fnhum.2021.744489", "pmid_url": "https://pubmed.ncbi.nlm.nih.gov/35069147/", "efetch_url": "https://eutils.ncbi.nlm.nih.gov/entrez/eutils/efetch.fcgi?db=pubmed&id=35069147"}, "display_title": "pmid: <a href=\"https://pubmed.ncbi.nlm.nih.gov/35069147/\">35069147</a>", "list_title": "PMID35069147  Effects of Linguistic Distance on Second Language Brain Activations in Bilinguals: An Exploratory Coordinate-Based Meta-Analysis."}
{"text": "Cargnelutti, Elisa and Tomasino, Barbara and Fabbro, Franco\nFrontiers in human neuroscience, 2022\n\n# Title\n\nEffects of Linguistic Distance on Second Language Brain Activations in Bilinguals: An Exploratory Coordinate-Based Meta-Analysis.\n\n# Keywords\n\nGinger-ALE meta-analysis \nage of appropriation (AoA) \nbilingualism \nfMRI \nlanguage families \nlinguistic distance \n\n\n# Abstract\n\nIn this quantitative meta-analysis, we used the activation likelihood estimation (ALE) approach to address the effects of linguistic distance between first (L1) and second (L2) languages on language-related brain activations. In particular, we investigated how L2-related networks may change in response to linguistic distance from L1. Thus, we examined L2 brain activations in two groups of participants with English as L2 and either (i) a European language (European group,  \n", "metadata": {"pmid": "35069147", "journal": "Frontiers in human neuroscience", "publication_year": "2022", "title": "Effects of Linguistic Distance on Second Language Brain Activations in Bilinguals: An Exploratory Coordinate-Based Meta-Analysis.", "keywords": "Ginger-ALE meta-analysis \nage of appropriation (AoA) \nbilingualism \nfMRI \nlanguage families \nlinguistic distance \n", "abstract": "In this quantitative meta-analysis, we used the activation likelihood estimation (ALE) approach to address the effects of linguistic distance between first (L1) and second (L2) languages on language-related brain activations. In particular, we investigated how L2-related networks may change in response to linguistic distance from L1. Thus, we examined L2 brain activations in two groups of participants with English as L2 and either (i) a European language (European group,  ", "authors": "Cargnelutti, Elisa and Tomasino, Barbara and Fabbro, Franco"}, "display_title": "pmid: <a href=\"https://pubmed.ncbi.nlm.nih.gov/35069147\">35069147</a>", "list_title": "PMID35069147 Effects of Linguistic Distance on Second Language Brain Activations in Bilinguals: An Exploratory Coordinate-Based Meta-Analysis."}
