{"text": "Lindquist, Kristen A and Satpute, Ajay B and Wager, Tor D and Weber, Jochen and Barrett, Lisa Feldman\nCereb Cortex, 2016\n\n# Title\n\nThe Brain Basis of Positive and Negative Affect: Evidence from a Meta-Analysis of the Human Neuroimaging Literature.\n\n# Keywords\n\naffect\nmeta-analysis\nneuroimaging\nvalence\nvalue\n\n# Abstract\nThe ability to experience pleasant or unpleasant feelings or to represent objects as \"positive\" or \"negative\" is known as representing hedonic \"valence.\" Although scientists overwhelmingly agree that valence is a basic psychological phenomenon, debate continues about how to best conceptualize it scientifically. We used a meta-analysis of 397 functional magnetic resonance imaging (fMRI) and positron emission tomography studies (containing 914 experimental contrasts and 6827 participants) to test 3 competing hypotheses about the brain basis of valence: the bipolarity hypothesis that positive and negative affect are supported by a brain system that monotonically increases and/or decreases along the valence dimension, the bivalent hypothesis that positive and negative affect are supported by independent brain systems, and the affective workspace hypothesis that positive and negative affect are supported by a flexible set of valence-general regions. We found little evidence for the bipolar or bivalent hypotheses. Findings instead supported the hypothesis that, at the level of brain activity measurable by fMRI, valence is flexibly implemented across instances by a set of valence-general limbic and paralimbic brain regions. ", "metadata": {"id": 25631056, "text_md5": "06ce3aef66019faf257d1aee36816471", "field_positions": {"authors": [0, 101], "journal": [102, 114], "publication_year": [116, 120], "title": [131, 247], "keywords": [261, 308], "abstract": [321, 1558], "body": [1567, 1567]}, "batch": 1, "pmid": 25631056, "doi": "10.1093/cercor/bhv001", "pmid_url": "https://pubmed.ncbi.nlm.nih.gov/25631056/", "efetch_url": "https://eutils.ncbi.nlm.nih.gov/entrez/eutils/efetch.fcgi?db=pubmed&id=25631056"}, "display_title": "pmid: <a href=\"https://pubmed.ncbi.nlm.nih.gov/25631056/\">25631056</a>", "list_title": "PMID25631056  The Brain Basis of Positive and Negative Affect: Evidence from a Meta-Analysis of the Human Neuroimaging Literature."}
{"text": "Lindquist, Kristen A and Satpute, Ajay B and Wager, Tor D and Weber, Jochen and Barrett, Lisa Feldman\nCerebral cortex (New York, N.Y. : 1991), 2016\n\n# Title\n\nThe Brain Basis of Positive and Negative Affect: Evidence from a Meta-Analysis of the Human Neuroimaging Literature.\n\n# Keywords\n\naffect \nmeta-analysis \nneuroimaging \nvalence \nvalue \n\n\n# Abstract\n\nThe ability to experience pleasant or unpleasant feelings or to represent objects as \"positive\" or \"negative\" is known as representing hedonic \"valence.\" Although scientists overwhelmingly agree that valence is a basic psychological phenomenon, debate continues about how to best conceptualize it scientifically. We used a meta-analysis of 397 functional magnetic resonance imaging (fMRI) and positron emission tomography studies (containing 914 experimental contrasts and 6827 participants) to test 3 competing hypotheses about the brain basis of valence: the bipolarity hypothesis that positive and negative affect are supported by a brain system that monotonically increases and/or decreases along the valence dimension, the bivalent hypothesis that positive and negative affect are supported by independent brain systems, and the affective workspace hypothesis that positive and negative affect are supported by a flexible set of valence-general regions. We found little evidence for the bipolar or bivalent hypotheses. Findings instead supported the hypothesis that, at the level of brain activity measurable by fMRI, valence is flexibly implemented across instances by a set of valence-general limbic and paralimbic brain regions. \n", "metadata": {"pmid": "25631056", "journal": "Cerebral cortex (New York, N.Y. : 1991)", "publication_year": "2016", "title": "The Brain Basis of Positive and Negative Affect: Evidence from a Meta-Analysis of the Human Neuroimaging Literature.", "keywords": "affect \nmeta-analysis \nneuroimaging \nvalence \nvalue \n", "abstract": "The ability to experience pleasant or unpleasant feelings or to represent objects as \"positive\" or \"negative\" is known as representing hedonic \"valence.\" Although scientists overwhelmingly agree that valence is a basic psychological phenomenon, debate continues about how to best conceptualize it scientifically. We used a meta-analysis of 397 functional magnetic resonance imaging (fMRI) and positron emission tomography studies (containing 914 experimental contrasts and 6827 participants) to test 3 competing hypotheses about the brain basis of valence: the bipolarity hypothesis that positive and negative affect are supported by a brain system that monotonically increases and/or decreases along the valence dimension, the bivalent hypothesis that positive and negative affect are supported by independent brain systems, and the affective workspace hypothesis that positive and negative affect are supported by a flexible set of valence-general regions. We found little evidence for the bipolar or bivalent hypotheses. Findings instead supported the hypothesis that, at the level of brain activity measurable by fMRI, valence is flexibly implemented across instances by a set of valence-general limbic and paralimbic brain regions. ", "authors": "Lindquist, Kristen A and Satpute, Ajay B and Wager, Tor D and Weber, Jochen and Barrett, Lisa Feldman"}, "display_title": "pmid: <a href=\"https://pubmed.ncbi.nlm.nih.gov/25631056\">25631056</a>", "list_title": "PMID25631056 The Brain Basis of Positive and Negative Affect: Evidence from a Meta-Analysis of the Human Neuroimaging Literature."}
