{"text": "Pietrzykowski, Malvina O and Daigle, Katrina M and Waters, Abigail B and Swenson, Lance P and Gansler, David A\nBrain Imaging Behav, 2022\n\n# Title\n\nThe central executive network and executive function in healthy and persons with schizophrenia groups: a meta-analysis of structural and functional MRI.\n\n# Keywords\n\nCentral executive network\nExecutive function\nMRI\nMeta-analysis\nSchizophrenia\n\n# Abstract\nThis meta-analysis evaluated the extent to which executive function can be understood with structural and functional magnetic resonance imaging. Studies included structural in schizophrenia (k\u2009=\u20098; n\u2009=\u2009241) and healthy controls (k\u2009=\u200912; n\u2009=\u20091660), and functional in schizophrenia (k\u2009=\u20094; n\u2009=\u2009104) and healthy controls (k\u2009=\u200912; n\u2009=\u2009712). Results revealed a positive association in the brain behavior relationship when pooled across schizophrenia and control samples for structural (pr\u2009=\u20090.27) and functional (pr\u2009=\u20090.29) modalities. Subgroup analyses revealed no significant difference for functional neuroimaging (pr\u2009=\u2009.43, 95%CI\u2009=\u2009-.08-.77, p\u2009=\u2009.088) but with structural neuroimaging (pr\u2009=\u2009.37, 95%CI\u2009=\u2009-.08-.69, p\u2009=\u2009.015) the association to executive functions is lower in the control group. Subgroup analyses also revealed no significant differences in the strength of the brain-behavior relationship in the schizophrenia group (pr\u2009=\u2009.59, 95%CI\u2009=\u2009.58-.61, p\u2009=\u2009.881) or the control group (pr\u2009=\u20090.19, 95%CI\u2009=\u20090.18-0.19, p\u2009=\u20090.920), suggesting concordance. ", "metadata": {"id": 34775552, "text_md5": "e5864e59f465a427f3f4667e687c11a8", "field_positions": {"authors": [0, 110], "journal": [111, 130], "publication_year": [132, 136], "title": [147, 299], "keywords": [313, 389], "abstract": [402, 1458], "body": [1467, 1467]}, "batch": 1, "pmid": 34775552, "doi": "10.1007/s11682-021-00589-3", "pmid_url": "https://pubmed.ncbi.nlm.nih.gov/34775552/", "efetch_url": "https://eutils.ncbi.nlm.nih.gov/entrez/eutils/efetch.fcgi?db=pubmed&id=34775552"}, "display_title": "pmid: <a href=\"https://pubmed.ncbi.nlm.nih.gov/34775552/\">34775552</a>", "list_title": "PMID34775552  The central executive network and executive function in healthy and persons with schizophrenia groups: a meta-analysis of structural and functional MRI."}
{"text": "Pietrzykowski, Malvina O and Daigle, Katrina M and Waters, Abigail B and Swenson, Lance P and Gansler, David A\nBrain imaging and behavior, 2022\n\n# Title\n\nThe central executive network and executive function in healthy and persons with schizophrenia groups: a meta-analysis of structural and functional MRI.\n\n# Keywords\n\nCentral executive network \nExecutive function \nMRI \nMeta-analysis \nSchizophrenia \n\n\n# Abstract\n\nThis meta-analysis evaluated the extent to which executive function can be understood with structural and functional magnetic resonance imaging. Studies included structural in schizophrenia (k\u2009=\u20098; n\u2009=\u2009241) and healthy controls (k\u2009=\u200912; n\u2009=\u20091660), and functional in schizophrenia (k\u2009=\u20094; n\u2009=\u2009104) and healthy controls (k\u2009=\u200912; n\u2009=\u2009712). Results revealed a positive association in the brain behavior relationship when pooled across schizophrenia and control samples for structural (pr\u2009=\u20090.27) and functional (pr\u2009=\u20090.29) modalities. Subgroup analyses revealed no significant difference for functional neuroimaging (pr\u2009=\u2009.43, 95%CI\u2009=\u2009-.08-.77, p\u2009=\u2009.088) but with structural neuroimaging (pr\u2009=\u2009.37, 95%CI\u2009=\u2009-.08-.69, p\u2009=\u2009.015) the association to executive functions is lower in the control group. Subgroup analyses also revealed no significant differences in the strength of the brain-behavior relationship in the schizophrenia group (pr\u2009=\u2009.59, 95%CI\u2009=\u2009.58-.61, p\u2009=\u2009.881) or the control group (pr\u2009=\u20090.19, 95%CI\u2009=\u20090.18-0.19, p\u2009=\u20090.920), suggesting concordance. \n", "metadata": {"pmid": "34775552", "journal": "Brain imaging and behavior", "publication_year": "2022", "title": "The central executive network and executive function in healthy and persons with schizophrenia groups: a meta-analysis of structural and functional MRI.", "keywords": "Central executive network \nExecutive function \nMRI \nMeta-analysis \nSchizophrenia \n", "abstract": "This meta-analysis evaluated the extent to which executive function can be understood with structural and functional magnetic resonance imaging. Studies included structural in schizophrenia (k\u2009=\u20098; n\u2009=\u2009241) and healthy controls (k\u2009=\u200912; n\u2009=\u20091660), and functional in schizophrenia (k\u2009=\u20094; n\u2009=\u2009104) and healthy controls (k\u2009=\u200912; n\u2009=\u2009712). Results revealed a positive association in the brain behavior relationship when pooled across schizophrenia and control samples for structural (pr\u2009=\u20090.27) and functional (pr\u2009=\u20090.29) modalities. Subgroup analyses revealed no significant difference for functional neuroimaging (pr\u2009=\u2009.43, 95%CI\u2009=\u2009-.08-.77, p\u2009=\u2009.088) but with structural neuroimaging (pr\u2009=\u2009.37, 95%CI\u2009=\u2009-.08-.69, p\u2009=\u2009.015) the association to executive functions is lower in the control group. Subgroup analyses also revealed no significant differences in the strength of the brain-behavior relationship in the schizophrenia group (pr\u2009=\u2009.59, 95%CI\u2009=\u2009.58-.61, p\u2009=\u2009.881) or the control group (pr\u2009=\u20090.19, 95%CI\u2009=\u20090.18-0.19, p\u2009=\u20090.920), suggesting concordance. ", "authors": "Pietrzykowski, Malvina O and Daigle, Katrina M and Waters, Abigail B and Swenson, Lance P and Gansler, David A"}, "display_title": "pmid: <a href=\"https://pubmed.ncbi.nlm.nih.gov/34775552\">34775552</a>", "list_title": "PMID34775552 The central executive network and executive function in healthy and persons with schizophrenia groups: a meta-analysis of structural and functional MRI."}
