{"text": "Samartsidis, Pantelis and Montagna, Silvia and Nichols, Thomas E and Johnson, Timothy D\nStat Sci, 2017\n\n# Title\n\nThe coordinate-based meta-analysis of neuroimaging data.\n\n# Keywords\n\nfunctional magnetic resonance imaging\nmeta-analysis\nneuroimaging\n\n# Abstract\nNeuroimaging meta-analysis is an area of growing interest in statistics. The special characteristics of neuroimaging data render classical meta-analysis methods inapplicable and therefore new methods have been developed. We review existing methodologies, explaining the benefits and drawbacks of each. A demonstration on a real dataset of emotion studies is included. We discuss some still-open problems in the field to highlight the need for future research. ", "metadata": {"id": 29545671, "text_md5": "9dc677ca74925e4513a45056cd064a88", "field_positions": {"authors": [0, 87], "journal": [88, 96], "publication_year": [98, 102], "title": [113, 169], "keywords": [183, 247], "abstract": [260, 720], "body": [729, 729]}, "batch": 2, "pmid": 29545671, "doi": "10.1214/17-STS624", "pmid_url": "https://pubmed.ncbi.nlm.nih.gov/29545671/", "efetch_url": "https://eutils.ncbi.nlm.nih.gov/entrez/eutils/efetch.fcgi?db=pubmed&id=29545671"}, "display_title": "pmid: <a href=\"https://pubmed.ncbi.nlm.nih.gov/29545671/\">29545671</a>", "list_title": "PMID29545671  The coordinate-based meta-analysis of neuroimaging data."}
{"text": "Samartsidis, Pantelis and Montagna, Silvia and Nichols, Thomas E and Johnson, Timothy D\nStatistical science : a review journal of the Institute of Mathematical Statistics, 2019\n\n# Title\n\nThe coordinate-based meta-analysis of neuroimaging data.\n\n# Keywords\n\nfunctional magnetic resonance imaging \nmeta-analysis \nneuroimaging \n\n\n# Abstract\n\nNeuroimaging meta-analysis is an area of growing interest in statistics. The special characteristics of neuroimaging data render classical meta-analysis methods inapplicable and therefore new methods have been developed. We review existing methodologies, explaining the benefits and drawbacks of each. A demonstration on a real dataset of emotion studies is included. We discuss some still-open problems in the field to highlight the need for future research. \n", "metadata": {"pmid": "29545671", "journal": "Statistical science : a review journal of the Institute of Mathematical Statistics", "publication_year": "2019", "title": "The coordinate-based meta-analysis of neuroimaging data.", "keywords": "functional magnetic resonance imaging \nmeta-analysis \nneuroimaging \n", "abstract": "Neuroimaging meta-analysis is an area of growing interest in statistics. The special characteristics of neuroimaging data render classical meta-analysis methods inapplicable and therefore new methods have been developed. We review existing methodologies, explaining the benefits and drawbacks of each. A demonstration on a real dataset of emotion studies is included. We discuss some still-open problems in the field to highlight the need for future research. ", "authors": "Samartsidis, Pantelis and Montagna, Silvia and Nichols, Thomas E and Johnson, Timothy D"}, "display_title": "pmid: <a href=\"https://pubmed.ncbi.nlm.nih.gov/29545671\">29545671</a>", "list_title": "PMID29545671 The coordinate-based meta-analysis of neuroimaging data."}
