{"text": "Lukow, P B and Kiemes, A and Kempton, M J and Turkheimer, F E and McGuire, P and Modinos, G\nNeurosci Biobehav Rev, 2021\n\n# Title\n\nNeural correlates of emotional processing in psychosis risk and onset - A systematic review and meta-analysis of fMRI studies.\n\n# Keywords\n\nClinical high-risk\nEmotion\nFunctional magnetic resonance imaging\nPsychosis\nSeed-based d mapping\n\n# Abstract\nAberrant emotion processing is a well-established component of psychotic disorders and is already present at the first episode of psychosis (FEP). However, the role of emotion processing abnormalities in the emergence of psychosis and the underlying neurobiology remain unclear. Here, we systematically reviewed functional magnetic resonance studies that used emotion processing task paradigms in FEP patients, and in people at clinical high-risk for psychosis (CHRp). Image-based meta-analyses with Seed-based d Mapping on available studies (n = 6) were also performed. Compared to controls, FEP patients showed decreased neural responses to emotion, particularly in the amygdala and anterior cingulate cortex. There were no significant differences between CHRp subjects and controls, but a high degree of heterogeneity was identified across studies. The role of altered emotion processing in the early phase of psychosis may be clarified through more homogenous experimental designs, particularly in the CHRp population. ", "metadata": {"id": 33722617, "text_md5": "8c4a9743210eddbbde1c82bf2a0912a8", "field_positions": {"authors": [0, 91], "journal": [92, 113], "publication_year": [115, 119], "title": [130, 256], "keywords": [270, 365], "abstract": [378, 1401], "body": [1410, 1410]}, "batch": 2, "pmid": 33722617, "doi": "10.1016/j.neubiorev.2021.03.010", "pmid_url": "https://pubmed.ncbi.nlm.nih.gov/33722617/", "efetch_url": "https://eutils.ncbi.nlm.nih.gov/entrez/eutils/efetch.fcgi?db=pubmed&id=33722617"}, "display_title": "pmid: <a href=\"https://pubmed.ncbi.nlm.nih.gov/33722617/\">33722617</a>", "list_title": "PMID33722617  Neural correlates of emotional processing in psychosis risk and onset - A systematic review and meta-analysis of fMRI studies."}
{"text": "Lukow, P B and Kiemes, A and Kempton, M J and Turkheimer, F E and McGuire, P and Modinos, G\nNeuroscience and biobehavioral reviews, 2021\n\n# Title\n\nNeural correlates of emotional processing in psychosis risk and onset - A systematic review and meta-analysis of fMRI studies.\n\n# Keywords\n\nClinical high-risk \nEmotion \nFunctional magnetic resonance imaging \nPsychosis \nSeed-based d mapping \n\n\n# Abstract\n\nAberrant emotion processing is a well-established component of psychotic disorders and is already present at the first episode of psychosis (FEP). However, the role of emotion processing abnormalities in the emergence of psychosis and the underlying neurobiology remain unclear. Here, we systematically reviewed functional magnetic resonance studies that used emotion processing task paradigms in FEP patients, and in people at clinical high-risk for psychosis (CHRp). Image-based meta-analyses with Seed-based d Mapping on available studies (n = 6) were also performed. Compared to controls, FEP patients showed decreased neural responses to emotion, particularly in the amygdala and anterior cingulate cortex. There were no significant differences between CHRp subjects and controls, but a high degree of heterogeneity was identified across studies. The role of altered emotion processing in the early phase of psychosis may be clarified through more homogenous experimental designs, particularly in the CHRp population. \n", "metadata": {"pmid": "33722617", "journal": "Neuroscience and biobehavioral reviews", "publication_year": "2021", "title": "Neural correlates of emotional processing in psychosis risk and onset - A systematic review and meta-analysis of fMRI studies.", "keywords": "Clinical high-risk \nEmotion \nFunctional magnetic resonance imaging \nPsychosis \nSeed-based d mapping \n", "abstract": "Aberrant emotion processing is a well-established component of psychotic disorders and is already present at the first episode of psychosis (FEP). However, the role of emotion processing abnormalities in the emergence of psychosis and the underlying neurobiology remain unclear. Here, we systematically reviewed functional magnetic resonance studies that used emotion processing task paradigms in FEP patients, and in people at clinical high-risk for psychosis (CHRp). Image-based meta-analyses with Seed-based d Mapping on available studies (n = 6) were also performed. Compared to controls, FEP patients showed decreased neural responses to emotion, particularly in the amygdala and anterior cingulate cortex. There were no significant differences between CHRp subjects and controls, but a high degree of heterogeneity was identified across studies. The role of altered emotion processing in the early phase of psychosis may be clarified through more homogenous experimental designs, particularly in the CHRp population. ", "authors": "Lukow, P B and Kiemes, A and Kempton, M J and Turkheimer, F E and McGuire, P and Modinos, G"}, "display_title": "pmid: <a href=\"https://pubmed.ncbi.nlm.nih.gov/33722617\">33722617</a>", "list_title": "PMID33722617 Neural correlates of emotional processing in psychosis risk and onset - A systematic review and meta-analysis of fMRI studies."}
