{"text": "Kuhnke, Philipp and Beaupain, Marie C and Arola, Johannes and Kiefer, Markus and Hartwigsen, Gesa\nNeurosci Biobehav Rev, 2023\n\n# Title\n\nMeta-analytic evidence for a novel hierarchical model of conceptual processing.\n\n# Keywords\n\nConcepts\nFMRI\nGrounded cognition\nLanguage\nSemantic memory\n\n# Abstract\nConceptual knowledge plays a pivotal role in human cognition. Grounded cognition theories propose that concepts consist of perceptual-motor features represented in modality-specific perceptual-motor cortices. However, it is unclear whether conceptual processing consistently engages modality-specific areas. Here, we performed an activation likelihood estimation (ALE) meta-analysis across 212 neuroimaging experiments on conceptual processing related to 7 perceptual-motor modalities (action, sound, visual shape, motion, color, olfaction-gustation, and emotion). We found that conceptual processing consistently engages brain regions also activated during real perceptual-motor experience of the same modalities. In addition, we identified multimodal convergence zones that are recruited for multiple modalities. In particular, the left inferior parietal lobe (IPL) and posterior middle temporal gyrus (pMTG) are engaged for three modalities: action, motion, and sound. These \"trimodal\" regions are surrounded by \"bimodal\" regions engaged for two modalities. Our findings support a novel model of the conceptual system, according to which conceptual processing relies on a hierarchical neural architecture from modality-specific to multimodal areas up to an amodal hub. ", "metadata": {"id": 36509206, "text_md5": "cb69b0281cfa3b70821cb60496814828", "field_positions": {"authors": [0, 97], "journal": [98, 119], "publication_year": [121, 125], "title": [136, 215], "keywords": [229, 286], "abstract": [299, 1571], "body": [1580, 1580]}, "batch": 1, "pmid": 36509206, "doi": "10.1016/j.neubiorev.2022.104994", "pmid_url": "https://pubmed.ncbi.nlm.nih.gov/36509206/", "efetch_url": "https://eutils.ncbi.nlm.nih.gov/entrez/eutils/efetch.fcgi?db=pubmed&id=36509206"}, "display_title": "pmid: <a href=\"https://pubmed.ncbi.nlm.nih.gov/36509206/\">36509206</a>", "list_title": "PMID36509206  Meta-analytic evidence for a novel hierarchical model of conceptual processing."}
{"text": "Kuhnke, Philipp and Beaupain, Marie C and Arola, Johannes and Kiefer, Markus and Hartwigsen, Gesa\nNeuroscience and biobehavioral reviews, 2023\n\n# Title\n\nMeta-analytic evidence for a novel hierarchical model of conceptual processing.\n\n# Keywords\n\nConcepts \nFMRI \nGrounded cognition \nLanguage \nSemantic memory \n\n\n# Abstract\n\nConceptual knowledge plays a pivotal role in human cognition. Grounded cognition theories propose that concepts consist of perceptual-motor features represented in modality-specific perceptual-motor cortices. However, it is unclear whether conceptual processing consistently engages modality-specific areas. Here, we performed an activation likelihood estimation (ALE) meta-analysis across 212 neuroimaging experiments on conceptual processing related to 7 perceptual-motor modalities (action, sound, visual shape, motion, color, olfaction-gustation, and emotion). We found that conceptual processing consistently engages brain regions also activated during real perceptual-motor experience of the same modalities. In addition, we identified multimodal convergence zones that are recruited for multiple modalities. In particular, the left inferior parietal lobe (IPL) and posterior middle temporal gyrus (pMTG) are engaged for three modalities: action, motion, and sound. These \"trimodal\" regions are surrounded by \"bimodal\" regions engaged for two modalities. Our findings support a novel model of the conceptual system, according to which conceptual processing relies on a hierarchical neural architecture from modality-specific to multimodal areas up to an amodal hub. \n", "metadata": {"pmid": "36509206", "journal": "Neuroscience and biobehavioral reviews", "publication_year": "2023", "title": "Meta-analytic evidence for a novel hierarchical model of conceptual processing.", "keywords": "Concepts \nFMRI \nGrounded cognition \nLanguage \nSemantic memory \n", "abstract": "Conceptual knowledge plays a pivotal role in human cognition. Grounded cognition theories propose that concepts consist of perceptual-motor features represented in modality-specific perceptual-motor cortices. However, it is unclear whether conceptual processing consistently engages modality-specific areas. Here, we performed an activation likelihood estimation (ALE) meta-analysis across 212 neuroimaging experiments on conceptual processing related to 7 perceptual-motor modalities (action, sound, visual shape, motion, color, olfaction-gustation, and emotion). We found that conceptual processing consistently engages brain regions also activated during real perceptual-motor experience of the same modalities. In addition, we identified multimodal convergence zones that are recruited for multiple modalities. In particular, the left inferior parietal lobe (IPL) and posterior middle temporal gyrus (pMTG) are engaged for three modalities: action, motion, and sound. These \"trimodal\" regions are surrounded by \"bimodal\" regions engaged for two modalities. Our findings support a novel model of the conceptual system, according to which conceptual processing relies on a hierarchical neural architecture from modality-specific to multimodal areas up to an amodal hub. ", "authors": "Kuhnke, Philipp and Beaupain, Marie C and Arola, Johannes and Kiefer, Markus and Hartwigsen, Gesa"}, "display_title": "pmid: <a href=\"https://pubmed.ncbi.nlm.nih.gov/36509206\">36509206</a>", "list_title": "PMID36509206 Meta-analytic evidence for a novel hierarchical model of conceptual processing."}
