{"text": "Kim, Hongkeun\nNeurosci Biobehav Rev, 2021\n\n# Title\n\nImaging recollection, familiarity, and novelty in the frontoparietal control and default mode networks and the anterior-posterior medial temporal lobe: An integrated view and meta-analysis.\n\n# Keywords\n\nDefault mode network\nEpisodic memory retrieval\nFamiliarity\nFrontoparietal control network\nMedial temporal lobe\nMeta-analysis\nNovelty\nRecollection\nfMRI\n\n# Abstract\nA network-level model of recollection-based recognition (R), familiarity-based recognition (F), and novelty recognition (N) was constructed, and its validity was evaluated through meta-analyses to produce an integrated view of neuroimaging data. The model predicted the following: (a) the overall magnitude of the frontoparietal control network (FPCN) activity (which supports retrieval and decision effort) is in the order of F\u2009>\u2009R\u2009>\u2009N; (b) that of the posterior medial temporal network (MTL) activity (which plays a direct role in retrieval) is in the order of R\u2009>\u2009N\u2009>\u2009F; (c) that of the anterior MTL activity (which supports novelty-encoding) is in the order of N\u2009>\u2009R\u2009>\u2009F; (d) that of the default mode network (DMN) activity (which supports the subjective experience of remembering) is in the order of R\u2009>\u2009N\u2009>\u2009F. The meta-analyses results were consistent with these predictions. Subsystem analysis indicated a functional dissociation between the cingulo-opercular vs. frontoparietal components of the FPCN and between the core vs. medial temporal components of the DMN. ", "metadata": {"id": 33857579, "text_md5": "61458852a9e4d0219e2abbb27cfeef8e", "field_positions": {"authors": [0, 13], "journal": [14, 35], "publication_year": [37, 41], "title": [52, 241], "keywords": [255, 405], "abstract": [418, 1491], "body": [1500, 1500]}, "batch": 3, "pmid": 33857579, "doi": "10.1016/j.neubiorev.2021.04.007", "pmid_url": "https://pubmed.ncbi.nlm.nih.gov/33857579/", "efetch_url": "https://eutils.ncbi.nlm.nih.gov/entrez/eutils/efetch.fcgi?db=pubmed&id=33857579"}, "display_title": "pmid: <a href=\"https://pubmed.ncbi.nlm.nih.gov/33857579/\">33857579</a>", "list_title": "PMID33857579  Imaging recollection, familiarity, and novelty in the frontoparietal control and default mode networks and the anterior-posterior medial temporal lobe: An integrated view and meta-analysis."}
{"text": "Kim, Hongkeun\nNeuroscience and biobehavioral reviews, 2021\n\n# Title\n\nImaging recollection, familiarity, and novelty in the frontoparietal control and default mode networks and the anterior-posterior medial temporal lobe: An integrated view and meta-analysis.\n\n# Keywords\n\nDefault mode network \nEpisodic memory retrieval \nFamiliarity \nFrontoparietal control network \nMedial temporal lobe \nMeta-analysis \nNovelty \nRecollection \nfMRI \n\n\n# Abstract\n\nA network-level model of recollection-based recognition (R), familiarity-based recognition (F), and novelty recognition (N) was constructed, and its validity was evaluated through meta-analyses to produce an integrated view of neuroimaging data. The model predicted the following: (a) the overall magnitude of the frontoparietal control network (FPCN) activity (which supports retrieval and decision effort) is in the order of F\u2009>\u2009R\u2009>\u2009N; (b) that of the posterior medial temporal network (MTL) activity (which plays a direct role in retrieval) is in the order of R\u2009>\u2009N\u2009>\u2009F; (c) that of the anterior MTL activity (which supports novelty-encoding) is in the order of N\u2009>\u2009R\u2009>\u2009F; (d) that of the default mode network (DMN) activity (which supports the subjective experience of remembering) is in the order of R\u2009>\u2009N\u2009>\u2009F. The meta-analyses results were consistent with these predictions. Subsystem analysis indicated a functional dissociation between the cingulo-opercular vs. frontoparietal components of the FPCN and between the core vs. medial temporal components of the DMN. \n", "metadata": {"pmid": "33857579", "journal": "Neuroscience and biobehavioral reviews", "publication_year": "2021", "title": "Imaging recollection, familiarity, and novelty in the frontoparietal control and default mode networks and the anterior-posterior medial temporal lobe: An integrated view and meta-analysis.", "keywords": "Default mode network \nEpisodic memory retrieval \nFamiliarity \nFrontoparietal control network \nMedial temporal lobe \nMeta-analysis \nNovelty \nRecollection \nfMRI \n", "abstract": "A network-level model of recollection-based recognition (R), familiarity-based recognition (F), and novelty recognition (N) was constructed, and its validity was evaluated through meta-analyses to produce an integrated view of neuroimaging data. The model predicted the following: (a) the overall magnitude of the frontoparietal control network (FPCN) activity (which supports retrieval and decision effort) is in the order of F\u2009>\u2009R\u2009>\u2009N; (b) that of the posterior medial temporal network (MTL) activity (which plays a direct role in retrieval) is in the order of R\u2009>\u2009N\u2009>\u2009F; (c) that of the anterior MTL activity (which supports novelty-encoding) is in the order of N\u2009>\u2009R\u2009>\u2009F; (d) that of the default mode network (DMN) activity (which supports the subjective experience of remembering) is in the order of R\u2009>\u2009N\u2009>\u2009F. The meta-analyses results were consistent with these predictions. Subsystem analysis indicated a functional dissociation between the cingulo-opercular vs. frontoparietal components of the FPCN and between the core vs. medial temporal components of the DMN. ", "authors": "Kim, Hongkeun"}, "display_title": "pmid: <a href=\"https://pubmed.ncbi.nlm.nih.gov/33857579\">33857579</a>", "list_title": "PMID33857579 Imaging recollection, familiarity, and novelty in the frontoparietal control and default mode networks and the anterior-posterior medial temporal lobe: An integrated view and meta-analysis."}
