{"text": "Escobar-Magari\u00f1o, Daniela and Turel, Ofir and He, Qinghua\nNeuroscience, 2022\n\n# Title\n\nBilateral Intraparietal Activation for Number Tasks in Studies Using Adaptation Paradigm: A Meta-analysis.\n\n# Keywords\n\nadaptation paradigm\nfMRI\nintraparietal sulcus\nmeta-analysis\nsymbolic vs. non-symbolic\n\n# Abstract\nMathematical processing is important for professional success. The adaptation paradigm has been widely used to study the brain underpinnings of mathematical processing. In this study, we aim at shedding light on an important component of mathematical processing, namely numerical cognition. To do so, we performed a meta-analysis using the Activation Likelihood Estimation method on studies that have employed the adaptation paradigm for examining numerical cognition. We found a bilateral Intraparietal Sulcus (IPS) activation in studies using both symbolic and non-symbolic stimuli formats. We also found a right lateralized brain activation for the non-symbolic condition and a left lateralized brain activation for the symbolic condition. These results imply that the adaptation paradigm likely targets numeric magnitude processing and confirms the potency of this paradigm to activate the IPS. ", "metadata": {"id": 35276305, "text_md5": "aa79a6ede831d28350c734ee838f9f95", "field_positions": {"authors": [0, 57], "journal": [58, 70], "publication_year": [72, 76], "title": [87, 193], "keywords": [207, 292], "abstract": [305, 1204], "body": [1213, 1213]}, "batch": 1, "pmid": 35276305, "doi": "10.1016/j.neuroscience.2022.02.024", "pmid_url": "https://pubmed.ncbi.nlm.nih.gov/35276305/", "efetch_url": "https://eutils.ncbi.nlm.nih.gov/entrez/eutils/efetch.fcgi?db=pubmed&id=35276305"}, "display_title": "pmid: <a href=\"https://pubmed.ncbi.nlm.nih.gov/35276305/\">35276305</a>", "list_title": "PMID35276305  Bilateral Intraparietal Activation for Number Tasks in Studies Using Adaptation Paradigm: A Meta-analysis."}
{"text": "Escobar-Magari\u00f1o, Daniela and Turel, Ofir and He, Qinghua\nNeuroscience, 2022\n\n# Title\n\nBilateral Intraparietal Activation for Number Tasks in Studies Using Adaptation Paradigm: A Meta-analysis.\n\n# Keywords\n\nadaptation paradigm \nfMRI \nintraparietal sulcus \nmeta-analysis \nsymbolic vs. non-symbolic \n\n\n# Abstract\n\nMathematical processing is important for professional success. The adaptation paradigm has been widely used to study the brain underpinnings of mathematical processing. In this study, we aim at shedding light on an important component of mathematical processing, namely numerical cognition. To do so, we performed a meta-analysis using the Activation Likelihood Estimation method on studies that have employed the adaptation paradigm for examining numerical cognition. We found a bilateral Intraparietal Sulcus (IPS) activation in studies using both symbolic and non-symbolic stimuli formats. We also found a right lateralized brain activation for the non-symbolic condition and a left lateralized brain activation for the symbolic condition. These results imply that the adaptation paradigm likely targets numeric magnitude processing and confirms the potency of this paradigm to activate the IPS. \n", "metadata": {"pmid": "35276305", "journal": "Neuroscience", "publication_year": "2022", "title": "Bilateral Intraparietal Activation for Number Tasks in Studies Using Adaptation Paradigm: A Meta-analysis.", "keywords": "adaptation paradigm \nfMRI \nintraparietal sulcus \nmeta-analysis \nsymbolic vs. non-symbolic \n", "abstract": "Mathematical processing is important for professional success. The adaptation paradigm has been widely used to study the brain underpinnings of mathematical processing. In this study, we aim at shedding light on an important component of mathematical processing, namely numerical cognition. To do so, we performed a meta-analysis using the Activation Likelihood Estimation method on studies that have employed the adaptation paradigm for examining numerical cognition. We found a bilateral Intraparietal Sulcus (IPS) activation in studies using both symbolic and non-symbolic stimuli formats. We also found a right lateralized brain activation for the non-symbolic condition and a left lateralized brain activation for the symbolic condition. These results imply that the adaptation paradigm likely targets numeric magnitude processing and confirms the potency of this paradigm to activate the IPS. ", "authors": "Escobar-Magari\u00f1o, Daniela and Turel, Ofir and He, Qinghua"}, "display_title": "pmid: <a href=\"https://pubmed.ncbi.nlm.nih.gov/35276305\">35276305</a>", "list_title": "PMID35276305 Bilateral Intraparietal Activation for Number Tasks in Studies Using Adaptation Paradigm: A Meta-analysis."}
