{"text": "McNorgan, Chris and Chabal, Sarah and O'Young, Daniel and Lukic, Sladjana and Booth, James R\nNeuropsychologia, 2015\n\n# Title\n\nTask dependent lexicality effects support interactive models of reading: a meta-analytic neuroimaging review.\n\n# Keywords\n\nActivation likelihood estimate\nLexical decision\nNaming\nParallel distributed processing\nPsycholinguistics\nfMRI\n\n# Abstract\nModels of reading must explain how orthographic input activates a phonological representation, and elicits the retrieval of word meaning from semantic memory. Comparisons between tasks that theoretically differ with respect to the degree to which they rely on connections between orthographic, phonological and semantic systems during reading can thus provide valuable insight into models of reading, but such direct comparisons are not well-represented in the literature. An ALE meta-analysis explored lexicality effects directly contrasting words and pseudowords using the lexical decision task and overt or covert naming, which we assume rely most on the semantic and phonological systems, respectively. Interactions between task and lexicality effects demonstrate that different demands of the lexical decision and naming tasks lead to different manifestations of lexicality effects. ", "metadata": {"id": 25524364, "text_md5": "d10477a3f688ec192d1ad0a43e85d2cd", "field_positions": {"authors": [0, 92], "journal": [93, 109], "publication_year": [111, 115], "title": [126, 235], "keywords": [249, 358], "abstract": [371, 1259], "body": [1268, 1268]}, "batch": 1, "pmid": 25524364, "doi": "10.1016/j.neuropsychologia.2014.12.014", "pmid_url": "https://pubmed.ncbi.nlm.nih.gov/25524364/", "efetch_url": "https://eutils.ncbi.nlm.nih.gov/entrez/eutils/efetch.fcgi?db=pubmed&id=25524364"}, "display_title": "pmid: <a href=\"https://pubmed.ncbi.nlm.nih.gov/25524364/\">25524364</a>", "list_title": "PMID25524364  Task dependent lexicality effects support interactive models of reading: a meta-analytic neuroimaging review."}
{"text": "McNorgan, Chris and Chabal, Sarah and O'Young, Daniel and Lukic, Sladjana and Booth, James R\nNeuropsychologia, 2016\n\n# Title\n\nTask dependent lexicality effects support interactive models of reading: a meta-analytic neuroimaging review.\n\n# Keywords\n\nActivation likelihood estimate \nLexical decision \nNaming \nParallel distributed processing \nPsycholinguistics \nfMRI \n\n\n# Abstract\n\nModels of reading must explain how orthographic input activates a phonological representation, and elicits the retrieval of word meaning from semantic memory. Comparisons between tasks that theoretically differ with respect to the degree to which they rely on connections between orthographic, phonological and semantic systems during reading can thus provide valuable insight into models of reading, but such direct comparisons are not well-represented in the literature. An ALE meta-analysis explored lexicality effects directly contrasting words and pseudowords using the lexical decision task and overt or covert naming, which we assume rely most on the semantic and phonological systems, respectively. Interactions between task and lexicality effects demonstrate that different demands of the lexical decision and naming tasks lead to different manifestations of lexicality effects. \n", "metadata": {"pmid": "25524364", "journal": "Neuropsychologia", "publication_year": "2016", "title": "Task dependent lexicality effects support interactive models of reading: a meta-analytic neuroimaging review.", "keywords": "Activation likelihood estimate \nLexical decision \nNaming \nParallel distributed processing \nPsycholinguistics \nfMRI \n", "abstract": "Models of reading must explain how orthographic input activates a phonological representation, and elicits the retrieval of word meaning from semantic memory. Comparisons between tasks that theoretically differ with respect to the degree to which they rely on connections between orthographic, phonological and semantic systems during reading can thus provide valuable insight into models of reading, but such direct comparisons are not well-represented in the literature. An ALE meta-analysis explored lexicality effects directly contrasting words and pseudowords using the lexical decision task and overt or covert naming, which we assume rely most on the semantic and phonological systems, respectively. Interactions between task and lexicality effects demonstrate that different demands of the lexical decision and naming tasks lead to different manifestations of lexicality effects. ", "authors": "McNorgan, Chris and Chabal, Sarah and O'Young, Daniel and Lukic, Sladjana and Booth, James R"}, "display_title": "pmid: <a href=\"https://pubmed.ncbi.nlm.nih.gov/25524364\">25524364</a>", "list_title": "PMID25524364 Task dependent lexicality effects support interactive models of reading: a meta-analytic neuroimaging review."}
