{"text": "Poeppl, Timm B and Langguth, Berthold and Rupprecht, Rainer and Safron, Adam and Bzdok, Danilo and Laird, Angela R and Eickhoff, Simon B\nFront Neuroendocrinol, 2016\n\n# Title\n\nThe neural basis of sex differences in sexual behavior: A quantitative meta-analysis.\n\n# Keywords\n\nALE\nActivation likelihood estimation\nFunctional magnetic resonance imaging\nMeta-analysis\nNeuroimaging\nPET\nPositron emission tomography\nSex differences\nSexual behavior\nfMRI\n\n# Abstract\nSexuality as to its etymology presupposes the duality of sexes. Using quantitative neuroimaging meta-analyses, we demonstrate robust sex differences in the neural processing of sexual stimuli in thalamus, hypothalamus, and basal ganglia. In a narrative review, we show how these relate to the well-established sex differences on the behavioral level. More specifically, we describe the neural bases of known poor agreement between self-reported and genital measures of female sexual arousal, of previously proposed male proneness to affective sexual conditioning, as well as hints of unconscious activation of bonding mechanisms during sexual stimulation in women. In summary, our meta-analytic review demonstrates that neurofunctional sex differences during sexual stimulation can account for well-established sex differences in sexual behavior. ", "metadata": {"id": 27742561, "text_md5": "f7098b4669abdba02b69acb1771581a5", "field_positions": {"authors": [0, 136], "journal": [137, 158], "publication_year": [160, 164], "title": [175, 260], "keywords": [274, 445], "abstract": [458, 1305], "body": [1314, 1314]}, "batch": 3, "pmid": 27742561, "doi": "10.1016/j.yfrne.2016.10.001", "pmid_url": "https://pubmed.ncbi.nlm.nih.gov/27742561/", "efetch_url": "https://eutils.ncbi.nlm.nih.gov/entrez/eutils/efetch.fcgi?db=pubmed&id=27742561"}, "display_title": "pmid: <a href=\"https://pubmed.ncbi.nlm.nih.gov/27742561/\">27742561</a>", "list_title": "PMID27742561  The neural basis of sex differences in sexual behavior: A quantitative meta-analysis."}
{"text": "Poeppl, Timm B and Langguth, Berthold and Rupprecht, Rainer and Safron, Adam and Bzdok, Danilo and Laird, Angela R and Eickhoff, Simon B\nFrontiers in neuroendocrinology, 2017\n\n# Title\n\nThe neural basis of sex differences in sexual behavior: A quantitative meta-analysis.\n\n# Keywords\n\nALE \nActivation likelihood estimation \nFunctional magnetic resonance imaging \nMeta-analysis \nNeuroimaging \nPET \nPositron emission tomography \nSex differences \nSexual behavior \nfMRI \n\n\n# Abstract\n\nSexuality as to its etymology presupposes the duality of sexes. Using quantitative neuroimaging meta-analyses, we demonstrate robust sex differences in the neural processing of sexual stimuli in thalamus, hypothalamus, and basal ganglia. In a narrative review, we show how these relate to the well-established sex differences on the behavioral level. More specifically, we describe the neural bases of known poor agreement between self-reported and genital measures of female sexual arousal, of previously proposed male proneness to affective sexual conditioning, as well as hints of unconscious activation of bonding mechanisms during sexual stimulation in women. In summary, our meta-analytic review demonstrates that neurofunctional sex differences during sexual stimulation can account for well-established sex differences in sexual behavior. \n", "metadata": {"pmid": "27742561", "journal": "Frontiers in neuroendocrinology", "publication_year": "2017", "title": "The neural basis of sex differences in sexual behavior: A quantitative meta-analysis.", "keywords": "ALE \nActivation likelihood estimation \nFunctional magnetic resonance imaging \nMeta-analysis \nNeuroimaging \nPET \nPositron emission tomography \nSex differences \nSexual behavior \nfMRI \n", "abstract": "Sexuality as to its etymology presupposes the duality of sexes. Using quantitative neuroimaging meta-analyses, we demonstrate robust sex differences in the neural processing of sexual stimuli in thalamus, hypothalamus, and basal ganglia. In a narrative review, we show how these relate to the well-established sex differences on the behavioral level. More specifically, we describe the neural bases of known poor agreement between self-reported and genital measures of female sexual arousal, of previously proposed male proneness to affective sexual conditioning, as well as hints of unconscious activation of bonding mechanisms during sexual stimulation in women. In summary, our meta-analytic review demonstrates that neurofunctional sex differences during sexual stimulation can account for well-established sex differences in sexual behavior. ", "authors": "Poeppl, Timm B and Langguth, Berthold and Rupprecht, Rainer and Safron, Adam and Bzdok, Danilo and Laird, Angela R and Eickhoff, Simon B"}, "display_title": "pmid: <a href=\"https://pubmed.ncbi.nlm.nih.gov/27742561\">27742561</a>", "list_title": "PMID27742561 The neural basis of sex differences in sexual behavior: A quantitative meta-analysis."}
