{"text": "Chen, Zhu-Hong and Cui, Yu-Ling and Sun, Jing-Ting and Li, Yu-Ting and Zhang, Chi and Zhang, Yang-Ming and Li, Ze-Yang and Shang, Yu-Xuan and Ni, Min-Hua and Hu, Bo and Yan, Lin-Feng and Wang, Wen\nFrontiers in neurology, 2022\n\n# Title\n\nThe brain structure and function abnormalities of migraineurs: A systematic review and neuroimaging meta-analysis.\n\n# Keywords\n\nfunction \nmagnetic resonance imaging \nmeta-analysis \nmigraine \nstructure \nsystematic review \n\n\n# Abstract\n\nTo quantitatively summarize the specific changes in brain structure and function in migraine patients. A literature screening of migraine was conducted from inception to Sept 1, 2022, in PubMed, Web of Science, Cochrane Library, and Medline databases using the keyword combination of \"migraine and MRI.\" Activation likelihood estimation (ALE) was performed to assess the differentiation of functional connectivity (FC), regional homogeneity (ReHo), and gray matter volume (GMV) of migraine patients. Eleven voxel-based morphometry (VBM) studies and 25 resting-state fMRI (rs-fMRI) studies (16 FC and 9 ReHo studies) were included in this study. ALE analysis revealed the ReHo increase in the brainstem and left thalamus, with no decreased area. Neither increased nor decreased regions were detected in FC and GMV of migraine patients. The left thalamus and brainstem were the significantly activated regions of migraine. It is a meaningful insights into the pathophysiology of migraine. The consistent alterated brain areas of morphometrical and functional in migraine patients were far from reached based on current studies. \n", "metadata": {"pmid": "36419535", "journal": "Frontiers in neurology", "publication_year": "2022", "title": "The brain structure and function abnormalities of migraineurs: A systematic review and neuroimaging meta-analysis.", "keywords": "function \nmagnetic resonance imaging \nmeta-analysis \nmigraine \nstructure \nsystematic review \n", "abstract": "To quantitatively summarize the specific changes in brain structure and function in migraine patients. A literature screening of migraine was conducted from inception to Sept 1, 2022, in PubMed, Web of Science, Cochrane Library, and Medline databases using the keyword combination of \"migraine and MRI.\" Activation likelihood estimation (ALE) was performed to assess the differentiation of functional connectivity (FC), regional homogeneity (ReHo), and gray matter volume (GMV) of migraine patients. Eleven voxel-based morphometry (VBM) studies and 25 resting-state fMRI (rs-fMRI) studies (16 FC and 9 ReHo studies) were included in this study. ALE analysis revealed the ReHo increase in the brainstem and left thalamus, with no decreased area. Neither increased nor decreased regions were detected in FC and GMV of migraine patients. The left thalamus and brainstem were the significantly activated regions of migraine. It is a meaningful insights into the pathophysiology of migraine. The consistent alterated brain areas of morphometrical and functional in migraine patients were far from reached based on current studies. ", "authors": "Chen, Zhu-Hong and Cui, Yu-Ling and Sun, Jing-Ting and Li, Yu-Ting and Zhang, Chi and Zhang, Yang-Ming and Li, Ze-Yang and Shang, Yu-Xuan and Ni, Min-Hua and Hu, Bo and Yan, Lin-Feng and Wang, Wen"}, "display_title": "pmid: <a href=\"https://pubmed.ncbi.nlm.nih.gov/36419535\">36419535</a>", "list_title": "PMID36419535 The brain structure and function abnormalities of migraineurs: A systematic review and neuroimaging meta-analysis."}
