{"text": "Liu, Mingtong and Liu, Chang Hong and Zheng, Shuang and Zhao, Ke and Fu, Xiaolan\nNeurosci Biobehav Rev, 2021\n\n# Title\n\nReexamining the neural network involved in perception of facial expression: A meta-analysis.\n\n# Keywords\n\nDorsal stream\nFFA\nFacial expression\nVentral stream\n\n# Abstract\nPerception of facial expression is essential for social interactions. Although a few competing models have enjoyed some success to map brain regions, they are also facing difficult challenges. The current study used an updated activation likelihood estimation (ALE) method of meta-analysis to explore the involvement of brain regions in facial expression processing. The sample contained 96 functional magnetic resonance imaging (fMRI) and positron emission tomography (PET) studies of healthy adults with the results of whole-brain analyses. The key findings revealed that the ventral pathway, especially the left fusiform face area (FFA) region, was more responsive to facial expression. The left posterior FFA showed strong involvement when participants passively viewing emotional faces without being asked to judge the type of expression or other attributes of the stimuli. Through meta-analytic connectivity modeling (MACM) of the main brain regions in the ventral pathway, we constructed a co-activating neural network as a revised model of facial expression processing that assigns prominent roles to the amygdala, FFA, the occipital gyrus, and the inferior frontal gyrus. ", "metadata": {"id": 34536463, "text_md5": "a15abdfc2a2145fde6d5c070de18cb8c", "field_positions": {"authors": [0, 80], "journal": [81, 102], "publication_year": [104, 108], "title": [119, 211], "keywords": [225, 275], "abstract": [288, 1469], "body": [1478, 1478]}, "batch": 3, "pmid": 34536463, "doi": "10.1016/j.neubiorev.2021.09.024", "pmid_url": "https://pubmed.ncbi.nlm.nih.gov/34536463/", "efetch_url": "https://eutils.ncbi.nlm.nih.gov/entrez/eutils/efetch.fcgi?db=pubmed&id=34536463"}, "display_title": "pmid: <a href=\"https://pubmed.ncbi.nlm.nih.gov/34536463/\">34536463</a>", "list_title": "PMID34536463  Reexamining the neural network involved in perception of facial expression: A meta-analysis."}
{"text": "Liu, Mingtong and Liu, Chang Hong and Zheng, Shuang and Zhao, Ke and Fu, Xiaolan\nNeuroscience and biobehavioral reviews, 2022\n\n# Title\n\nReexamining the neural network involved in perception of facial expression: A meta-analysis.\n\n# Keywords\n\nDorsal stream \nFFA \nFacial expression \nVentral stream \n\n\n# Abstract\n\nPerception of facial expression is essential for social interactions. Although a few competing models have enjoyed some success to map brain regions, they are also facing difficult challenges. The current study used an updated activation likelihood estimation (ALE) method of meta-analysis to explore the involvement of brain regions in facial expression processing. The sample contained 96 functional magnetic resonance imaging (fMRI) and positron emission tomography (PET) studies of healthy adults with the results of whole-brain analyses. The key findings revealed that the ventral pathway, especially the left fusiform face area (FFA) region, was more responsive to facial expression. The left posterior FFA showed strong involvement when participants passively viewing emotional faces without being asked to judge the type of expression or other attributes of the stimuli. Through meta-analytic connectivity modeling (MACM) of the main brain regions in the ventral pathway, we constructed a co-activating neural network as a revised model of facial expression processing that assigns prominent roles to the amygdala, FFA, the occipital gyrus, and the inferior frontal gyrus. \n", "metadata": {"pmid": "34536463", "journal": "Neuroscience and biobehavioral reviews", "publication_year": "2022", "title": "Reexamining the neural network involved in perception of facial expression: A meta-analysis.", "keywords": "Dorsal stream \nFFA \nFacial expression \nVentral stream \n", "abstract": "Perception of facial expression is essential for social interactions. Although a few competing models have enjoyed some success to map brain regions, they are also facing difficult challenges. The current study used an updated activation likelihood estimation (ALE) method of meta-analysis to explore the involvement of brain regions in facial expression processing. The sample contained 96 functional magnetic resonance imaging (fMRI) and positron emission tomography (PET) studies of healthy adults with the results of whole-brain analyses. The key findings revealed that the ventral pathway, especially the left fusiform face area (FFA) region, was more responsive to facial expression. The left posterior FFA showed strong involvement when participants passively viewing emotional faces without being asked to judge the type of expression or other attributes of the stimuli. Through meta-analytic connectivity modeling (MACM) of the main brain regions in the ventral pathway, we constructed a co-activating neural network as a revised model of facial expression processing that assigns prominent roles to the amygdala, FFA, the occipital gyrus, and the inferior frontal gyrus. ", "authors": "Liu, Mingtong and Liu, Chang Hong and Zheng, Shuang and Zhao, Ke and Fu, Xiaolan"}, "display_title": "pmid: <a href=\"https://pubmed.ncbi.nlm.nih.gov/34536463\">34536463</a>", "list_title": "PMID34536463 Reexamining the neural network involved in perception of facial expression: A meta-analysis."}
