{"text": "Dugr\u00e9, Jules Roger and Potvin, St\u00e9phane\nPsychol Med, 2021\n\n# Title\n\nImpaired attentional and socio-affective networks in subjects with antisocial behaviors: a meta-analysis of resting-state functional connectivity studies.\n\n# Keywords\n\nFunctional connectivity\nantisocial behaviors\nconduct disorder\ndefault mode network\ndorsal attention network\nventral attention network\n\n# Abstract\nIn the past decade, there has been a growing interest in examining resting-state functional connectivity deficits in subjects with conduct and antisocial personality disorder. Through meta-analyses and literature reviews, extensive work has been done to characterize their abnormalities in brain activation during a wide range of functional magnetic resonance imaging (fMRI) tasks. However, there is currently no meta-analytical evidence regarding neural connectivity patterns during resting-state fMRI. Therefore, we conducted a coordinate-based meta-analysis of resting-state fMRI studies on individuals exhibiting antisocial behaviors. Of the retrieved studies, 18 used a seed-based connectivity approach (513 cases  ", "metadata": {"id": 33902772, "text_md5": "28a7a94a160489a6c1fa36e8cdd8510f", "field_positions": {"authors": [0, 39], "journal": [40, 51], "publication_year": [53, 57], "title": [68, 222], "keywords": [236, 369], "abstract": [382, 1102], "body": [1111, 1111]}, "batch": 1, "pmid": 33902772, "doi": "10.1017/S0033291721001525", "pmid_url": "https://pubmed.ncbi.nlm.nih.gov/33902772/", "efetch_url": "https://eutils.ncbi.nlm.nih.gov/entrez/eutils/efetch.fcgi?db=pubmed&id=33902772"}, "display_title": "pmid: <a href=\"https://pubmed.ncbi.nlm.nih.gov/33902772/\">33902772</a>", "list_title": "PMID33902772  Impaired attentional and socio-affective networks in subjects with antisocial behaviors: a meta-analysis of resting-state functional connectivity studies."}
{"text": "Dugr\u00e9, Jules Roger and Potvin, St\u00e9phane\nPsychological medicine, 2022\n\n# Title\n\nImpaired attentional and socio-affective networks in subjects with antisocial behaviors: a meta-analysis of resting-state functional connectivity studies.\n\n# Keywords\n\nFunctional connectivity \nantisocial behaviors \nconduct disorder \ndefault mode network \ndorsal attention network \nventral attention network \n\n\n# Abstract\n\nIn the past decade, there has been a growing interest in examining resting-state functional connectivity deficits in subjects with conduct and antisocial personality disorder. Through meta-analyses and literature reviews, extensive work has been done to characterize their abnormalities in brain activation during a wide range of functional magnetic resonance imaging (fMRI) tasks. However, there is currently no meta-analytical evidence regarding neural connectivity patterns during resting-state fMRI. Therefore, we conducted a coordinate-based meta-analysis of resting-state fMRI studies on individuals exhibiting antisocial behaviors. Of the retrieved studies, 18 used a seed-based connectivity approach (513 cases  \n", "metadata": {"pmid": "33902772", "journal": "Psychological medicine", "publication_year": "2022", "title": "Impaired attentional and socio-affective networks in subjects with antisocial behaviors: a meta-analysis of resting-state functional connectivity studies.", "keywords": "Functional connectivity \nantisocial behaviors \nconduct disorder \ndefault mode network \ndorsal attention network \nventral attention network \n", "abstract": "In the past decade, there has been a growing interest in examining resting-state functional connectivity deficits in subjects with conduct and antisocial personality disorder. Through meta-analyses and literature reviews, extensive work has been done to characterize their abnormalities in brain activation during a wide range of functional magnetic resonance imaging (fMRI) tasks. However, there is currently no meta-analytical evidence regarding neural connectivity patterns during resting-state fMRI. Therefore, we conducted a coordinate-based meta-analysis of resting-state fMRI studies on individuals exhibiting antisocial behaviors. Of the retrieved studies, 18 used a seed-based connectivity approach (513 cases  ", "authors": "Dugr\u00e9, Jules Roger and Potvin, St\u00e9phane"}, "display_title": "pmid: <a href=\"https://pubmed.ncbi.nlm.nih.gov/33902772\">33902772</a>", "list_title": "PMID33902772 Impaired attentional and socio-affective networks in subjects with antisocial behaviors: a meta-analysis of resting-state functional connectivity studies."}
