{"text": "Fox, Peter T and Lancaster, Jack L and Laird, Angela R and Eickhoff, Simon B\nAnnu Rev Neurosci, 2014\n\n# Title\n\nMeta-analysis in human neuroimaging: computational modeling of large-scale databases.\n\n# Keywords\n\nALE\nMRI\nactivation likelihood estimation\nfMRI\nhuman brain mapping\nmagnetic resonance imaging\n\n# Abstract\nSpatial normalization--applying standardized coordinates as anatomical addresses within a reference space--was introduced to human neuroimaging research nearly 30 years ago. Over these three decades, an impressive series of methodological advances have adopted, extended, and popularized this standard. Collectively, this work has generated a methodologically coherent literature of unprecedented rigor, size, and scope. Large-scale online databases have compiled these observations and their associated meta-data, stimulating the development of meta-analytic methods to exploit this expanding corpus. Coordinate-based meta-analytic methods have emerged and evolved in rigor and utility. Early methods computed cross-study consensus, in a manner roughly comparable to traditional (nonimaging) meta-analysis. Recent advances now compute coactivation-based connectivity, connectivity-based functional parcellation, and complex network models powered from data sets representing tens of thousands of subjects. Meta-analyses of human neuroimaging data in large-scale databases now stand at the forefront of computational neurobiology. ", "metadata": {"id": 25032500, "text_md5": "1b3af4c8ca215fa7fa00b5fbdbb6cb0a", "field_positions": {"authors": [0, 76], "journal": [77, 94], "publication_year": [96, 100], "title": [111, 196], "keywords": [210, 302], "abstract": [315, 1446], "body": [1455, 1455]}, "batch": 1, "pmid": 25032500, "doi": "10.1146/annurev-neuro-062012-170320", "pmid_url": "https://pubmed.ncbi.nlm.nih.gov/25032500/", "efetch_url": "https://eutils.ncbi.nlm.nih.gov/entrez/eutils/efetch.fcgi?db=pubmed&id=25032500"}, "display_title": "pmid: <a href=\"https://pubmed.ncbi.nlm.nih.gov/25032500/\">25032500</a>", "list_title": "PMID25032500  Meta-analysis in human neuroimaging: computational modeling of large-scale databases."}
{"text": "Fox, Peter T and Lancaster, Jack L and Laird, Angela R and Eickhoff, Simon B\nAnnual review of neuroscience, 2015\n\n# Title\n\nMeta-analysis in human neuroimaging: computational modeling of large-scale databases.\n\n# Keywords\n\nALE \nMRI \nactivation likelihood estimation \nfMRI \nhuman brain mapping \nmagnetic resonance imaging \n\n\n# Abstract\n\nSpatial normalization--applying standardized coordinates as anatomical addresses within a reference space--was introduced to human neuroimaging research nearly 30 years ago. Over these three decades, an impressive series of methodological advances have adopted, extended, and popularized this standard. Collectively, this work has generated a methodologically coherent literature of unprecedented rigor, size, and scope. Large-scale online databases have compiled these observations and their associated meta-data, stimulating the development of meta-analytic methods to exploit this expanding corpus. Coordinate-based meta-analytic methods have emerged and evolved in rigor and utility. Early methods computed cross-study consensus, in a manner roughly comparable to traditional (nonimaging) meta-analysis. Recent advances now compute coactivation-based connectivity, connectivity-based functional parcellation, and complex network models powered from data sets representing tens of thousands of subjects. Meta-analyses of human neuroimaging data in large-scale databases now stand at the forefront of computational neurobiology. \n", "metadata": {"pmid": "25032500", "journal": "Annual review of neuroscience", "publication_year": "2015", "title": "Meta-analysis in human neuroimaging: computational modeling of large-scale databases.", "keywords": "ALE \nMRI \nactivation likelihood estimation \nfMRI \nhuman brain mapping \nmagnetic resonance imaging \n", "abstract": "Spatial normalization--applying standardized coordinates as anatomical addresses within a reference space--was introduced to human neuroimaging research nearly 30 years ago. Over these three decades, an impressive series of methodological advances have adopted, extended, and popularized this standard. Collectively, this work has generated a methodologically coherent literature of unprecedented rigor, size, and scope. Large-scale online databases have compiled these observations and their associated meta-data, stimulating the development of meta-analytic methods to exploit this expanding corpus. Coordinate-based meta-analytic methods have emerged and evolved in rigor and utility. Early methods computed cross-study consensus, in a manner roughly comparable to traditional (nonimaging) meta-analysis. Recent advances now compute coactivation-based connectivity, connectivity-based functional parcellation, and complex network models powered from data sets representing tens of thousands of subjects. Meta-analyses of human neuroimaging data in large-scale databases now stand at the forefront of computational neurobiology. ", "authors": "Fox, Peter T and Lancaster, Jack L and Laird, Angela R and Eickhoff, Simon B"}, "display_title": "pmid: <a href=\"https://pubmed.ncbi.nlm.nih.gov/25032500\">25032500</a>", "list_title": "PMID25032500 Meta-analysis in human neuroimaging: computational modeling of large-scale databases."}
