{"text": "Bosulu, Juvenal and Allaire, Max-Antoine and Tremblay-Gr\u00e9nier, Laurence and Luo, Yi and Eickhoff, Simon and H\u00e9tu, S\u00e9bastien\nBrain Behav, 2022\n\n# Title\n\n\"Wanting\" versus \"needing\" related value: An fMRI meta-analysis.\n\n# Keywords\n\nconsumption\nfMRI\nmotivation\nneeding\nwanting\n\n# Abstract\nConsumption and its excesses are sometimes explained by imbalance of need or lack of control over \"wanting.\" \"Wanting\" assigns value to cues that predict rewards, whereas \"needing\" assigns value to biologically significant stimuli that one is deprived of. Here we aimed at studying how the brain activation patterns related to value of \"wanted\" stimuli differs from that of \"needed\" stimuli using activation likelihood estimation neuroimaging meta-analysis approaches. We used the perception of a cue predicting a reward for \"wanting\" related value and the perception of food stimuli in a hungry state as a model for \"needing\" related value. We carried out separate, contrasts, and conjunction meta-analyses to identify differences and similarities between \"wanting\" and \"needing\" values. Our overall results for \"wanting\" related value show consistent activation of the ventral tegmental area, striatum, and pallidum, regions that both activate behavior and direct choice, while for \"needing\" related value, we found an overall consistent activation of the middle insula and to some extent the caudal-ventral putamen, regions that only direct choice. Our study suggests that wanting has more control on consumption and behavioral activation. ", "metadata": {"id": 36000558, "text_md5": "145b950607d444751b2925674d461725", "field_positions": {"authors": [0, 123], "journal": [124, 135], "publication_year": [137, 141], "title": [152, 216], "keywords": [230, 273], "abstract": [286, 1529], "body": [1538, 1538]}, "batch": 4, "pmid": 36000558, "doi": "10.1002/brb3.2713", "pmid_url": "https://pubmed.ncbi.nlm.nih.gov/36000558/", "efetch_url": "https://eutils.ncbi.nlm.nih.gov/entrez/eutils/efetch.fcgi?db=pubmed&id=36000558"}, "display_title": "pmid: <a href=\"https://pubmed.ncbi.nlm.nih.gov/36000558/\">36000558</a>", "list_title": "PMID36000558  \"Wanting\" versus \"needing\" related value: An fMRI meta-analysis."}
{"text": "Bosulu, Juvenal and Allaire, Max-Antoine and Tremblay-Gr\u00e9nier, Laurence and Luo, Yi and Eickhoff, Simon and H\u00e9tu, S\u00e9bastien\nBrain and behavior, 2022\n\n# Title\n\n\"Wanting\" versus \"needing\" related value: An fMRI meta-analysis.\n\n# Keywords\n\nconsumption \nfMRI \nmotivation \nneeding \nwanting \n\n\n# Abstract\n\nConsumption and its excesses are sometimes explained by imbalance of need or lack of control over \"wanting.\" \"Wanting\" assigns value to cues that predict rewards, whereas \"needing\" assigns value to biologically significant stimuli that one is deprived of. Here we aimed at studying how the brain activation patterns related to value of \"wanted\" stimuli differs from that of \"needed\" stimuli using activation likelihood estimation neuroimaging meta-analysis approaches. We used the perception of a cue predicting a reward for \"wanting\" related value and the perception of food stimuli in a hungry state as a model for \"needing\" related value. We carried out separate, contrasts, and conjunction meta-analyses to identify differences and similarities between \"wanting\" and \"needing\" values. Our overall results for \"wanting\" related value show consistent activation of the ventral tegmental area, striatum, and pallidum, regions that both activate behavior and direct choice, while for \"needing\" related value, we found an overall consistent activation of the middle insula and to some extent the caudal-ventral putamen, regions that only direct choice. Our study suggests that wanting has more control on consumption and behavioral activation. \n", "metadata": {"pmid": "36000558", "journal": "Brain and behavior", "publication_year": "2022", "title": "\"Wanting\" versus \"needing\" related value: An fMRI meta-analysis.", "keywords": "consumption \nfMRI \nmotivation \nneeding \nwanting \n", "abstract": "Consumption and its excesses are sometimes explained by imbalance of need or lack of control over \"wanting.\" \"Wanting\" assigns value to cues that predict rewards, whereas \"needing\" assigns value to biologically significant stimuli that one is deprived of. Here we aimed at studying how the brain activation patterns related to value of \"wanted\" stimuli differs from that of \"needed\" stimuli using activation likelihood estimation neuroimaging meta-analysis approaches. We used the perception of a cue predicting a reward for \"wanting\" related value and the perception of food stimuli in a hungry state as a model for \"needing\" related value. We carried out separate, contrasts, and conjunction meta-analyses to identify differences and similarities between \"wanting\" and \"needing\" values. Our overall results for \"wanting\" related value show consistent activation of the ventral tegmental area, striatum, and pallidum, regions that both activate behavior and direct choice, while for \"needing\" related value, we found an overall consistent activation of the middle insula and to some extent the caudal-ventral putamen, regions that only direct choice. Our study suggests that wanting has more control on consumption and behavioral activation. ", "authors": "Bosulu, Juvenal and Allaire, Max-Antoine and Tremblay-Gr\u00e9nier, Laurence and Luo, Yi and Eickhoff, Simon and H\u00e9tu, S\u00e9bastien"}, "display_title": "pmid: <a href=\"https://pubmed.ncbi.nlm.nih.gov/36000558\">36000558</a>", "list_title": "PMID36000558 \"Wanting\" versus \"needing\" related value: An fMRI meta-analysis."}
